Workbook

Sheet Cover Page

Sheet Data Log
B2: Data Log
B4: # | C4: Variable | D4: Unit | E4: Value | F4: Source | G4: Frequency | H4: Geography | I4: Date | J4: Used In Model | K4: Note
B6: 1 | C6: Electricity Price Data
C8: Day-ahead market prices | D8: EUR/MWh | E8: — | F8: ENTSO-E Transparency Platform, 2025 | G8: Hourly | H8: DK1/DK2 | I8: 01/01/2019 - 31/12/2025 | J8: OU Calibration, Monte Carlo Simulation
B10: 2 | C10: Solar and Consumption Data - Capture Price Inputs
C12: Solar Power Production over 40 kW | D12: MWh | E12: — | F12: Energy Data Service (Energinet.dk), 2025 | G12: Hourly | H12: DK1/DK2 | I12: 01/01/2019 - 31/12/2025 | J12: Cannibalisation regression α(t)
C13: Power Gross Consumption MWh | D13: MWh | E13: — | F13: Energy Data Service (Energinet.dk), 2025 | G13: Hourly | H13: DK1/DK2 | I13: 01/01/2019 - 31/12/2025 | J13: Cannibalisation regression α(t)
B15: 3 | C15: Derived Cannibalisation Variables - Capture Price Inputs & Calibration
C17: Solar penetration proxy | D17: % | E17: Derived | F17: Energy Data Service (Energinet.dk), 2025 | G17: Monthly | H17: DK1/DK2 | I17: 01/01/2019 - 31/12/2025 | J17: Cannibalisation regression α(t): independent variable (X) for estimating α(t) | K17: Solar Penetration Proxy = Solar Production MWh / Gross Consumption MWh
C18: Capture Prices | D18: EUR/MWh | E18: Derived | F18: Energy Data Service (Energinet.dk), 2025 | G18: Monthly | H18: DK1/DK2 | I18: 01/01/2019 - 31/12/2025 | J18: Cannibalisation regression α(t): used to calculate CPR | K18: Σ(Price × Solar Production) / Σ(Solar Production)
C19: Capture Price Ratio (CPR) | D19: Ratio | E19: Derived | F19: Energy Data Service (Energinet.dk), 2025 | G19: Monthly | H19: DK1/DK2 | I19: 01/01/2019 - 31/12/2025 | J19: Cannibalisation regression α(t): dependent variable (Y) for estimating α(t) | K19: Capture Price / Spot Price
B21: 4 | C21: Financial Input - Assumptions & WACC
C23: Risk-free rate (Rf) | D23: % | E23: 0.0225 | F23: Danmarks Nationalbank, 2025 | G23: Point estimate | H23: Denmark | I23: 2026 | J23: PPA WACC, Merchant WACC | K23: 2.25% Danske Stat 2035
C24: Equity Risk Premium (ERP) | D24: % | E24: 0.0423 | F24: Damodaran: Country Risk Premiums (Denmark, Aaa), 2026 | G24: Annual | H24: Denmark | I24: 2026 | J24: PPA WACC, Merchant WACC
C26: β_PPA (unlevered) | D26: — | E26: 0.46 | F26: Damodaran: Power sector, Global Betas by Sector, 2026 | G26: Annual | H26: Global | I26: 2026 | J26: PPA WACC
C27: β_merchant (unlevered) | D27: — | E27: 0.57 | F27: Damodaran: Green & Renewable Energy, Global Betas, 2026 | G27: Annual | H27: Global | I27: 2026 | J27: Merchant WACC
C29: Debt margin (PPA phase) | D29: % spread | E29: 0.0175 | F29: Gatti, 2019; IRENA, The Cost of Financing for Renewable Power, 2023 | G29: Point estimate | H29: Europe | I29: 2023 | J29: r_d,PPA for WACC_PPA | K29: Debt margins represent midpoints of indicative ranges for European contracted (150-200 bps) and merchant-exposed (300-350 bps) renewable project finance, consistent with Gatti (2019) and IRENA (2023)
C30: Debt margin (Merchant phase) | D30: % spread | E30: 0.0325 | F30: Gatti, 2019; IRENA, The Cost of Financing for Renewable Power, 2023 | G30: Point estimate | H30: Europe | I30: 2023 | J30: r_d,merchant for WACC_merchant | K30: Debt margins represent midpoints of indicative ranges for European contracted (150-200 bps) and merchant-exposed (300-350 bps) renewable project finance, consistent with Gatti (2019) and IRENA (2023)
C32: Equity Share (PPA phase) | D32: % | E32: 0.25 | F32: Gatti, 2019; Steffen, 2020 | G32: Point estimate | H32: Europe | I32: 2020 | J32: WACC_PPA (equity weight) | K32: 25% equity PPA consistent with 70-80% debt standard for contracted renewables (Gatti, 2019); 45% equity merchant reflects reduced debt capacity under unhedged exposure (Steffen, 2020)
C33: Equity Share (Merchant phase) | D33: % | E33: 0.45 | F33: Gatti, 2019; Steffen, 2020 | G33: Point estimate | H33: Europe | I33: 2020 | J33: WACC_merchant (equity weight) | K33: 25% equity PPA consistent with 70-80% debt standard for contracted renewables (Gatti, 2019); 45% equity merchant reflects reduced debt capacity under unhedged exposure (Steffen, 2020)
C35: Corporate tax rate (τ) | D35: % | E35: 0.22 | F35: Damodaran Country Risk Premiums, 2026; Skattestyrelsen, 2025 | G35: Point estimate | H35: Denmark | I35: 2026 | J35: WACC, FCFF model
B37: 5 | C37: Technical and Commercial Input - Assumptions
C39: CAPEX | D39: USD/kW | E39: 500 | F39: IRENA, Renewable Power Generation Costs, 2024 | G39: Annual | H39: Europe | I39: 2024 | J39: FCFF model | K39: EUR/USD conversion at time of modelling required
C40: OPEX | D40: USD/kW/year | E40: 9 | F40: Wood Mackenzie, Europe LCOE Report, 2024 | G40: Annual | H40: Europe | I40: 2024 | J40: FCFF model
C41: OPEX Escalation | D41: % | E41: 0.02 | F41: European Central Bank, 2025 | I41: 2025 | J41: FCFF model | K41: European Central Bank, ECB inflation target 2%, consistent with Danish long-run inflation expectations
C43: PPA benchmark price | D43: EUR/MWh | E43: 45 | F43: Pexapark, 2025; LevelTen Energy Q3, 2025; KYOS, 2025; DK1 solar PPA reference price, March 2025 | G43: Point estimate | H43: DK1 | I43: 2025 | J43: Revenue model (PPA phase)
C44: Project capacity | D44: MW | E44: 50 | F44: IEA, 2025; Energinet, 2025 | G44: Point estimate | H44: Denmark | I44: 2025 | J44: Revenue model | K44: Representative Danish utility-scale
C45: Project life | D45: Years | E45: 25 | F45: IEA, 2025 | G45: Point estimate | H45: Denmark | I45: 2025 | J45: All models | K45: Standard for solar PV
C46: PPA duration | D46: Years | E46: 10 | F46: Pexapark, 2024 | G46: Point estimate | H46: Denmark | I46: 2024 | J46: Switch date T* | K46: Typical bankable PPA tenor in Denmark
C48: Panel degradation rate | D48: % p.a. | E48: 0.005 | F48: IEA Renewables 2025; IRENA industry standard | G48: Point estimate | H48: Global | I48: 2025 | J48: Production profile
C49: Capacity factor | D49: % | E49: 0.13 | F49: Derived: EurObserv'ER, 2024 | G49: Point estimate | H49: Denmark | I49: 2024 | J49: Revenue model | K49: 3,363 GWh production, 3,529 MW capacity, 8,760 hours
C50: Technical availability | D50: % | E50: 0.97 | F50: IEA, 2025; IRENA, 2024 | G50: Point estimate | H50: Global | I50: 2025 | J50: Production profile | K50: Industry standard for utility-scale solar PV (consistent with IEA/IRENA O&M benchmarks)
C51: Curtailment | D51: % | E51: 0.03 | F51: IEA Renewables, 2025 | G51: Point estimate | H51: Global | I51: 2025 | J51: Production profile | K51: Global solar PV curtailment rate 2024 per IEA Renewables 2025; applied as conservative Danish base case
C52: AC:DC Ratio | D52: Ratio | E52: 1 | F52: IEA, 2025; IRENA, 2024 | G52: Point estimate | H52: Global | I52: 2024 | J52: Production profile | K52: AC:DC ratio of 1.0 implies no DC oversizing — conservative baseline
C54: End

Sheet Assumptions
B2: Assumptions
B4: # | C4: Variable | D4: Unit | E4: Value | G4: Note
B6: 1 | C6: Timeline
C8: Start of Development | D8: Date | E8: 46023
C9: Start of Construction | D9: Date | E9: 47484
C10: Commercial Operation Date | D10: Date | E10: 48214
C11: Operational Lifetime | D11: Months | E11: ='Data Log'!E45*12 | G11: Input from Data Log
B13: 2 | C13: Technicalities
C15: Installed Capacity | D15: MW(dc) | E15: =+'Data Log'!E44 | G15: Input from Data Log
C16: Power Production
C18: NCF, P50 | D18: % | E18: ='Data Log'!E49*(1-Assumptions!E22)*(1-Assumptions!E23)*E25 | G18: Derived: NCF = Capacity Factor * (1 − Curtailment) * (1 − Degradation) * Technical Availability
C19: NCF, P90 | D19: % | G19: Will be calculated using Monte Carlo simulation
C20: NCF, P99 | D20: % | G20: Will be calculated using Monte Carlo simulation
C22: Curtailment | D22: % | E22: =+'Data Log'!E51 | G22: Input from Data Log
C23: Degradation | D23: % p.a. | E23: =+'Data Log'!E48 | G23: Input from Data Log
C24: AC:DC Ratio | D24: Ratio | E24: =+'Data Log'!E52 | G24: Input from Data Log
C25: Technical Availability | D25: % | E25: =+'Data Log'!E50 | G25: Input from Data Log
B27: 3 | C27: Project Costs
C29: Construction Costs
C31: CAPEX | D31: EURk | E31: ='Data Log'!E39*0.92*E15 | G31: Input from Data Log
C33: Operational Costs
C35: O&M | D35: EURk | E35: =+'Data Log'!E40*E15*0.92 | G35: Input from Data Log
C36: OPEX Escalation | D36: % p.a. | E36: =+'Data Log'!E41 | G36: Input from Data Log
B38: 4 | C38: Revenue
C40: PPA | D40: EUR/MWh | E40: =+'Data Log'!E43 | G40: Input from Data Log
C41: PPA Tenor | D41: Years | E41: =+'Data Log'!E46 | G41: Input from Data Log
C43: Merchant Price | D43: EUR/MWh | G43: Will be calculated using Monte Carlo simulation
B45: 5 | C45: Taxes
C47: Corporate Tax Rate | D47: % | E47: =+'Data Log'!E35
C49: End

Sheet WACC
B2: WACC
B4: # | C4: Parameter | D4: Unit | E4: Value | G4: Formula / Note
B6: 1 | C6: Macroeconomic Inputs
C8: Risk-free rate (Rf) | D8: % | E8: =+'Data Log'!E23 | G8: Input from Data Log
C9: Equity Risk Premium (ERP) | D9: % | E9: =+'Data Log'!E24 | G9: Input from Data Log
C10: Corporate tax rate (τ) | D10: % | E10: =+'Data Log'!E35 | G10: Input from Data Log
B12: 2 | C12: PPA Phase - Cost of Capital
C14: β_PPA (unlevered asset beta) | D14: — | E14: =+'Data Log'!E26 | G14: Input from Data Log
C15: Equity share — PPA (E/V) | D15: % | E15: =+'Data Log'!E32 | G15: Input from Data Log
C16: Debt share — PPA (D/V) | D16: % | E16: =1-E15 | G16: Derived: 1 - Equity Share - PPA (E/V)
C17: Debt margin — PPA | D17: % | E17: =+'Data Log'!E29 | G17: Input from Data Log
C18: r_e,PPA (cost of equity) | D18: % | E18: =E8+E14*E9 | G18: Derived: CAPM: Rf + β_PPA × ERP
C19: r_d,PPA (cost of debt) | D19: % | E19: =E8+E17 | G19: Derived: Rf + debt margin PPA
C20: WACC_PPA | D20: % | E20: =E15*E18+E16*E19*(1-E10) | G20: Derived: WACC_PPA = (E_PPA/V_PPA) · r_e,PPA + (D_PPA/V_PPA) · r_d,PPA · (1 − τ)
B22: 3 | C22: Merchant Phase - Cost of Capital
C24: β_merchant (unlevered asset beta) | D24: — | E24: =+'Data Log'!E27 | G24: Input from Data Log
C25: Equity share — Merchant (E/V) | D25: % | E25: =+'Data Log'!E33 | G25: Input from Data Log
C26: Debt share — Merchant (D/V) | D26: % | E26: =1-E25 | G26: Derived: 1 - Equity Share - Merchant (E/V)
C27: Debt margin — Merchant | D27: % | E27: =+'Data Log'!E30 | G27: Input from Data Log
C28: r_e,merchant (cost of equity) | D28: % | E28: =E8+E24*E9 | G28: Derived: CAPM: Rf + β_merchant × ERP
C29: r_d,merchant (cost of debt) | D29: % | E29: =E8+E27 | G29: Derived: Rf + debt margin merchant
C30: WACC_merchant | D30: % | E30: =E25*E28+E26*E29*(1-E10) | G30: Derived: WACC_merchant = (E_merchant/V_merchant) · r_e,merchant + (D_merchant/V_merchant) · r_d,merchant · (1 − τ)
B32: 4 | C32: Monthly Discount Rates
C34: WACC_PPA,m (monthly) | D34: % | E34: =(1+E20)^(1/12)-1 | G34: Derived (Converted for monthly cash flow model)
C35: WACC_merchant,m (monthly) | D35: % | E35: =(1+E30)^(1/12)-1 | G35: Derived (Converted for monthly cash flow model)
B37: 5 | C37: Beta Shift Summary
C39: Δβ (beta shift) | D39: — | E39: =E24-E14 | G39: β_merchant (unlevered asset beta) - β_PPA (unlevered asset beta)
C40: ΔWACC (discount rate shift) | D40: % | E40: =E30-E20 | G40: WACC_merchant - WACC_PPA
C42: Three-channel WACC differentiation: | G42: 1) r_e rises via beta shift
G43: 2) r_d rises via higher credit spread
G44: 3) D/V falls via reduced debt capacity
C46: End

Sheet Electricity Price Data
A1: Month | B1: DK1 Spot Price (EUR/MWh) — Primary | C1: DK2 Spot Price (EUR/MWh) — Robustness | D1: DK1 Seasonal Component (EUR/MWh) | E1: DK1 De-seasonalised Price (EUR/MWh) | F1: DK2 Seasonal Component (EUR/MWh) | G1: DK2 De-seasonalised Price (EUR/MWh)
A2: 2019-01 | B2: 50.295645 | C2: 51.655027 | D2: 75.530384 | E2: -25.234739 | F2: 74.231822 | G2: -22.576795
A3: 2019-02 | B3: 42.813958 | C3: 43.932946 | D3: 72.914187 | E3: -30.100228 | F3: 70.12802 | G3: -26.195074
A4: 2019-03 | B4: 33.608259 | C4: 35.667355 | D4: 82.507618 | E4: -48.899359 | F4: 80.579396 | G4: -44.912041
A5: 2019-04 | B5: 39.068417 | C5: 39.892097 | D5: 70.829002 | E5: -31.760585 | F5: 68.268173 | G5: -28.376075
A6: 2019-05 | B6: 37.429516 | C6: 38.151398 | D6: 68.052166 | E6: -30.62265 | F6: 66.059996 | G6: -27.908598
A7: 2019-06 | B7: 32.879222 | C7: 33.622236 | D7: 80.334095 | E7: -47.454873 | F7: 80.703994 | G7: -47.081758
A8: 2019-07 | B8: 38.817312 | C8: 39.000175 | D8: 89.731125 | E8: -50.913813 | F8: 83.978132 | G8: -44.977957
A9: 2019-08 | B9: 37.865699 | C9: 39.493172 | D9: 120.61983 | E9: -82.754126 | F9: 121.25327 | G9: -81.760094
A10: 2019-09 | B10: 35.378861 | C10: 37.321347 | D10: 110.13558 | E10: -74.756714 | F10: 109.81753 | G10: -72.496187
A11: 2019-10 | B11: 38.347402 | C11: 41.599354 | D11: 76.225889 | E11: -37.878486 | F11: 75.426141 | G11: -33.826787
A12: 2019-11 | B12: 41.745069 | C12: 42.696444 | D12: 89.133429 | E12: -47.38836 | F12: 90.04428 | G12: -47.347836
A13: 2019-12 | B13: 34.041976 | C13: 35.34711 | D13: 107.33221 | E13: -73.290233 | F13: 108.60634 | G13: -73.259228
... A85: 2025-12 | B85: 82.437466 | C85: 82.081529 | D85: 107.33221 | E85: -24.894743 | F85: 108.60634 | G85: -26.524809

Sheet Capture Price Inputs
A1: Month | B1: DK1 Solar Production (MWh) — Primary | C1: DK2 Solar Production (MWh) — Robustness | D1: DK1 Gross Consumption (MWh) | E1: DK2 Gross Consumption (MWh) | F1: DK1 Solar Penetration (%) — Primary | G1: DK2 Solar Penetration (%) — Robustness | H1: DK1 Capture Price (EUR/MWh) — Primary | I1: DK2 Capture Price (EUR/MWh) — Robustness | J1: DK1 CPR — Primary | K1: DK2 CPR — Robustness
A2: 2019-01 | B2: 0 | C2: 0 | D2: 1981398.6 | E2: 1314033.1
A3: 2019-02 | B3: 0 | C3: 0 | D3: 1722773.8 | E3: 1131046.6
A4: 2019-03 | B4: 0 | C4: 0 | D4: 1852201.6 | E4: 1198126.6
A5: 2019-04 | B5: 0 | C5: 0 | D5: 1635794.5 | E5: 1043346.8
A6: 2019-05 | B6: 0 | C6: 0 | D6: 1705809.8 | E6: 1053002.4
A7: 2019-06 | B7: 0 | C7: 0 | D7: 1584045.4 | E7: 975899.2
A8: 2019-07 | B8: 0 | C8: 0 | D8: 1586666.8 | E8: 974240.52
A9: 2019-08 | B9: 0 | C9: 0 | D9: 1656328 | E9: 1032294
A10: 2019-09 | B10: 0 | C10: 0 | D10: 1676866.1 | E10: 1027039.5
A11: 2019-10 | B11: 0 | C11: 0 | D11: 1811180.1 | E11: 1150263.6
A12: 2019-11 | B12: 0 | C12: 0 | D12: 1863227.8 | E12: 1178952.8
A13: 2019-12 | B13: 0 | C13: 0 | D13: 1899232.9 | E13: 1242107.4
A14: 2020-01 | B14: 4471 | C14: 2331 | D14: 1974432.7 | E14: 1250319.8 | F14: 0.0022644479 | G14: 0.001864323 | H14: 25.22321 | I14: 29.862136 | J14: 1.0091487 | K14: 1.0904463
A15: 2020-02 | B15: 10110 | C15: 5861 | D15: 1926649.3 | E15: 1181334.2 | F15: 0.005247452 | G15: 0.0049613393 | H15: 22.835819 | I15: 23.555518 | J15: 1.2985912 | K15: 1.2518213
A16: 2020-03 | B16: 38892 | C16: 18129 | D16: 1925186.6 | E16: 1183329.3 | F16: 0.020201678 | G16: 0.015320333 | H16: 15.941073 | I16: 17.149051 | J16: 0.87101469 | K16: 0.85520776
A17: 2020-04 | B17: 55159 | C17: 26915 | D17: 1700968.8 | E17: 1028051.5 | F17: 0.03242799 | G17: 0.026180595 | H17: 10.364876 | I17: 13.252523 | J17: 0.71315773 | K17: 0.76362024
A18: 2020-05 | B18: 61569 | C18: 33210 | D18: 1706453.7 | E18: 1030057.1 | F18: 0.036080087 | G18: 0.032240931 | H18: 15.478549 | I18: 18.594049 | J18: 0.96415577 | K18: 0.97636938
A19: 2020-06 | B19: 61474 | C19: 30998 | D19: 1643091.5 | E19: 1011294.2 | F19: 0.037413619 | G19: 0.030651812 | H19: 27.313308 | I19: 35.21078 | J19: 1.0394664 | K19: 1.180647
A20: 2020-07 | B20: 54854 | C20: 29317 | D20: 1613427.3 | E20: 977817.81 | F20: 0.033998434 | G20: 0.029982068 | H20: 24.831745 | I20: 26.450778 | J20: 1.0086182 | K20: 1.021791
A21: 2020-08 | B21: 59389 | C21: 28887 | D21: 1735264 | E21: 1030401.1 | F21: 0.034224763 | G21: 0.028034713 | H21: 33.876915 | I21: 44.113765 | J21: 0.98082264 | K21: 1.0779484
A22: 2020-09 | B22: 41721 | C22: 21825 | D22: 1714785.8 | E22: 1004072.5 | F22: 0.024330152 | G22: 0.021736479 | H22: 38.935979 | I22: 41.853048 | J22: 1.0104045 | K22: 1.0591891
A23: 2020-10 | B23: 21643 | C23: 12341 | D23: 1883574.4 | E23: 1113897.4 | F23: 0.011490388 | G23: 0.011079118 | H23: 31.927742 | I23: 33.600878 | J23: 1.2368022 | K23: 1.2475491
A24: 2020-11 | B24: 297 | C24: 128 | D24: 1952532.7 | E24: 1158936.2 | F24: 0.00015211013 | G24: 0.00011044612 | H24: 26.005993 | I24: 37.749766 | J24: 1.0947779 | K24: 1.0570804
A25: 2020-12 | B25: 31 | C25: 7 | D25: 2105390.9 | E25: 1242182.4 | F25: 1.4724107e-05 | G25: 5.6352434e-06 | H25: 34.795161 | I25: 44.191429 | J25: 1.0082302 | K25: 1.1256912
... A85: 2025-12 | B85: 32931.052 | C85: 13184.951 | D85: 2347966.7 | E85: 1453769.6 | F85: 0.014025349 | G85: 0.0090694912 | H85: 80.958034 | I85: 79.631228 | J85: 0.98205389 | K85: 0.97014796

Sheet Calibration
A1: ADF TEST RESULTS — DK1 PRIMARY | G1: Lags | H1: DK1 Full | I1: DK1 ex-2022 | J1: DK1 post-crisis | K1: CV 5%
A2: Sample | B2: Lags=0 | C2: Lags=1 | D2: Lags=2 | E2: Conclusion | G2: 0 | H2: -2.7049 | I2: -2.7732 | J2: -3.435 | K2: -2.89
A3: DK1 Full (2019-2025) | B3: -2.7049 | C3: -2.5651 | D3: -1.782 | E3: Weakly stationary | G3: 1 | H3: -2.5651 | I3: -2.3519 | J3: -3.4777 | K3: -2.89
A4: DK1 Full ex-2022 (primary) | B4: -2.7732 | C4: -2.3519 | D4: -1.8495 | E4: Stationary at 5% | G4: 2 | H4: -1.782 | I4: -1.8495 | J4: -2.6639 | K4: -2.89
A5: DK1 Post-crisis 2023-2025 | B5: -3.435 | C5: -3.4777 | D5: -2.6639 | E5: Stationary at 1% | G5: 3 | H5: -1.6911 | I5: -1.8987 | J5: -3.0968 | K5: -2.89
A6: DK2 Full ex-2022 (robustness) | B6: -3.1475 | C6: -2.5148 | D6: -1.8943 | E6: Robustness | G6: 4 | H6: -1.6501 | I6: -1.8872 | J6: -2.9904 | K6: -2.89
A7: Critical values: 1% = -3.51 | B7: 5% = -2.89 | C7: 10% = -2.58
A10: OU PARAMETER ESTIMATES
A11: Parameter | B11: DK1 ex-2022 (primary) | C11: DK1 post-crisis | D11: DK2 ex-2022 | E11: DK2 post-crisis
A12: Long-run mean (mu) EUR/MWh | B12: 68.2947 | C12: 77.6851 | D12: 67.3754 | E12: 77.2663
A13: Mean reversion (kappa) /month | B13: 0.1401 | C13: 0.5931 | D13: 0.1928 | E13: 0.7383
A14: Volatility (sigma) EUR/MWh | B14: 17.5069 | C14: 16.815 | D14: 19.3572 | E14: 18.0415
A15: Half-life (months) | B15: 4.95 | C15: 1.17 | D15: 3.59 | E15: 0.94
A16: Observations | B16: 72 | C16: 36 | D16: 72 | E16: 36
A19: SEASONAL COEFFICIENTS (OLS) — DK1 PRIMARY vs DK2 ROBUSTNESS
A20: Month | B20: DK1 Coefficient (EUR/MWh) | C20: DK2 Coefficient (EUR/MWh)
A21: Jan | B21: 75.53 | C21: 74.23
A22: Feb | B22: 72.91 | C22: 70.13
A23: Mar | B23: 82.51 | C23: 80.58
A24: Apr | B24: 70.83 | C24: 68.27
A25: May | B25: 68.05 | C25: 66.06
A26: Jun | B26: 80.33 | C26: 80.7
A27: Jul | B27: 89.73 | C27: 83.98
A28: Aug | B28: 120.62 | C28: 121.25
A29: Sep | B29: 110.14 | C29: 109.82
A30: Oct | B30: 76.23 | C30: 75.43
A31: Nov | B31: 89.13 | C31: 90.04
A32: Dec | B32: 107.33 | C32: 108.61
A35: CANNIBALISATION REGRESSION
A36: Parameter | B36: DK1 (primary) | C36: DK2 (robustness)
A37: Intercept (b0) | B37: 1.0513 | C37: 1.093
A38: Slope (b1) | B38: -2.0262 | C38: -4.3648
A39: R-squared | B39: 0.6658 | C39: 0.6409
A40: p-value (b1) | B40: 0 | C40: 0
A41: Sign check | B41: PASS | C41: PASS
A42: Observations | B42: 72 | C42: 72

Sheet Simulation
A1: Month | B1: Year | C1: mu_capture | D1: P50 | E1: P75 | F1: P90 | G1: P25 | H1: P10 | I1: P1 | K1: MC SIMULATION SUMMARY — DK1 PRIMARY
A2: 1 | B2: 0 | C2: 64.8799 | D2: 68.2947 | E2: 68.2947 | F2: 68.2947 | G2: 68.2947 | H2: 68.2947 | I2: 68.2947 | K2: Horizon | L2: P50 | M2: P90 | N2: P99 | O2: mu_capture
A3: 2 | B3: 0.0833 | C3: 64.8457 | D3: 67.8014 | E3: 78.8156 | F3: 88.792 | G3: 56.8474 | H3: 46.7156 | I3: 29.9044 | K3: Year 5 | L3: 62.42 | M3: 19.97 | N3: -14.85 | O3: 62.86
A4: 3 | B4: 0.1667 | C4: 64.8114 | D4: 67.716 | E4: 82.2192 | F4: 95.4219 | G4: 53.0994 | H4: 40.3735 | I4: 16.7822 | K4: Year 10 | L4: 60.67 | M4: 18.27 | N4: -17.66 | O4: 60.8
A5: 4 | B5: 0.25 | C5: 64.7771 | D5: 67.0428 | E5: 84.2939 | F5: 99.4051 | G5: 49.9277 | H5: 34.7439 | I5: 8.3993 | K5: Year 15 | L5: 58.52 | M5: 16.52 | N5: -15.45 | O5: 58.75
A6: 5 | B6: 0.3333 | C6: 64.7429 | D6: 66.6091 | E6: 85.5648 | F6: 101.8293 | G6: 48.1797 | H6: 31.6711 | I6: 1.8518 | K6: Year 20 | L6: 57.43 | M6: 14.71 | N6: -19.55 | O6: 56.69
A7: 6 | B7: 0.4167 | C7: 64.7086 | D7: 66.6004 | E7: 86.4228 | F7: 103.2061 | G7: 47.2189 | H7: 28.6783 | I7: -0.5872 | K7: Year 25 | L7: 54.79 | M7: 12.55 | N7: -22.5 | O7: 54.64
A8: 7 | B8: 0.5 | C8: 64.6744 | D8: 66.3599 | E8: 86.4675 | F8: 104.5352 | G8: 46.2468 | H8: 27.915 | I8: -3.1092
A9: 8 | B9: 0.5833 | C9: 64.6401 | D9: 66.1206 | E9: 86.9863 | F9: 105.3618 | G9: 45.8921 | H9: 26.7437 | I9: -3.7243 | K9: PARAMETERS USED (DK1 Primary)
A10: 9 | B10: 0.6667 | C10: 64.6058 | D10: 65.9305 | E10: 86.6401 | F10: 106.6822 | G10: 45.0162 | H10: 25.3956 | I10: -6.282 | K10: mu (EUR/MWh) | L10: 68.2947
A11: 10 | B11: 0.75 | C11: 64.5716 | D11: 65.7839 | E11: 87.5344 | F11: 106.2259 | G11: 44.5769 | H11: 24.3668 | I11: -7.1671 | K11: kappa (/month) | L11: 0.1401
A12: 11 | B12: 0.8333 | C12: 64.5373 | D12: 65.3835 | E12: 87.267 | F12: 106.8023 | G12: 43.8629 | H12: 25.1914 | I12: -9.9291 | K12: sigma (EUR/MWh) | L12: 17.5069
A13: 12 | B13: 0.9167 | C13: 64.503 | D13: 65.4964 | E13: 87.2853 | F13: 107.4839 | G13: 44.1724 | H13: 25.084 | I13: -10.277 | K13: N paths | L13: 10000
A14: 13 | B14: 1 | C14: 64.4688 | D14: 65.4259 | E14: 87.6909 | F14: 107.7007 | G14: 44.0839 | H14: 23.6892 | I14: -10.3538 | K14: Alpha(t=0) | L14: 5%
A15: 14 | B15: 1.0833 | C15: 64.4345 | D15: 65.3168 | E15: 87.2552 | F15: 107.1667 | G15: 43.4157 | H15: 23.858 | I15: -10.6224 | K15: Alpha(t=25) | L15: 20%
A16: 15 | B16: 1.1667 | C16: 64.4003 | D16: 65.3124 | E16: 87.5832 | F16: 106.9542 | G16: 43.4516 | H16: 23.8034 | I16: -11.7282
A17: 16 | B17: 1.25 | C17: 64.366 | D17: 65.4709 | E17: 86.9666 | F17: 107.1016 | G17: 43.0965 | H17: 23.6992 | I17: -10.7847
A18: 17 | B18: 1.3333 | C18: 64.3317 | D18: 65.0741 | E18: 87.4701 | F18: 106.7117 | G18: 43.264 | H18: 23.9804 | I18: -10.3581
A19: 18 | B19: 1.4167 | C19: 64.2975 | D19: 65.3845 | E19: 87.0495 | F19: 106.6975 | G19: 42.6962 | H19: 22.4691 | I19: -10.7838
A20: 19 | B20: 1.5 | C20: 64.2632 | D20: 65.3837 | E20: 87.492 | F20: 107.0715 | G20: 42.517 | H20: 22.1187 | I20: -10.436
A21: 20 | B21: 1.5833 | C21: 64.229 | D21: 64.921 | E21: 86.8609 | F21: 106.3661 | G21: 42.8854 | H21: 22.2167 | I21: -12.1113
A22: 21 | B22: 1.6667 | C22: 64.1947 | D22: 64.6719 | E22: 86.9376 | F22: 106.0552 | G22: 42.9933 | H22: 22.0319 | I22: -13.504
A23: 22 | B23: 1.75 | C23: 64.1604 | D23: 64.6659 | E23: 86.666 | F23: 106.5405 | G23: 42.2253 | H23: 22.427 | I23: -13.9411
A24: 23 | B24: 1.8333 | C24: 64.1262 | D24: 64.5806 | E24: 86.7883 | F24: 106.2385 | G24: 42.09 | H24: 21.8143 | I24: -13.6475
A25: 24 | B25: 1.9167 | C25: 64.0919 | D25: 64.753 | E25: 86.4153 | F25: 107.0212 | G25: 42.1765 | H25: 22.4859 | I25: -12.8962
A26: 25 | B26: 2 | C26: 64.0576 | D26: 64.5184 | E26: 86.7178 | F26: 106.5809 | G26: 42.3217 | H26: 21.6924 | I26: -12.7455
A27: 26 | B27: 2.0833 | C27: 64.0234 | D27: 63.9402 | E27: 86.4723 | F27: 106.9217 | G27: 41.9212 | H27: 21.8213 | I27: -14.4254
... A301: 300 | B301: 24.9167 | C301: 54.6357 | D301: 54.7877 | E301: 77.5664 | F301: 97.0165 | G301: 32.5956 | H301: 12.547 | I301: -22.496

Sheet FCFF Model
A1: FCFF Model — Monthly Cash Flow Waterfall | 50MW Danish Solar PV | DK1 Primary
A2: All formulas linked to Assumptions (E15/E16/E23/E31/E35/E36/E40/E47) and WACC (E34/E35) sheets. Merchant prices from Simulation sheet cols E/I/J rows 7-306. PPA months 1-120 | Merchant months 121-300.
C3: PPA | D3: PPA | E3: PPA | F3: PPA | G3: PPA | H3: PPA | I3: PPA | J3: PPA | K3: PPA | L3: PPA | M3: PPA | N3: PPA | O3: PPA | P3: PPA | Q3: PPA | R3: PPA | S3: PPA | T3: PPA | U3: PPA | V3: PPA | W3: PPA | X3: PPA | Y3: PPA | Z3: PPA | AA3: PPA | AB3: PPA | AC3: PPA | AD3: PPA | AE3: PPA | AF3: PPA | AG3: PPA | AH3: PPA | AI3: PPA | AJ3: PPA | AK3: PPA | AL3: PPA | AM3: PPA | AN3: PPA | AO3: PPA | AP3: PPA | AQ3: PPA | AR3: PPA | AS3: PPA | AT3: PPA | AU3: PPA | AV3: PPA | AW3: PPA | AX3: PPA | AY3: PPA | AZ3: PPA | BA3: PPA | BB3: PPA | BC3: PPA | BD3: PPA | BE3: PPA | BF3: PPA | BG3: PPA | BH3: PPA | BI3: PPA | BJ3: PPA | BK3: PPA | BL3: PPA | BM3: PPA | BN3: PPA | BO3: PPA | BP3: PPA | BQ3: PPA | BR3: PPA | BS3: PPA | BT3: PPA | BU3: PPA | BV3: PPA | BW3: PPA | BX3: PPA | BY3: PPA | BZ3: PPA | CA3: PPA | CB3: PPA | CC3: PPA | CD3: PPA | CE3: PPA | CF3: PPA | CG3: PPA | CH3: PPA | CI3: PPA | CJ3: PPA | CK3: PPA | CL3: PPA | CM3: PPA | CN3: PPA | CO3: PPA | CP3: PPA | CQ3: PPA | CR3: PPA | CS3: PPA | CT3: PPA | CU3: PPA | CV3: PPA | CW3: PPA | CX3: PPA | CY3: PPA | CZ3: PPA | DA3: PPA | DB3: PPA | DC3: PPA | DD3: PPA | DE3: PPA | DF3: PPA | DG3: PPA | DH3: PPA | DI3: PPA | DJ3: PPA | DK3: PPA | DL3: PPA | DM3: PPA | DN3: PPA | DO3: PPA | DP3: PPA | DQ3: PPA | DR3: PPA | DS3: Merchant | DT3: Merchant | DU3: Merchant | DV3: Merchant | DW3: Merchant | DX3: Merchant | DY3: Merchant | DZ3: Merchant | EA3: Merchant | EB3: Merchant | EC3: Merchant | ED3: Merchant | EE3: Merchant | EF3: Merchant | EG3: Merchant | EH3: Merchant | EI3: Merchant | EJ3: Merchant | EK3: Merchant | EL3: Merchant | EM3: Merchant | EN3: Merchant | EO3: Merchant | EP3: Merchant | EQ3: Merchant | ER3: Merchant | ES3: Merchant | ET3: Merchant | EU3: Merchant | EV3: Merchant | EW3: Merchant | EX3: Merchant | EY3: Merchant | EZ3: Merchant | FA3: Merchant | FB3: Merchant | FC3: Merchant | FD3: Merchant | FE3: Merchant | FF3: Merchant | FG3: Merchant | FH3: Merchant | FI3: Merchant | FJ3: Merchant | FK3: Merchant | FL3: Merchant | FM3: Merchant | FN3: Merchant | FO3: Merchant | FP3: Merchant | FQ3: Merchant | FR3: Merchant | FS3: Merchant | FT3: Merchant | FU3: Merchant | FV3: Merchant | FW3: Merchant | FX3: Merchant | FY3: Merchant | FZ3: Merchant | GA3: Merchant | GB3: Merchant | GC3: Merchant | GD3: Merchant | GE3: Merchant | GF3: Merchant | GG3: Merchant | GH3: Merchant | GI3: Merchant | GJ3: Merchant | GK3: Merchant | GL3: Merchant | GM3: Merchant | GN3: Merchant | GO3: Merchant | GP3: Merchant | GQ3: Merchant | GR3: Merchant | GS3: Merchant | GT3: Merchant | GU3: Merchant | GV3: Merchant | GW3: Merchant | GX3: Merchant | GY3: Merchant | GZ3: Merchant | HA3: Merchant | HB3: Merchant | HC3: Merchant | HD3: Merchant | HE3: Merchant | HF3: Merchant | HG3: Merchant | HH3: Merchant | HI3: Merchant | HJ3: Merchant | HK3: Merchant | HL3: Merchant | HM3: Merchant | HN3: Merchant | HO3: Merchant | HP3: Merchant | HQ3: Merchant | HR3: Merchant | HS3: Merchant | HT3: Merchant | HU3: Merchant | HV3: Merchant | HW3: Merchant | HX3: Merchant | HY3: Merchant | HZ3: Merchant | IA3: Merchant | IB3: Merchant | IC3: Merchant | ID3: Merchant | IE3: Merchant | IF3: Merchant | IG3: Merchant | IH3: Merchant | II3: Merchant | IJ3: Merchant | IK3: Merchant | IL3: Merchant | IM3: Merchant | IN3: Merchant | IO3: Merchant | IP3: Merchant | IQ3: Merchant | IR3: Merchant | IS3: Merchant | IT3: Merchant | IU3: Merchant | IV3: Merchant | IW3: Merchant | IX3: Merchant | IY3: Merchant | IZ3: Merchant | JA3: Merchant | JB3: Merchant | JC3: Merchant | JD3: Merchant | JE3: Merchant | JF3: Merchant | JG3: Merchant | JH3: Merchant | JI3: Merchant | JJ3: Merchant | JK3: Merchant | JL3: Merchant | JM3: Merchant | JN3: Merchant | JO3: Merchant | JP3: Merchant | JQ3: Merchant | JR3: Merchant | JS3: Merchant | JT3: Merchant | JU3: Merchant | JV3: Merchant | JW3: Merchant | JX3: Merchant | JY3: Merchant | JZ3: Merchant | KA3: Merchant | KB3: Merchant | KC3: Merchant | KD3: Merchant | KE3: Merchant | KF3: Merchant | KG3: Merchant | KH3: Merchant | KI3: Merchant | KJ3: Merchant | KK3: Merchant | KL3: Merchant | KM3: Merchant | KN3: Merchant | KO3: Merchant | KP3: Merchant
A4: Line Item | B4: Unit | C4: 1 | D4: 2 | E4: 3 | F4: 4 | G4: 5 | H4: 6 | I4: 7 | J4: 8 | K4: 9 | L4: 10 | M4: 11 | N4: 12 | O4: 13 | P4: 14 | Q4: 15 | R4: 16 | S4: 17 | T4: 18 | U4: 19 | V4: 20 | W4: 21 | X4: 22 | Y4: 23 | Z4: 24 | AA4: 25 | AB4: 26 | AC4: 27 | AD4: 28 | AE4: 29 | AF4: 30 | AG4: 31 | AH4: 32 | AI4: 33 | AJ4: 34 | AK4: 35 | AL4: 36 | AM4: 37 | AN4: 38 | AO4: 39 | AP4: 40 | AQ4: 41 | AR4: 42 | AS4: 43 | AT4: 44 | AU4: 45 | AV4: 46 | AW4: 47 | AX4: 48 | AY4: 49 | AZ4: 50 | BA4: 51 | BB4: 52 | BC4: 53 | BD4: 54 | BE4: 55 | BF4: 56 | BG4: 57 | BH4: 58 | BI4: 59 | BJ4: 60 | BK4: 61 | BL4: 62 | BM4: 63 | BN4: 64 | BO4: 65 | BP4: 66 | BQ4: 67 | BR4: 68 | BS4: 69 | BT4: 70 | BU4: 71 | BV4: 72 | BW4: 73 | BX4: 74 | BY4: 75 | BZ4: 76 | CA4: 77 | CB4: 78 | CC4: 79 | CD4: 80 | CE4: 81 | CF4: 82 | CG4: 83 | CH4: 84 | CI4: 85 | CJ4: 86 | CK4: 87 | CL4: 88 | CM4: 89 | CN4: 90 | CO4: 91 | CP4: 92 | CQ4: 93 | CR4: 94 | CS4: 95 | CT4: 96 | CU4: 97 | CV4: 98 | CW4: 99 | CX4: 100 | CY4: 101 | CZ4: 102 | DA4: 103 | DB4: 104 | DC4: 105 | DD4: 106 | DE4: 107 | DF4: 108 | DG4: 109 | DH4: 110 | DI4: 111 | DJ4: 112 | DK4: 113 | DL4: 114 | DM4: 115 | DN4: 116 | DO4: 117 | DP4: 118 | DQ4: 119 | DR4: 120 | DS4: 121 | DT4: 122 | DU4: 123 | DV4: 124 | DW4: 125 | DX4: 126 | DY4: 127 | DZ4: 128 | EA4: 129 | EB4: 130 | EC4: 131 | ED4: 132 | EE4: 133 | EF4: 134 | EG4: 135 | EH4: 136 | EI4: 137 | EJ4: 138 | EK4: 139 | EL4: 140 | EM4: 141 | EN4: 142 | EO4: 143 | EP4: 144 | EQ4: 145 | ER4: 146 | ES4: 147 | ET4: 148 | EU4: 149 | EV4: 150 | EW4: 151 | EX4: 152 | EY4: 153 | EZ4: 154 | FA4: 155 | FB4: 156 | FC4: 157 | FD4: 158 | FE4: 159 | FF4: 160 | FG4: 161 | FH4: 162 | FI4: 163 | FJ4: 164 | FK4: 165 | FL4: 166 | FM4: 167 | FN4: 168 | FO4: 169 | FP4: 170 | FQ4: 171 | FR4: 172 | FS4: 173 | FT4: 174 | FU4: 175 | FV4: 176 | FW4: 177 | FX4: 178 | FY4: 179 | FZ4: 180 | GA4: 181 | GB4: 182 | GC4: 183 | GD4: 184 | GE4: 185 | GF4: 186 | GG4: 187 | GH4: 188 | GI4: 189 | GJ4: 190 | GK4: 191 | GL4: 192 | GM4: 193 | GN4: 194 | GO4: 195 | GP4: 196 | GQ4: 197 | GR4: 198 | GS4: 199 | GT4: 200 | GU4: 201 | GV4: 202 | GW4: 203 | GX4: 204 | GY4: 205 | GZ4: 206 | HA4: 207 | HB4: 208 | HC4: 209 | HD4: 210 | HE4: 211 | HF4: 212 | HG4: 213 | HH4: 214 | HI4: 215 | HJ4: 216 | HK4: 217 | HL4: 218 | HM4: 219 | HN4: 220 | HO4: 221 | HP4: 222 | HQ4: 223 | HR4: 224 | HS4: 225 | HT4: 226 | HU4: 227 | HV4: 228 | HW4: 229 | HX4: 230 | HY4: 231 | HZ4: 232 | IA4: 233 | IB4: 234 | IC4: 235 | ID4: 236 | IE4: 237 | IF4: 238 | IG4: 239 | IH4: 240 | II4: 241 | IJ4: 242 | IK4: 243 | IL4: 244 | IM4: 245 | IN4: 246 | IO4: 247 | IP4: 248 | IQ4: 249 | IR4: 250 | IS4: 251 | IT4: 252 | IU4: 253 | IV4: 254 | IW4: 255 | IX4: 256 | IY4: 257 | IZ4: 258 | JA4: 259 | JB4: 260 | JC4: 261 | JD4: 262 | JE4: 263 | JF4: 264 | JG4: 265 | JH4: 266 | JI4: 267 | JJ4: 268 | JK4: 269 | JL4: 270 | JM4: 271 | JN4: 272 | JO4: 273 | JP4: 274 | JQ4: 275 | JR4: 276 | JS4: 277 | JT4: 278 | JU4: 279 | JV4: 280 | JW4: 281 | JX4: 282 | JY4: 283 | JZ4: 284 | KA4: 285 | KB4: 286 | KC4: 287 | KD4: 288 | KE4: 289 | KF4: 290 | KG4: 291 | KH4: 292 | KI4: 293 | KJ4: 294 | KK4: 295 | KL4: 296 | KM4: 297 | KN4: 298 | KO4: 299 | KP4: 300
A5: P50 — Base Case
A6: Production (MWh) | B6: MWh | C6: =Assumptions!$E$16*(1-Assumptions!$E$23)^0 | D6: =Assumptions!$E$16*(1-Assumptions!$E$23)^0 | E6: =Assumptions!$E$16*(1-Assumptions!$E$23)^0 | F6: =Assumptions!$E$16*(1-Assumptions!$E$23)^0 | G6: =Assumptions!$E$16*(1-Assumptions!$E$23)^0 | H6: =Assumptions!$E$16*(1-Assumptions!$E$23)^0 | I6: =Assumptions!$E$16*(1-Assumptions!$E$23)^0 | J6: =Assumptions!$E$16*(1-Assumptions!$E$23)^0 | ... N6: =Assumptions!$E$16*(1-Assumptions!$E$23)^0 | O6: =Assumptions!$E$16*(1-Assumptions!$E$23)^1 | P6: =Assumptions!$E$16*(1-Assumptions!$E$23)^1 | Q6: =Assumptions!$E$16*(1-Assumptions!$E$23)^1 | R6: =Assumptions!$E$16*(1-Assumptions!$E$23)^1 | S6: =Assumptions!$E$16*(1-Assumptions!$E$23)^1 | T6: =Assumptions!$E$16*(1-Assumptions!$E$23)^1 | U6: =Assumptions!$E$16*(1-Assumptions!$E$23)^1 | V6: =Assumptions!$E$16*(1-Assumptions!$E$23)^1 | ... Z6: =Assumptions!$E$16*(1-Assumptions!$E$23)^1 | AA6: =Assumptions!$E$16*(1-Assumptions!$E$23)^2 | AB6: =Assumptions!$E$16*(1-Assumptions!$E$23)^2 | AC6: =Assumptions!$E$16*(1-Assumptions!$E$23)^2 | AD6: =Assumptions!$E$16*(1-Assumptions!$E$23)^2 | AE6: =Assumptions!$E$16*(1-Assumptions!$E$23)^2 | AF6: =Assumptions!$E$16*(1-Assumptions!$E$23)^2 | AG6: =Assumptions!$E$16*(1-Assumptions!$E$23)^2 | AH6: =Assumptions!$E$16*(1-Assumptions!$E$23)^2 | ... AL6: =Assumptions!$E$16*(1-Assumptions!$E$23)^2 | AM6: =Assumptions!$E$16*(1-Assumptions!$E$23)^3 | AN6: =Assumptions!$E$16*(1-Assumptions!$E$23)^3 | AO6: =Assumptions!$E$16*(1-Assumptions!$E$23)^3 | AP6: =Assumptions!$E$16*(1-Assumptions!$E$23)^3 | AQ6: =Assumptions!$E$16*(1-Assumptions!$E$23)^3 | AR6: =Assumptions!$E$16*(1-Assumptions!$E$23)^3 | AS6: =Assumptions!$E$16*(1-Assumptions!$E$23)^3 | AT6: =Assumptions!$E$16*(1-Assumptions!$E$23)^3 | ... AX6: =Assumptions!$E$16*(1-Assumptions!$E$23)^3 | AY6: =Assumptions!$E$16*(1-Assumptions!$E$23)^4 | AZ6: =Assumptions!$E$16*(1-Assumptions!$E$23)^4 | BA6: =Assumptions!$E$16*(1-Assumptions!$E$23)^4 | BB6: =Assumptions!$E$16*(1-Assumptions!$E$23)^4 | BC6: =Assumptions!$E$16*(1-Assumptions!$E$23)^4 | BD6: =Assumptions!$E$16*(1-Assumptions!$E$23)^4 | BE6: =Assumptions!$E$16*(1-Assumptions!$E$23)^4 | BF6: =Assumptions!$E$16*(1-Assumptions!$E$23)^4 | ... BJ6: =Assumptions!$E$16*(1-Assumptions!$E$23)^4 | BK6: =Assumptions!$E$16*(1-Assumptions!$E$23)^5 | BL6: =Assumptions!$E$16*(1-Assumptions!$E$23)^5 | BM6: =Assumptions!$E$16*(1-Assumptions!$E$23)^5 | BN6: =Assumptions!$E$16*(1-Assumptions!$E$23)^5 | BO6: =Assumptions!$E$16*(1-Assumptions!$E$23)^5 | BP6: =Assumptions!$E$16*(1-Assumptions!$E$23)^5 | BQ6: =Assumptions!$E$16*(1-Assumptions!$E$23)^5 | BR6: =Assumptions!$E$16*(1-Assumptions!$E$23)^5 | ... BV6: =Assumptions!$E$16*(1-Assumptions!$E$23)^5 | BW6: =Assumptions!$E$16*(1-Assumptions!$E$23)^6 | BX6: =Assumptions!$E$16*(1-Assumptions!$E$23)^6 | BY6: =Assumptions!$E$16*(1-Assumptions!$E$23)^6 | BZ6: =Assumptions!$E$16*(1-Assumptions!$E$23)^6 | CA6: =Assumptions!$E$16*(1-Assumptions!$E$23)^6 | CB6: =Assumptions!$E$16*(1-Assumptions!$E$23)^6 | CC6: =Assumptions!$E$16*(1-Assumptions!$E$23)^6 | CD6: =Assumptions!$E$16*(1-Assumptions!$E$23)^6 | ... CH6: =Assumptions!$E$16*(1-Assumptions!$E$23)^6 | CI6: =Assumptions!$E$16*(1-Assumptions!$E$23)^7 | CJ6: =Assumptions!$E$16*(1-Assumptions!$E$23)^7 | CK6: =Assumptions!$E$16*(1-Assumptions!$E$23)^7 | CL6: =Assumptions!$E$16*(1-Assumptions!$E$23)^7 | CM6: =Assumptions!$E$16*(1-Assumptions!$E$23)^7 | CN6: =Assumptions!$E$16*(1-Assumptions!$E$23)^7 | CO6: =Assumptions!$E$16*(1-Assumptions!$E$23)^7 | CP6: =Assumptions!$E$16*(1-Assumptions!$E$23)^7 | ... CT6: =Assumptions!$E$16*(1-Assumptions!$E$23)^7 | CU6: =Assumptions!$E$16*(1-Assumptions!$E$23)^8 | CV6: =Assumptions!$E$16*(1-Assumptions!$E$23)^8 | CW6: =Assumptions!$E$16*(1-Assumptions!$E$23)^8 | CX6: =Assumptions!$E$16*(1-Assumptions!$E$23)^8 | CY6: =Assumptions!$E$16*(1-Assumptions!$E$23)^8 | CZ6: =Assumptions!$E$16*(1-Assumptions!$E$23)^8 | DA6: =Assumptions!$E$16*(1-Assumptions!$E$23)^8 | DB6: =Assumptions!$E$16*(1-Assumptions!$E$23)^8 | ... DF6: =Assumptions!$E$16*(1-Assumptions!$E$23)^8 | DG6: =Assumptions!$E$16*(1-Assumptions!$E$23)^9 | DH6: =Assumptions!$E$16*(1-Assumptions!$E$23)^9 | DI6: =Assumptions!$E$16*(1-Assumptions!$E$23)^9 | DJ6: =Assumptions!$E$16*(1-Assumptions!$E$23)^9 | DK6: =Assumptions!$E$16*(1-Assumptions!$E$23)^9 | DL6: =Assumptions!$E$16*(1-Assumptions!$E$23)^9 | DM6: =Assumptions!$E$16*(1-Assumptions!$E$23)^9 | DN6: =Assumptions!$E$16*(1-Assumptions!$E$23)^9 | ... DR6: =Assumptions!$E$16*(1-Assumptions!$E$23)^9 | DS6: =Assumptions!$E$16*(1-Assumptions!$E$23)^10 | DT6: =Assumptions!$E$16*(1-Assumptions!$E$23)^10 | DU6: =Assumptions!$E$16*(1-Assumptions!$E$23)^10 | DV6: =Assumptions!$E$16*(1-Assumptions!$E$23)^10 | DW6: =Assumptions!$E$16*(1-Assumptions!$E$23)^10 | DX6: =Assumptions!$E$16*(1-Assumptions!$E$23)^10 | DY6: =Assumptions!$E$16*(1-Assumptions!$E$23)^10 | DZ6: =Assumptions!$E$16*(1-Assumptions!$E$23)^10 | ... ED6: =Assumptions!$E$16*(1-Assumptions!$E$23)^10 | EE6: =Assumptions!$E$16*(1-Assumptions!$E$23)^11 | EF6: =Assumptions!$E$16*(1-Assumptions!$E$23)^11 | EG6: =Assumptions!$E$16*(1-Assumptions!$E$23)^11 | EH6: =Assumptions!$E$16*(1-Assumptions!$E$23)^11 | EI6: =Assumptions!$E$16*(1-Assumptions!$E$23)^11 | EJ6: =Assumptions!$E$16*(1-Assumptions!$E$23)^11 | EK6: =Assumptions!$E$16*(1-Assumptions!$E$23)^11 | EL6: =Assumptions!$E$16*(1-Assumptions!$E$23)^11 | ... EP6: =Assumptions!$E$16*(1-Assumptions!$E$23)^11 | EQ6: =Assumptions!$E$16*(1-Assumptions!$E$23)^12 | ER6: =Assumptions!$E$16*(1-Assumptions!$E$23)^12 | ES6: =Assumptions!$E$16*(1-Assumptions!$E$23)^12 | ET6: =Assumptions!$E$16*(1-Assumptions!$E$23)^12 | EU6: =Assumptions!$E$16*(1-Assumptions!$E$23)^12 | EV6: =Assumptions!$E$16*(1-Assumptions!$E$23)^12 | EW6: =Assumptions!$E$16*(1-Assumptions!$E$23)^12 | EX6: =Assumptions!$E$16*(1-Assumptions!$E$23)^12 | ... FB6: =Assumptions!$E$16*(1-Assumptions!$E$23)^12 | FC6: =Assumptions!$E$16*(1-Assumptions!$E$23)^13 | FD6: =Assumptions!$E$16*(1-Assumptions!$E$23)^13 | FE6: =Assumptions!$E$16*(1-Assumptions!$E$23)^13 | FF6: =Assumptions!$E$16*(1-Assumptions!$E$23)^13 | FG6: =Assumptions!$E$16*(1-Assumptions!$E$23)^13 | FH6: =Assumptions!$E$16*(1-Assumptions!$E$23)^13 | FI6: =Assumptions!$E$16*(1-Assumptions!$E$23)^13 | FJ6: =Assumptions!$E$16*(1-Assumptions!$E$23)^13 | ... FN6: =Assumptions!$E$16*(1-Assumptions!$E$23)^13 | FO6: =Assumptions!$E$16*(1-Assumptions!$E$23)^14 | FP6: =Assumptions!$E$16*(1-Assumptions!$E$23)^14 | FQ6: =Assumptions!$E$16*(1-Assumptions!$E$23)^14 | FR6: =Assumptions!$E$16*(1-Assumptions!$E$23)^14 | FS6: =Assumptions!$E$16*(1-Assumptions!$E$23)^14 | FT6: =Assumptions!$E$16*(1-Assumptions!$E$23)^14 | FU6: =Assumptions!$E$16*(1-Assumptions!$E$23)^14 | FV6: =Assumptions!$E$16*(1-Assumptions!$E$23)^14 | ... FZ6: =Assumptions!$E$16*(1-Assumptions!$E$23)^14 | GA6: =Assumptions!$E$16*(1-Assumptions!$E$23)^15 | GB6: =Assumptions!$E$16*(1-Assumptions!$E$23)^15 | GC6: =Assumptions!$E$16*(1-Assumptions!$E$23)^15 | GD6: =Assumptions!$E$16*(1-Assumptions!$E$23)^15 | GE6: =Assumptions!$E$16*(1-Assumptions!$E$23)^15 | GF6: =Assumptions!$E$16*(1-Assumptions!$E$23)^15 | GG6: =Assumptions!$E$16*(1-Assumptions!$E$23)^15 | GH6: =Assumptions!$E$16*(1-Assumptions!$E$23)^15 | ... GL6: =Assumptions!$E$16*(1-Assumptions!$E$23)^15 | GM6: =Assumptions!$E$16*(1-Assumptions!$E$23)^16 | GN6: =Assumptions!$E$16*(1-Assumptions!$E$23)^16 | GO6: =Assumptions!$E$16*(1-Assumptions!$E$23)^16 | GP6: =Assumptions!$E$16*(1-Assumptions!$E$23)^16 | GQ6: =Assumptions!$E$16*(1-Assumptions!$E$23)^16 | GR6: =Assumptions!$E$16*(1-Assumptions!$E$23)^16 | GS6: =Assumptions!$E$16*(1-Assumptions!$E$23)^16 | GT6: =Assumptions!$E$16*(1-Assumptions!$E$23)^16 | ... GX6: =Assumptions!$E$16*(1-Assumptions!$E$23)^16 | GY6: =Assumptions!$E$16*(1-Assumptions!$E$23)^17 | GZ6: =Assumptions!$E$16*(1-Assumptions!$E$23)^17 | HA6: =Assumptions!$E$16*(1-Assumptions!$E$23)^17 | HB6: =Assumptions!$E$16*(1-Assumptions!$E$23)^17 | HC6: =Assumptions!$E$16*(1-Assumptions!$E$23)^17 | HD6: =Assumptions!$E$16*(1-Assumptions!$E$23)^17 | HE6: =Assumptions!$E$16*(1-Assumptions!$E$23)^17 | HF6: =Assumptions!$E$16*(1-Assumptions!$E$23)^17 | ... HJ6: =Assumptions!$E$16*(1-Assumptions!$E$23)^17 | HK6: =Assumptions!$E$16*(1-Assumptions!$E$23)^18 | HL6: =Assumptions!$E$16*(1-Assumptions!$E$23)^18 | HM6: =Assumptions!$E$16*(1-Assumptions!$E$23)^18 | HN6: =Assumptions!$E$16*(1-Assumptions!$E$23)^18 | HO6: =Assumptions!$E$16*(1-Assumptions!$E$23)^18 | HP6: =Assumptions!$E$16*(1-Assumptions!$E$23)^18 | HQ6: =Assumptions!$E$16*(1-Assumptions!$E$23)^18 | HR6: =Assumptions!$E$16*(1-Assumptions!$E$23)^18 | ... HV6: =Assumptions!$E$16*(1-Assumptions!$E$23)^18 | HW6: =Assumptions!$E$16*(1-Assumptions!$E$23)^19 | HX6: =Assumptions!$E$16*(1-Assumptions!$E$23)^19 | HY6: =Assumptions!$E$16*(1-Assumptions!$E$23)^19 | HZ6: =Assumptions!$E$16*(1-Assumptions!$E$23)^19 | IA6: =Assumptions!$E$16*(1-Assumptions!$E$23)^19 | IB6: =Assumptions!$E$16*(1-Assumptions!$E$23)^19 | IC6: =Assumptions!$E$16*(1-Assumptions!$E$23)^19 | ID6: =Assumptions!$E$16*(1-Assumptions!$E$23)^19 | ... IH6: =Assumptions!$E$16*(1-Assumptions!$E$23)^19 | II6: =Assumptions!$E$16*(1-Assumptions!$E$23)^20 | IJ6: =Assumptions!$E$16*(1-Assumptions!$E$23)^20 | IK6: =Assumptions!$E$16*(1-Assumptions!$E$23)^20 | IL6: =Assumptions!$E$16*(1-Assumptions!$E$23)^20 | IM6: =Assumptions!$E$16*(1-Assumptions!$E$23)^20 | IN6: =Assumptions!$E$16*(1-Assumptions!$E$23)^20 | IO6: =Assumptions!$E$16*(1-Assumptions!$E$23)^20 | IP6: =Assumptions!$E$16*(1-Assumptions!$E$23)^20 | ... IT6: =Assumptions!$E$16*(1-Assumptions!$E$23)^20 | IU6: =Assumptions!$E$16*(1-Assumptions!$E$23)^21 | IV6: =Assumptions!$E$16*(1-Assumptions!$E$23)^21 | IW6: =Assumptions!$E$16*(1-Assumptions!$E$23)^21 | IX6: =Assumptions!$E$16*(1-Assumptions!$E$23)^21 | IY6: =Assumptions!$E$16*(1-Assumptions!$E$23)^21 | IZ6: =Assumptions!$E$16*(1-Assumptions!$E$23)^21 | JA6: =Assumptions!$E$16*(1-Assumptions!$E$23)^21 | JB6: =Assumptions!$E$16*(1-Assumptions!$E$23)^21 | ... JF6: =Assumptions!$E$16*(1-Assumptions!$E$23)^21 | JG6: =Assumptions!$E$16*(1-Assumptions!$E$23)^22 | JH6: =Assumptions!$E$16*(1-Assumptions!$E$23)^22 | JI6: =Assumptions!$E$16*(1-Assumptions!$E$23)^22 | JJ6: =Assumptions!$E$16*(1-Assumptions!$E$23)^22 | JK6: =Assumptions!$E$16*(1-Assumptions!$E$23)^22 | JL6: =Assumptions!$E$16*(1-Assumptions!$E$23)^22 | JM6: =Assumptions!$E$16*(1-Assumptions!$E$23)^22 | JN6: =Assumptions!$E$16*(1-Assumptions!$E$23)^22 | ... JR6: =Assumptions!$E$16*(1-Assumptions!$E$23)^22 | JS6: =Assumptions!$E$16*(1-Assumptions!$E$23)^23 | JT6: =Assumptions!$E$16*(1-Assumptions!$E$23)^23 | JU6: =Assumptions!$E$16*(1-Assumptions!$E$23)^23 | JV6: =Assumptions!$E$16*(1-Assumptions!$E$23)^23 | JW6: =Assumptions!$E$16*(1-Assumptions!$E$23)^23 | JX6: =Assumptions!$E$16*(1-Assumptions!$E$23)^23 | JY6: =Assumptions!$E$16*(1-Assumptions!$E$23)^23 | JZ6: =Assumptions!$E$16*(1-Assumptions!$E$23)^23 | ... KD6: =Assumptions!$E$16*(1-Assumptions!$E$23)^23 | KE6: =Assumptions!$E$16*(1-Assumptions!$E$23)^24 | KF6: =Assumptions!$E$16*(1-Assumptions!$E$23)^24 | KG6: =Assumptions!$E$16*(1-Assumptions!$E$23)^24 | KH6: =Assumptions!$E$16*(1-Assumptions!$E$23)^24 | KI6: =Assumptions!$E$16*(1-Assumptions!$E$23)^24 | KJ6: =Assumptions!$E$16*(1-Assumptions!$E$23)^24 | KK6: =Assumptions!$E$16*(1-Assumptions!$E$23)^24 | KL6: =Assumptions!$E$16*(1-Assumptions!$E$23)^24 | ... KP6: =Assumptions!$E$16*(1-Assumptions!$E$23)^24
A7: Price (EUR/MWh) | B7: EUR/MWh | C7: =Assumptions!$E$40 | D7: =Assumptions!$E$40 | E7: =Assumptions!$E$40 | F7: =Assumptions!$E$40 | G7: =Assumptions!$E$40 | H7: =Assumptions!$E$40 | I7: =Assumptions!$E$40 | J7: =Assumptions!$E$40 | ... DR7: =Assumptions!$E$40 | DS7: =Simulation!$E$127 | DT7: =Simulation!$E$128 | DU7: =Simulation!$E$129 | DV7: =Simulation!$E$130 | DW7: =Simulation!$E$131 | DX7: =Simulation!$E$132 | DY7: =Simulation!$E$133 | DZ7: =Simulation!$E$134 | EA7: =Simulation!$E$135 | EB7: =Simulation!$E$136 | EC7: =Simulation!$E$137 | ED7: =Simulation!$E$138 | EE7: =Simulation!$E$139 | EF7: =Simulation!$E$140 | EG7: =Simulation!$E$141 | EH7: =Simulation!$E$142 | EI7: =Simulation!$E$143 | EJ7: =Simulation!$E$144 | EK7: =Simulation!$E$145 | EL7: =Simulation!$E$146 | EM7: =Simulation!$E$147 | EN7: =Simulation!$E$148 | EO7: =Simulation!$E$149 | EP7: =Simulation!$E$150 | EQ7: =Simulation!$E$151 | ER7: =Simulation!$E$152 | ES7: =Simulation!$E$153 | ET7: =Simulation!$E$154 | EU7: =Simulation!$E$155 | EV7: =Simulation!$E$156 | EW7: =Simulation!$E$157 | EX7: =Simulation!$E$158 | EY7: =Simulation!$E$159 | EZ7: =Simulation!$E$160 | FA7: =Simulation!$E$161 | FB7: =Simulation!$E$162 | FC7: =Simulation!$E$163 | FD7: =Simulation!$E$164 | FE7: =Simulation!$E$165 | FF7: =Simulation!$E$166 | FG7: =Simulation!$E$167 | FH7: =Simulation!$E$168 | FI7: =Simulation!$E$169 | FJ7: =Simulation!$E$170 | FK7: =Simulation!$E$171 | FL7: =Simulation!$E$172 | FM7: =Simulation!$E$173 | FN7: =Simulation!$E$174 | FO7: =Simulation!$E$175 | FP7: =Simulation!$E$176 | FQ7: =Simulation!$E$177 | FR7: =Simulation!$E$178 | FS7: =Simulation!$E$179 | FT7: =Simulation!$E$180 | FU7: =Simulation!$E$181 | FV7: =Simulation!$E$182 | FW7: =Simulation!$E$183 | FX7: =Simulation!$E$184 | FY7: =Simulation!$E$185 | FZ7: =Simulation!$E$186 | GA7: =Simulation!$E$187 | GB7: =Simulation!$E$188 | GC7: =Simulation!$E$189 | GD7: =Simulation!$E$190 | GE7: =Simulation!$E$191 | GF7: =Simulation!$E$192 | GG7: =Simulation!$E$193 | GH7: =Simulation!$E$194 | GI7: =Simulation!$E$195 | GJ7: =Simulation!$E$196 | GK7: =Simulation!$E$197 | GL7: =Simulation!$E$198 | GM7: =Simulation!$E$199 | GN7: =Simulation!$E$200 | GO7: =Simulation!$E$201 | GP7: =Simulation!$E$202 | GQ7: =Simulation!$E$203 | GR7: =Simulation!$E$204 | GS7: =Simulation!$E$205 | GT7: =Simulation!$E$206 | GU7: =Simulation!$E$207 | GV7: =Simulation!$E$208 | GW7: =Simulation!$E$209 | GX7: =Simulation!$E$210 | GY7: =Simulation!$E$211 | GZ7: =Simulation!$E$212 | HA7: =Simulation!$E$213 | HB7: =Simulation!$E$214 | HC7: =Simulation!$E$215 | HD7: =Simulation!$E$216 | HE7: =Simulation!$E$217 | HF7: =Simulation!$E$218 | HG7: =Simulation!$E$219 | HH7: =Simulation!$E$220 | HI7: =Simulation!$E$221 | HJ7: =Simulation!$E$222 | HK7: =Simulation!$E$223 | HL7: =Simulation!$E$224 | HM7: =Simulation!$E$225 | HN7: =Simulation!$E$226 | HO7: =Simulation!$E$227 | HP7: =Simulation!$E$228 | HQ7: =Simulation!$E$229 | HR7: =Simulation!$E$230 | HS7: =Simulation!$E$231 | HT7: =Simulation!$E$232 | HU7: =Simulation!$E$233 | HV7: =Simulation!$E$234 | HW7: =Simulation!$E$235 | HX7: =Simulation!$E$236 | HY7: =Simulation!$E$237 | HZ7: =Simulation!$E$238 | IA7: =Simulation!$E$239 | IB7: =Simulation!$E$240 | IC7: =Simulation!$E$241 | ID7: =Simulation!$E$242 | IE7: =Simulation!$E$243 | IF7: =Simulation!$E$244 | IG7: =Simulation!$E$245 | IH7: =Simulation!$E$246 | II7: =Simulation!$E$247 | IJ7: =Simulation!$E$248 | IK7: =Simulation!$E$249 | IL7: =Simulation!$E$250 | IM7: =Simulation!$E$251 | IN7: =Simulation!$E$252 | IO7: =Simulation!$E$253 | IP7: =Simulation!$E$254 | IQ7: =Simulation!$E$255 | IR7: =Simulation!$E$256 | IS7: =Simulation!$E$257 | IT7: =Simulation!$E$258 | IU7: =Simulation!$E$259 | IV7: =Simulation!$E$260 | IW7: =Simulation!$E$261 | IX7: =Simulation!$E$262 | IY7: =Simulation!$E$263 | IZ7: =Simulation!$E$264 | JA7: =Simulation!$E$265 | JB7: =Simulation!$E$266 | JC7: =Simulation!$E$267 | JD7: =Simulation!$E$268 | JE7: =Simulation!$E$269 | JF7: =Simulation!$E$270 | JG7: =Simulation!$E$271 | JH7: =Simulation!$E$272 | JI7: =Simulation!$E$273 | JJ7: =Simulation!$E$274 | JK7: =Simulation!$E$275 | JL7: =Simulation!$E$276 | JM7: =Simulation!$E$277 | JN7: =Simulation!$E$278 | JO7: =Simulation!$E$279 | JP7: =Simulation!$E$280 | JQ7: =Simulation!$E$281 | JR7: =Simulation!$E$282 | JS7: =Simulation!$E$283 | JT7: =Simulation!$E$284 | JU7: =Simulation!$E$285 | JV7: =Simulation!$E$286 | JW7: =Simulation!$E$287 | JX7: =Simulation!$E$288 | JY7: =Simulation!$E$289 | JZ7: =Simulation!$E$290 | KA7: =Simulation!$E$291 | KB7: =Simulation!$E$292 | KC7: =Simulation!$E$293 | KD7: =Simulation!$E$294 | KE7: =Simulation!$E$295 | KF7: =Simulation!$E$296 | KG7: =Simulation!$E$297 | KH7: =Simulation!$E$298 | KI7: =Simulation!$E$299 | KJ7: =Simulation!$E$300 | KK7: =Simulation!$E$301 | KL7: =Simulation!$E$302 | KM7: =Simulation!$E$303 | KN7: =Simulation!$E$304 | KO7: =Simulation!$E$305 | KP7: =Simulation!$E$306
A8: Revenue (EURk) | B8: EURk | C8: =C6*C7/1000 | D8: =D6*D7/1000 | E8: =E6*E7/1000 | F8: =F6*F7/1000 | G8: =G6*G7/1000 | H8: =H6*H7/1000 | I8: =I6*I7/1000 | J8: =J6*J7/1000 | ... KP8: =KP6*KP7/1000
A9: OPEX (EURk) | B9: EURk | C9: =-Assumptions!$E$35*(1+Assumptions!$E$36)^0/12 | D9: =-Assumptions!$E$35*(1+Assumptions!$E$36)^0/12 | E9: =-Assumptions!$E$35*(1+Assumptions!$E$36)^0/12 | F9: =-Assumptions!$E$35*(1+Assumptions!$E$36)^0/12 | G9: =-Assumptions!$E$35*(1+Assumptions!$E$36)^0/12 | H9: =-Assumptions!$E$35*(1+Assumptions!$E$36)^0/12 | I9: =-Assumptions!$E$35*(1+Assumptions!$E$36)^0/12 | J9: =-Assumptions!$E$35*(1+Assumptions!$E$36)^0/12 | ... N9: =-Assumptions!$E$35*(1+Assumptions!$E$36)^0/12 | O9: =-Assumptions!$E$35*(1+Assumptions!$E$36)^1/12 | P9: =-Assumptions!$E$35*(1+Assumptions!$E$36)^1/12 | Q9: =-Assumptions!$E$35*(1+Assumptions!$E$36)^1/12 | R9: =-Assumptions!$E$35*(1+Assumptions!$E$36)^1/12 | S9: =-Assumptions!$E$35*(1+Assumptions!$E$36)^1/12 | T9: =-Assumptions!$E$35*(1+Assumptions!$E$36)^1/12 | U9: =-Assumptions!$E$35*(1+Assumptions!$E$36)^1/12 | V9: =-Assumptions!$E$35*(1+Assumptions!$E$36)^1/12 | ... Z9: =-Assumptions!$E$35*(1+Assumptions!$E$36)^1/12 | AA9: =-Assumptions!$E$35*(1+Assumptions!$E$36)^2/12 | AB9: =-Assumptions!$E$35*(1+Assumptions!$E$36)^2/12 | AC9: =-Assumptions!$E$35*(1+Assumptions!$E$36)^2/12 | AD9: =-Assumptions!$E$35*(1+Assumptions!$E$36)^2/12 | AE9: =-Assumptions!$E$35*(1+Assumptions!$E$36)^2/12 | AF9: =-Assumptions!$E$35*(1+Assumptions!$E$36)^2/12 | AG9: =-Assumptions!$E$35*(1+Assumptions!$E$36)^2/12 | AH9: =-Assumptions!$E$35*(1+Assumptions!$E$36)^2/12 | ... AL9: =-Assumptions!$E$35*(1+Assumptions!$E$36)^2/12 | AM9: =-Assumptions!$E$35*(1+Assumptions!$E$36)^3/12 | AN9: =-Assumptions!$E$35*(1+Assumptions!$E$36)^3/12 | AO9: =-Assumptions!$E$35*(1+Assumptions!$E$36)^3/12 | AP9: =-Assumptions!$E$35*(1+Assumptions!$E$36)^3/12 | AQ9: =-Assumptions!$E$35*(1+Assumptions!$E$36)^3/12 | AR9: =-Assumptions!$E$35*(1+Assumptions!$E$36)^3/12 | AS9: =-Assumptions!$E$35*(1+Assumptions!$E$36)^3/12 | AT9: =-Assumptions!$E$35*(1+Assumptions!$E$36)^3/12 | ... AX9: =-Assumptions!$E$35*(1+Assumptions!$E$36)^3/12 | AY9: =-Assumptions!$E$35*(1+Assumptions!$E$36)^4/12 | AZ9: =-Assumptions!$E$35*(1+Assumptions!$E$36)^4/12 | BA9: =-Assumptions!$E$35*(1+Assumptions!$E$36)^4/12 | BB9: =-Assumptions!$E$35*(1+Assumptions!$E$36)^4/12 | BC9: =-Assumptions!$E$35*(1+Assumptions!$E$36)^4/12 | BD9: =-Assumptions!$E$35*(1+Assumptions!$E$36)^4/12 | BE9: =-Assumptions!$E$35*(1+Assumptions!$E$36)^4/12 | BF9: =-Assumptions!$E$35*(1+Assumptions!$E$36)^4/12 | ... BJ9: =-Assumptions!$E$35*(1+Assumptions!$E$36)^4/12 | BK9: =-Assumptions!$E$35*(1+Assumptions!$E$36)^5/12 | BL9: =-Assumptions!$E$35*(1+Assumptions!$E$36)^5/12 | BM9: =-Assumptions!$E$35*(1+Assumptions!$E$36)^5/12 | BN9: =-Assumptions!$E$35*(1+Assumptions!$E$36)^5/12 | BO9: =-Assumptions!$E$35*(1+Assumptions!$E$36)^5/12 | BP9: =-Assumptions!$E$35*(1+Assumptions!$E$36)^5/12 | BQ9: =-Assumptions!$E$35*(1+Assumptions!$E$36)^5/12 | BR9: =-Assumptions!$E$35*(1+Assumptions!$E$36)^5/12 | ... BV9: =-Assumptions!$E$35*(1+Assumptions!$E$36)^5/12 | BW9: =-Assumptions!$E$35*(1+Assumptions!$E$36)^6/12 | BX9: =-Assumptions!$E$35*(1+Assumptions!$E$36)^6/12 | BY9: =-Assumptions!$E$35*(1+Assumptions!$E$36)^6/12 | BZ9: =-Assumptions!$E$35*(1+Assumptions!$E$36)^6/12 | CA9: =-Assumptions!$E$35*(1+Assumptions!$E$36)^6/12 | CB9: =-Assumptions!$E$35*(1+Assumptions!$E$36)^6/12 | CC9: =-Assumptions!$E$35*(1+Assumptions!$E$36)^6/12 | CD9: =-Assumptions!$E$35*(1+Assumptions!$E$36)^6/12 | ... CH9: =-Assumptions!$E$35*(1+Assumptions!$E$36)^6/12 | CI9: =-Assumptions!$E$35*(1+Assumptions!$E$36)^7/12 | CJ9: =-Assumptions!$E$35*(1+Assumptions!$E$36)^7/12 | CK9: =-Assumptions!$E$35*(1+Assumptions!$E$36)^7/12 | CL9: =-Assumptions!$E$35*(1+Assumptions!$E$36)^7/12 | CM9: =-Assumptions!$E$35*(1+Assumptions!$E$36)^7/12 | CN9: =-Assumptions!$E$35*(1+Assumptions!$E$36)^7/12 | CO9: =-Assumptions!$E$35*(1+Assumptions!$E$36)^7/12 | CP9: =-Assumptions!$E$35*(1+Assumptions!$E$36)^7/12 | ... CT9: =-Assumptions!$E$35*(1+Assumptions!$E$36)^7/12 | CU9: =-Assumptions!$E$35*(1+Assumptions!$E$36)^8/12 | CV9: =-Assumptions!$E$35*(1+Assumptions!$E$36)^8/12 | CW9: =-Assumptions!$E$35*(1+Assumptions!$E$36)^8/12 | CX9: =-Assumptions!$E$35*(1+Assumptions!$E$36)^8/12 | CY9: =-Assumptions!$E$35*(1+Assumptions!$E$36)^8/12 | CZ9: =-Assumptions!$E$35*(1+Assumptions!$E$36)^8/12 | DA9: =-Assumptions!$E$35*(1+Assumptions!$E$36)^8/12 | DB9: =-Assumptions!$E$35*(1+Assumptions!$E$36)^8/12 | ... DF9: =-Assumptions!$E$35*(1+Assumptions!$E$36)^8/12 | DG9: =-Assumptions!$E$35*(1+Assumptions!$E$36)^9/12 | DH9: =-Assumptions!$E$35*(1+Assumptions!$E$36)^9/12 | DI9: =-Assumptions!$E$35*(1+Assumptions!$E$36)^9/12 | DJ9: =-Assumptions!$E$35*(1+Assumptions!$E$36)^9/12 | DK9: =-Assumptions!$E$35*(1+Assumptions!$E$36)^9/12 | DL9: =-Assumptions!$E$35*(1+Assumptions!$E$36)^9/12 | DM9: =-Assumptions!$E$35*(1+Assumptions!$E$36)^9/12 | DN9: =-Assumptions!$E$35*(1+Assumptions!$E$36)^9/12 | ... DR9: =-Assumptions!$E$35*(1+Assumptions!$E$36)^9/12 | DS9: =-Assumptions!$E$35*(1+Assumptions!$E$36)^10/12 | DT9: =-Assumptions!$E$35*(1+Assumptions!$E$36)^10/12 | DU9: =-Assumptions!$E$35*(1+Assumptions!$E$36)^10/12 | DV9: =-Assumptions!$E$35*(1+Assumptions!$E$36)^10/12 | DW9: =-Assumptions!$E$35*(1+Assumptions!$E$36)^10/12 | DX9: =-Assumptions!$E$35*(1+Assumptions!$E$36)^10/12 | DY9: =-Assumptions!$E$35*(1+Assumptions!$E$36)^10/12 | DZ9: =-Assumptions!$E$35*(1+Assumptions!$E$36)^10/12 | ... ED9: =-Assumptions!$E$35*(1+Assumptions!$E$36)^10/12 | EE9: =-Assumptions!$E$35*(1+Assumptions!$E$36)^11/12 | EF9: =-Assumptions!$E$35*(1+Assumptions!$E$36)^11/12 | EG9: =-Assumptions!$E$35*(1+Assumptions!$E$36)^11/12 | EH9: =-Assumptions!$E$35*(1+Assumptions!$E$36)^11/12 | EI9: =-Assumptions!$E$35*(1+Assumptions!$E$36)^11/12 | EJ9: =-Assumptions!$E$35*(1+Assumptions!$E$36)^11/12 | EK9: =-Assumptions!$E$35*(1+Assumptions!$E$36)^11/12 | EL9: =-Assumptions!$E$35*(1+Assumptions!$E$36)^11/12 | ... EP9: =-Assumptions!$E$35*(1+Assumptions!$E$36)^11/12 | EQ9: =-Assumptions!$E$35*(1+Assumptions!$E$36)^12/12 | ER9: =-Assumptions!$E$35*(1+Assumptions!$E$36)^12/12 | ES9: =-Assumptions!$E$35*(1+Assumptions!$E$36)^12/12 | ET9: =-Assumptions!$E$35*(1+Assumptions!$E$36)^12/12 | EU9: =-Assumptions!$E$35*(1+Assumptions!$E$36)^12/12 | EV9: =-Assumptions!$E$35*(1+Assumptions!$E$36)^12/12 | EW9: =-Assumptions!$E$35*(1+Assumptions!$E$36)^12/12 | EX9: =-Assumptions!$E$35*(1+Assumptions!$E$36)^12/12 | ... FB9: =-Assumptions!$E$35*(1+Assumptions!$E$36)^12/12 | FC9: =-Assumptions!$E$35*(1+Assumptions!$E$36)^13/12 | FD9: =-Assumptions!$E$35*(1+Assumptions!$E$36)^13/12 | FE9: =-Assumptions!$E$35*(1+Assumptions!$E$36)^13/12 | FF9: =-Assumptions!$E$35*(1+Assumptions!$E$36)^13/12 | FG9: =-Assumptions!$E$35*(1+Assumptions!$E$36)^13/12 | FH9: =-Assumptions!$E$35*(1+Assumptions!$E$36)^13/12 | FI9: =-Assumptions!$E$35*(1+Assumptions!$E$36)^13/12 | FJ9: =-Assumptions!$E$35*(1+Assumptions!$E$36)^13/12 | ... FN9: =-Assumptions!$E$35*(1+Assumptions!$E$36)^13/12 | FO9: =-Assumptions!$E$35*(1+Assumptions!$E$36)^14/12 | FP9: =-Assumptions!$E$35*(1+Assumptions!$E$36)^14/12 | FQ9: =-Assumptions!$E$35*(1+Assumptions!$E$36)^14/12 | FR9: =-Assumptions!$E$35*(1+Assumptions!$E$36)^14/12 | FS9: =-Assumptions!$E$35*(1+Assumptions!$E$36)^14/12 | FT9: =-Assumptions!$E$35*(1+Assumptions!$E$36)^14/12 | FU9: =-Assumptions!$E$35*(1+Assumptions!$E$36)^14/12 | FV9: =-Assumptions!$E$35*(1+Assumptions!$E$36)^14/12 | ... FZ9: =-Assumptions!$E$35*(1+Assumptions!$E$36)^14/12 | GA9: =-Assumptions!$E$35*(1+Assumptions!$E$36)^15/12 | GB9: =-Assumptions!$E$35*(1+Assumptions!$E$36)^15/12 | GC9: =-Assumptions!$E$35*(1+Assumptions!$E$36)^15/12 | GD9: =-Assumptions!$E$35*(1+Assumptions!$E$36)^15/12 | GE9: =-Assumptions!$E$35*(1+Assumptions!$E$36)^15/12 | GF9: =-Assumptions!$E$35*(1+Assumptions!$E$36)^15/12 | GG9: =-Assumptions!$E$35*(1+Assumptions!$E$36)^15/12 | GH9: =-Assumptions!$E$35*(1+Assumptions!$E$36)^15/12 | ... GL9: =-Assumptions!$E$35*(1+Assumptions!$E$36)^15/12 | GM9: =-Assumptions!$E$35*(1+Assumptions!$E$36)^16/12 | GN9: =-Assumptions!$E$35*(1+Assumptions!$E$36)^16/12 | GO9: =-Assumptions!$E$35*(1+Assumptions!$E$36)^16/12 | GP9: =-Assumptions!$E$35*(1+Assumptions!$E$36)^16/12 | GQ9: =-Assumptions!$E$35*(1+Assumptions!$E$36)^16/12 | GR9: =-Assumptions!$E$35*(1+Assumptions!$E$36)^16/12 | GS9: =-Assumptions!$E$35*(1+Assumptions!$E$36)^16/12 | GT9: =-Assumptions!$E$35*(1+Assumptions!$E$36)^16/12 | ... GX9: =-Assumptions!$E$35*(1+Assumptions!$E$36)^16/12 | GY9: =-Assumptions!$E$35*(1+Assumptions!$E$36)^17/12 | GZ9: =-Assumptions!$E$35*(1+Assumptions!$E$36)^17/12 | HA9: =-Assumptions!$E$35*(1+Assumptions!$E$36)^17/12 | HB9: =-Assumptions!$E$35*(1+Assumptions!$E$36)^17/12 | HC9: =-Assumptions!$E$35*(1+Assumptions!$E$36)^17/12 | HD9: =-Assumptions!$E$35*(1+Assumptions!$E$36)^17/12 | HE9: =-Assumptions!$E$35*(1+Assumptions!$E$36)^17/12 | HF9: =-Assumptions!$E$35*(1+Assumptions!$E$36)^17/12 | ... HJ9: =-Assumptions!$E$35*(1+Assumptions!$E$36)^17/12 | HK9: =-Assumptions!$E$35*(1+Assumptions!$E$36)^18/12 | HL9: =-Assumptions!$E$35*(1+Assumptions!$E$36)^18/12 | HM9: =-Assumptions!$E$35*(1+Assumptions!$E$36)^18/12 | HN9: =-Assumptions!$E$35*(1+Assumptions!$E$36)^18/12 | HO9: =-Assumptions!$E$35*(1+Assumptions!$E$36)^18/12 | HP9: =-Assumptions!$E$35*(1+Assumptions!$E$36)^18/12 | HQ9: =-Assumptions!$E$35*(1+Assumptions!$E$36)^18/12 | HR9: =-Assumptions!$E$35*(1+Assumptions!$E$36)^18/12 | ... HV9: =-Assumptions!$E$35*(1+Assumptions!$E$36)^18/12 | HW9: =-Assumptions!$E$35*(1+Assumptions!$E$36)^19/12 | HX9: =-Assumptions!$E$35*(1+Assumptions!$E$36)^19/12 | HY9: =-Assumptions!$E$35*(1+Assumptions!$E$36)^19/12 | HZ9: =-Assumptions!$E$35*(1+Assumptions!$E$36)^19/12 | IA9: =-Assumptions!$E$35*(1+Assumptions!$E$36)^19/12 | IB9: =-Assumptions!$E$35*(1+Assumptions!$E$36)^19/12 | IC9: =-Assumptions!$E$35*(1+Assumptions!$E$36)^19/12 | ID9: =-Assumptions!$E$35*(1+Assumptions!$E$36)^19/12 | ... IH9: =-Assumptions!$E$35*(1+Assumptions!$E$36)^19/12 | II9: =-Assumptions!$E$35*(1+Assumptions!$E$36)^20/12 | IJ9: =-Assumptions!$E$35*(1+Assumptions!$E$36)^20/12 | IK9: =-Assumptions!$E$35*(1+Assumptions!$E$36)^20/12 | IL9: =-Assumptions!$E$35*(1+Assumptions!$E$36)^20/12 | IM9: =-Assumptions!$E$35*(1+Assumptions!$E$36)^20/12 | IN9: =-Assumptions!$E$35*(1+Assumptions!$E$36)^20/12 | IO9: =-Assumptions!$E$35*(1+Assumptions!$E$36)^20/12 | IP9: =-Assumptions!$E$35*(1+Assumptions!$E$36)^20/12 | ... IT9: =-Assumptions!$E$35*(1+Assumptions!$E$36)^20/12 | IU9: =-Assumptions!$E$35*(1+Assumptions!$E$36)^21/12 | IV9: =-Assumptions!$E$35*(1+Assumptions!$E$36)^21/12 | IW9: =-Assumptions!$E$35*(1+Assumptions!$E$36)^21/12 | IX9: =-Assumptions!$E$35*(1+Assumptions!$E$36)^21/12 | IY9: =-Assumptions!$E$35*(1+Assumptions!$E$36)^21/12 | IZ9: =-Assumptions!$E$35*(1+Assumptions!$E$36)^21/12 | JA9: =-Assumptions!$E$35*(1+Assumptions!$E$36)^21/12 | JB9: =-Assumptions!$E$35*(1+Assumptions!$E$36)^21/12 | ... JF9: =-Assumptions!$E$35*(1+Assumptions!$E$36)^21/12 | JG9: =-Assumptions!$E$35*(1+Assumptions!$E$36)^22/12 | JH9: =-Assumptions!$E$35*(1+Assumptions!$E$36)^22/12 | JI9: =-Assumptions!$E$35*(1+Assumptions!$E$36)^22/12 | JJ9: =-Assumptions!$E$35*(1+Assumptions!$E$36)^22/12 | JK9: =-Assumptions!$E$35*(1+Assumptions!$E$36)^22/12 | JL9: =-Assumptions!$E$35*(1+Assumptions!$E$36)^22/12 | JM9: =-Assumptions!$E$35*(1+Assumptions!$E$36)^22/12 | JN9: =-Assumptions!$E$35*(1+Assumptions!$E$36)^22/12 | ... JR9: =-Assumptions!$E$35*(1+Assumptions!$E$36)^22/12 | JS9: =-Assumptions!$E$35*(1+Assumptions!$E$36)^23/12 | JT9: =-Assumptions!$E$35*(1+Assumptions!$E$36)^23/12 | JU9: =-Assumptions!$E$35*(1+Assumptions!$E$36)^23/12 | JV9: =-Assumptions!$E$35*(1+Assumptions!$E$36)^23/12 | JW9: =-Assumptions!$E$35*(1+Assumptions!$E$36)^23/12 | JX9: =-Assumptions!$E$35*(1+Assumptions!$E$36)^23/12 | JY9: =-Assumptions!$E$35*(1+Assumptions!$E$36)^23/12 | JZ9: =-Assumptions!$E$35*(1+Assumptions!$E$36)^23/12 | ... KD9: =-Assumptions!$E$35*(1+Assumptions!$E$36)^23/12 | KE9: =-Assumptions!$E$35*(1+Assumptions!$E$36)^24/12 | KF9: =-Assumptions!$E$35*(1+Assumptions!$E$36)^24/12 | KG9: =-Assumptions!$E$35*(1+Assumptions!$E$36)^24/12 | KH9: =-Assumptions!$E$35*(1+Assumptions!$E$36)^24/12 | KI9: =-Assumptions!$E$35*(1+Assumptions!$E$36)^24/12 | KJ9: =-Assumptions!$E$35*(1+Assumptions!$E$36)^24/12 | KK9: =-Assumptions!$E$35*(1+Assumptions!$E$36)^24/12 | KL9: =-Assumptions!$E$35*(1+Assumptions!$E$36)^24/12 | ... KP9: =-Assumptions!$E$35*(1+Assumptions!$E$36)^24/12
A10: EBITDA (EURk) | B10: EURk | C10: =C8+C9 | D10: =D8+D9 | E10: =E8+E9 | F10: =F8+F9 | G10: =G8+G9 | H10: =H8+H9 | I10: =I8+I9 | J10: =J8+J9 | ... KP10: =KP8+KP9
A11: Tax (EURk) | B11: EURk | C11: =IF(C10>0,-C10*Assumptions!$E$47,0) | D11: =IF(D10>0,-D10*Assumptions!$E$47,0) | E11: =IF(E10>0,-E10*Assumptions!$E$47,0) | F11: =IF(F10>0,-F10*Assumptions!$E$47,0) | G11: =IF(G10>0,-G10*Assumptions!$E$47,0) | H11: =IF(H10>0,-H10*Assumptions!$E$47,0) | I11: =IF(I10>0,-I10*Assumptions!$E$47,0) | J11: =IF(J10>0,-J10*Assumptions!$E$47,0) | ... KP11: =IF(KP10>0,-KP10*Assumptions!$E$47,0)
A12: FCFF (EURk) | B12: EURk | C12: =C10+C11 | D12: =D10+D11 | E12: =E10+E11 | F12: =F10+F11 | G12: =G10+G11 | H12: =H10+H11 | I12: =I10+I11 | J12: =J10+J11 | ... KP12: =KP10+KP11
A13: Discount Factor | B13: - | C13: =1/(1+WACC!$E$34)^1 | D13: =1/(1+WACC!$E$34)^2 | E13: =1/(1+WACC!$E$34)^3 | F13: =1/(1+WACC!$E$34)^4 | G13: =1/(1+WACC!$E$34)^5 | H13: =1/(1+WACC!$E$34)^6 | I13: =1/(1+WACC!$E$34)^7 | J13: =1/(1+WACC!$E$34)^8 | K13: =1/(1+WACC!$E$34)^9 | L13: =1/(1+WACC!$E$34)^10 | M13: =1/(1+WACC!$E$34)^11 | N13: =1/(1+WACC!$E$34)^12 | O13: =1/(1+WACC!$E$34)^13 | P13: =1/(1+WACC!$E$34)^14 | Q13: =1/(1+WACC!$E$34)^15 | R13: =1/(1+WACC!$E$34)^16 | S13: =1/(1+WACC!$E$34)^17 | T13: =1/(1+WACC!$E$34)^18 | U13: =1/(1+WACC!$E$34)^19 | V13: =1/(1+WACC!$E$34)^20 | W13: =1/(1+WACC!$E$34)^21 | X13: =1/(1+WACC!$E$34)^22 | Y13: =1/(1+WACC!$E$34)^23 | Z13: =1/(1+WACC!$E$34)^24 | AA13: =1/(1+WACC!$E$34)^25 | AB13: =1/(1+WACC!$E$34)^26 | AC13: =1/(1+WACC!$E$34)^27 | AD13: =1/(1+WACC!$E$34)^28 | AE13: =1/(1+WACC!$E$34)^29 | AF13: =1/(1+WACC!$E$34)^30 | AG13: =1/(1+WACC!$E$34)^31 | AH13: =1/(1+WACC!$E$34)^32 | AI13: =1/(1+WACC!$E$34)^33 | AJ13: =1/(1+WACC!$E$34)^34 | AK13: =1/(1+WACC!$E$34)^35 | AL13: =1/(1+WACC!$E$34)^36 | AM13: =1/(1+WACC!$E$34)^37 | AN13: =1/(1+WACC!$E$34)^38 | AO13: =1/(1+WACC!$E$34)^39 | AP13: =1/(1+WACC!$E$34)^40 | AQ13: =1/(1+WACC!$E$34)^41 | AR13: =1/(1+WACC!$E$34)^42 | AS13: =1/(1+WACC!$E$34)^43 | AT13: =1/(1+WACC!$E$34)^44 | AU13: =1/(1+WACC!$E$34)^45 | AV13: =1/(1+WACC!$E$34)^46 | AW13: =1/(1+WACC!$E$34)^47 | AX13: =1/(1+WACC!$E$34)^48 | AY13: =1/(1+WACC!$E$34)^49 | AZ13: =1/(1+WACC!$E$34)^50 | BA13: =1/(1+WACC!$E$34)^51 | BB13: =1/(1+WACC!$E$34)^52 | BC13: =1/(1+WACC!$E$34)^53 | BD13: =1/(1+WACC!$E$34)^54 | BE13: =1/(1+WACC!$E$34)^55 | BF13: =1/(1+WACC!$E$34)^56 | BG13: =1/(1+WACC!$E$34)^57 | BH13: =1/(1+WACC!$E$34)^58 | BI13: =1/(1+WACC!$E$34)^59 | BJ13: =1/(1+WACC!$E$34)^60 | BK13: =1/(1+WACC!$E$34)^61 | BL13: =1/(1+WACC!$E$34)^62 | BM13: =1/(1+WACC!$E$34)^63 | BN13: =1/(1+WACC!$E$34)^64 | BO13: =1/(1+WACC!$E$34)^65 | BP13: =1/(1+WACC!$E$34)^66 | BQ13: =1/(1+WACC!$E$34)^67 | BR13: =1/(1+WACC!$E$34)^68 | BS13: =1/(1+WACC!$E$34)^69 | BT13: =1/(1+WACC!$E$34)^70 | BU13: =1/(1+WACC!$E$34)^71 | BV13: =1/(1+WACC!$E$34)^72 | BW13: =1/(1+WACC!$E$34)^73 | BX13: =1/(1+WACC!$E$34)^74 | BY13: =1/(1+WACC!$E$34)^75 | BZ13: =1/(1+WACC!$E$34)^76 | CA13: =1/(1+WACC!$E$34)^77 | CB13: =1/(1+WACC!$E$34)^78 | CC13: =1/(1+WACC!$E$34)^79 | CD13: =1/(1+WACC!$E$34)^80 | CE13: =1/(1+WACC!$E$34)^81 | CF13: =1/(1+WACC!$E$34)^82 | CG13: =1/(1+WACC!$E$34)^83 | CH13: =1/(1+WACC!$E$34)^84 | CI13: =1/(1+WACC!$E$34)^85 | CJ13: =1/(1+WACC!$E$34)^86 | CK13: =1/(1+WACC!$E$34)^87 | CL13: =1/(1+WACC!$E$34)^88 | CM13: =1/(1+WACC!$E$34)^89 | CN13: =1/(1+WACC!$E$34)^90 | CO13: =1/(1+WACC!$E$34)^91 | CP13: =1/(1+WACC!$E$34)^92 | CQ13: =1/(1+WACC!$E$34)^93 | CR13: =1/(1+WACC!$E$34)^94 | CS13: =1/(1+WACC!$E$34)^95 | CT13: =1/(1+WACC!$E$34)^96 | CU13: =1/(1+WACC!$E$34)^97 | CV13: =1/(1+WACC!$E$34)^98 | CW13: =1/(1+WACC!$E$34)^99 | CX13: =1/(1+WACC!$E$34)^100 | CY13: =1/(1+WACC!$E$34)^101 | CZ13: =1/(1+WACC!$E$34)^102 | DA13: =1/(1+WACC!$E$34)^103 | DB13: =1/(1+WACC!$E$34)^104 | DC13: =1/(1+WACC!$E$34)^105 | DD13: =1/(1+WACC!$E$34)^106 | DE13: =1/(1+WACC!$E$34)^107 | DF13: =1/(1+WACC!$E$34)^108 | DG13: =1/(1+WACC!$E$34)^109 | DH13: =1/(1+WACC!$E$34)^110 | DI13: =1/(1+WACC!$E$34)^111 | DJ13: =1/(1+WACC!$E$34)^112 | DK13: =1/(1+WACC!$E$34)^113 | DL13: =1/(1+WACC!$E$34)^114 | DM13: =1/(1+WACC!$E$34)^115 | DN13: =1/(1+WACC!$E$34)^116 | DO13: =1/(1+WACC!$E$34)^117 | DP13: =1/(1+WACC!$E$34)^118 | DQ13: =1/(1+WACC!$E$34)^119 | DR13: =1/(1+WACC!$E$34)^120 | DS13: =(1/(1+WACC!$E$34)^120)*(1/(1+WACC!$E$35)^1) | DT13: =(1/(1+WACC!$E$34)^120)*(1/(1+WACC!$E$35)^2) | DU13: =(1/(1+WACC!$E$34)^120)*(1/(1+WACC!$E$35)^3) | DV13: =(1/(1+WACC!$E$34)^120)*(1/(1+WACC!$E$35)^4) | DW13: =(1/(1+WACC!$E$34)^120)*(1/(1+WACC!$E$35)^5) | DX13: =(1/(1+WACC!$E$34)^120)*(1/(1+WACC!$E$35)^6) | DY13: =(1/(1+WACC!$E$34)^120)*(1/(1+WACC!$E$35)^7) | DZ13: =(1/(1+WACC!$E$34)^120)*(1/(1+WACC!$E$35)^8) | EA13: =(1/(1+WACC!$E$34)^120)*(1/(1+WACC!$E$35)^9) | EB13: =(1/(1+WACC!$E$34)^120)*(1/(1+WACC!$E$35)^10) | EC13: =(1/(1+WACC!$E$34)^120)*(1/(1+WACC!$E$35)^11) | ED13: =(1/(1+WACC!$E$34)^120)*(1/(1+WACC!$E$35)^12) | EE13: =(1/(1+WACC!$E$34)^120)*(1/(1+WACC!$E$35)^13) | EF13: =(1/(1+WACC!$E$34)^120)*(1/(1+WACC!$E$35)^14) | EG13: =(1/(1+WACC!$E$34)^120)*(1/(1+WACC!$E$35)^15) | EH13: =(1/(1+WACC!$E$34)^120)*(1/(1+WACC!$E$35)^16) | EI13: =(1/(1+WACC!$E$34)^120)*(1/(1+WACC!$E$35)^17) | EJ13: =(1/(1+WACC!$E$34)^120)*(1/(1+WACC!$E$35)^18) | EK13: =(1/(1+WACC!$E$34)^120)*(1/(1+WACC!$E$35)^19) | EL13: =(1/(1+WACC!$E$34)^120)*(1/(1+WACC!$E$35)^20) | EM13: =(1/(1+WACC!$E$34)^120)*(1/(1+WACC!$E$35)^21) | EN13: =(1/(1+WACC!$E$34)^120)*(1/(1+WACC!$E$35)^22) | EO13: =(1/(1+WACC!$E$34)^120)*(1/(1+WACC!$E$35)^23) | EP13: =(1/(1+WACC!$E$34)^120)*(1/(1+WACC!$E$35)^24) | EQ13: =(1/(1+WACC!$E$34)^120)*(1/(1+WACC!$E$35)^25) | ER13: =(1/(1+WACC!$E$34)^120)*(1/(1+WACC!$E$35)^26) | ES13: =(1/(1+WACC!$E$34)^120)*(1/(1+WACC!$E$35)^27) | ET13: =(1/(1+WACC!$E$34)^120)*(1/(1+WACC!$E$35)^28) | EU13: =(1/(1+WACC!$E$34)^120)*(1/(1+WACC!$E$35)^29) | EV13: =(1/(1+WACC!$E$34)^120)*(1/(1+WACC!$E$35)^30) | EW13: =(1/(1+WACC!$E$34)^120)*(1/(1+WACC!$E$35)^31) | EX13: =(1/(1+WACC!$E$34)^120)*(1/(1+WACC!$E$35)^32) | EY13: =(1/(1+WACC!$E$34)^120)*(1/(1+WACC!$E$35)^33) | EZ13: =(1/(1+WACC!$E$34)^120)*(1/(1+WACC!$E$35)^34) | FA13: =(1/(1+WACC!$E$34)^120)*(1/(1+WACC!$E$35)^35) | FB13: =(1/(1+WACC!$E$34)^120)*(1/(1+WACC!$E$35)^36) | FC13: =(1/(1+WACC!$E$34)^120)*(1/(1+WACC!$E$35)^37) | FD13: =(1/(1+WACC!$E$34)^120)*(1/(1+WACC!$E$35)^38) | FE13: =(1/(1+WACC!$E$34)^120)*(1/(1+WACC!$E$35)^39) | FF13: =(1/(1+WACC!$E$34)^120)*(1/(1+WACC!$E$35)^40) | FG13: =(1/(1+WACC!$E$34)^120)*(1/(1+WACC!$E$35)^41) | FH13: =(1/(1+WACC!$E$34)^120)*(1/(1+WACC!$E$35)^42) | FI13: =(1/(1+WACC!$E$34)^120)*(1/(1+WACC!$E$35)^43) | FJ13: =(1/(1+WACC!$E$34)^120)*(1/(1+WACC!$E$35)^44) | FK13: =(1/(1+WACC!$E$34)^120)*(1/(1+WACC!$E$35)^45) | FL13: =(1/(1+WACC!$E$34)^120)*(1/(1+WACC!$E$35)^46) | FM13: =(1/(1+WACC!$E$34)^120)*(1/(1+WACC!$E$35)^47) | FN13: =(1/(1+WACC!$E$34)^120)*(1/(1+WACC!$E$35)^48) | FO13: =(1/(1+WACC!$E$34)^120)*(1/(1+WACC!$E$35)^49) | FP13: =(1/(1+WACC!$E$34)^120)*(1/(1+WACC!$E$35)^50) | FQ13: =(1/(1+WACC!$E$34)^120)*(1/(1+WACC!$E$35)^51) | FR13: =(1/(1+WACC!$E$34)^120)*(1/(1+WACC!$E$35)^52) | FS13: =(1/(1+WACC!$E$34)^120)*(1/(1+WACC!$E$35)^53) | FT13: =(1/(1+WACC!$E$34)^120)*(1/(1+WACC!$E$35)^54) | FU13: =(1/(1+WACC!$E$34)^120)*(1/(1+WACC!$E$35)^55) | FV13: =(1/(1+WACC!$E$34)^120)*(1/(1+WACC!$E$35)^56) | FW13: =(1/(1+WACC!$E$34)^120)*(1/(1+WACC!$E$35)^57) | FX13: =(1/(1+WACC!$E$34)^120)*(1/(1+WACC!$E$35)^58) | FY13: =(1/(1+WACC!$E$34)^120)*(1/(1+WACC!$E$35)^59) | FZ13: =(1/(1+WACC!$E$34)^120)*(1/(1+WACC!$E$35)^60) | GA13: =(1/(1+WACC!$E$34)^120)*(1/(1+WACC!$E$35)^61) | GB13: =(1/(1+WACC!$E$34)^120)*(1/(1+WACC!$E$35)^62) | GC13: =(1/(1+WACC!$E$34)^120)*(1/(1+WACC!$E$35)^63) | GD13: =(1/(1+WACC!$E$34)^120)*(1/(1+WACC!$E$35)^64) | GE13: =(1/(1+WACC!$E$34)^120)*(1/(1+WACC!$E$35)^65) | GF13: =(1/(1+WACC!$E$34)^120)*(1/(1+WACC!$E$35)^66) | GG13: =(1/(1+WACC!$E$34)^120)*(1/(1+WACC!$E$35)^67) | GH13: =(1/(1+WACC!$E$34)^120)*(1/(1+WACC!$E$35)^68) | GI13: =(1/(1+WACC!$E$34)^120)*(1/(1+WACC!$E$35)^69) | GJ13: =(1/(1+WACC!$E$34)^120)*(1/(1+WACC!$E$35)^70) | GK13: =(1/(1+WACC!$E$34)^120)*(1/(1+WACC!$E$35)^71) | GL13: =(1/(1+WACC!$E$34)^120)*(1/(1+WACC!$E$35)^72) | GM13: =(1/(1+WACC!$E$34)^120)*(1/(1+WACC!$E$35)^73) | GN13: =(1/(1+WACC!$E$34)^120)*(1/(1+WACC!$E$35)^74) | GO13: =(1/(1+WACC!$E$34)^120)*(1/(1+WACC!$E$35)^75) | GP13: =(1/(1+WACC!$E$34)^120)*(1/(1+WACC!$E$35)^76) | GQ13: =(1/(1+WACC!$E$34)^120)*(1/(1+WACC!$E$35)^77) | GR13: =(1/(1+WACC!$E$34)^120)*(1/(1+WACC!$E$35)^78) | GS13: =(1/(1+WACC!$E$34)^120)*(1/(1+WACC!$E$35)^79) | GT13: =(1/(1+WACC!$E$34)^120)*(1/(1+WACC!$E$35)^80) | GU13: =(1/(1+WACC!$E$34)^120)*(1/(1+WACC!$E$35)^81) | GV13: =(1/(1+WACC!$E$34)^120)*(1/(1+WACC!$E$35)^82) | GW13: =(1/(1+WACC!$E$34)^120)*(1/(1+WACC!$E$35)^83) | GX13: =(1/(1+WACC!$E$34)^120)*(1/(1+WACC!$E$35)^84) | GY13: =(1/(1+WACC!$E$34)^120)*(1/(1+WACC!$E$35)^85) | GZ13: =(1/(1+WACC!$E$34)^120)*(1/(1+WACC!$E$35)^86) | HA13: =(1/(1+WACC!$E$34)^120)*(1/(1+WACC!$E$35)^87) | HB13: =(1/(1+WACC!$E$34)^120)*(1/(1+WACC!$E$35)^88) | HC13: =(1/(1+WACC!$E$34)^120)*(1/(1+WACC!$E$35)^89) | HD13: =(1/(1+WACC!$E$34)^120)*(1/(1+WACC!$E$35)^90) | HE13: =(1/(1+WACC!$E$34)^120)*(1/(1+WACC!$E$35)^91) | HF13: =(1/(1+WACC!$E$34)^120)*(1/(1+WACC!$E$35)^92) | HG13: =(1/(1+WACC!$E$34)^120)*(1/(1+WACC!$E$35)^93) | HH13: =(1/(1+WACC!$E$34)^120)*(1/(1+WACC!$E$35)^94) | HI13: =(1/(1+WACC!$E$34)^120)*(1/(1+WACC!$E$35)^95) | HJ13: =(1/(1+WACC!$E$34)^120)*(1/(1+WACC!$E$35)^96) | HK13: =(1/(1+WACC!$E$34)^120)*(1/(1+WACC!$E$35)^97) | HL13: =(1/(1+WACC!$E$34)^120)*(1/(1+WACC!$E$35)^98) | HM13: =(1/(1+WACC!$E$34)^120)*(1/(1+WACC!$E$35)^99) | HN13: =(1/(1+WACC!$E$34)^120)*(1/(1+WACC!$E$35)^100) | HO13: =(1/(1+WACC!$E$34)^120)*(1/(1+WACC!$E$35)^101) | HP13: =(1/(1+WACC!$E$34)^120)*(1/(1+WACC!$E$35)^102) | HQ13: =(1/(1+WACC!$E$34)^120)*(1/(1+WACC!$E$35)^103) | HR13: =(1/(1+WACC!$E$34)^120)*(1/(1+WACC!$E$35)^104) | HS13: =(1/(1+WACC!$E$34)^120)*(1/(1+WACC!$E$35)^105) | HT13: =(1/(1+WACC!$E$34)^120)*(1/(1+WACC!$E$35)^106) | HU13: =(1/(1+WACC!$E$34)^120)*(1/(1+WACC!$E$35)^107) | HV13: =(1/(1+WACC!$E$34)^120)*(1/(1+WACC!$E$35)^108) | HW13: =(1/(1+WACC!$E$34)^120)*(1/(1+WACC!$E$35)^109) | HX13: =(1/(1+WACC!$E$34)^120)*(1/(1+WACC!$E$35)^110) | HY13: =(1/(1+WACC!$E$34)^120)*(1/(1+WACC!$E$35)^111) | HZ13: =(1/(1+WACC!$E$34)^120)*(1/(1+WACC!$E$35)^112) | IA13: =(1/(1+WACC!$E$34)^120)*(1/(1+WACC!$E$35)^113) | IB13: =(1/(1+WACC!$E$34)^120)*(1/(1+WACC!$E$35)^114) | IC13: =(1/(1+WACC!$E$34)^120)*(1/(1+WACC!$E$35)^115) | ID13: =(1/(1+WACC!$E$34)^120)*(1/(1+WACC!$E$35)^116) | IE13: =(1/(1+WACC!$E$34)^120)*(1/(1+WACC!$E$35)^117) | IF13: =(1/(1+WACC!$E$34)^120)*(1/(1+WACC!$E$35)^118) | IG13: =(1/(1+WACC!$E$34)^120)*(1/(1+WACC!$E$35)^119) | IH13: =(1/(1+WACC!$E$34)^120)*(1/(1+WACC!$E$35)^120) | II13: =(1/(1+WACC!$E$34)^120)*(1/(1+WACC!$E$35)^121) | IJ13: =(1/(1+WACC!$E$34)^120)*(1/(1+WACC!$E$35)^122) | IK13: =(1/(1+WACC!$E$34)^120)*(1/(1+WACC!$E$35)^123) | IL13: =(1/(1+WACC!$E$34)^120)*(1/(1+WACC!$E$35)^124) | IM13: =(1/(1+WACC!$E$34)^120)*(1/(1+WACC!$E$35)^125) | IN13: =(1/(1+WACC!$E$34)^120)*(1/(1+WACC!$E$35)^126) | IO13: =(1/(1+WACC!$E$34)^120)*(1/(1+WACC!$E$35)^127) | IP13: =(1/(1+WACC!$E$34)^120)*(1/(1+WACC!$E$35)^128) | IQ13: =(1/(1+WACC!$E$34)^120)*(1/(1+WACC!$E$35)^129) | IR13: =(1/(1+WACC!$E$34)^120)*(1/(1+WACC!$E$35)^130) | IS13: =(1/(1+WACC!$E$34)^120)*(1/(1+WACC!$E$35)^131) | IT13: =(1/(1+WACC!$E$34)^120)*(1/(1+WACC!$E$35)^132) | IU13: =(1/(1+WACC!$E$34)^120)*(1/(1+WACC!$E$35)^133) | IV13: =(1/(1+WACC!$E$34)^120)*(1/(1+WACC!$E$35)^134) | IW13: =(1/(1+WACC!$E$34)^120)*(1/(1+WACC!$E$35)^135) | IX13: =(1/(1+WACC!$E$34)^120)*(1/(1+WACC!$E$35)^136) | IY13: =(1/(1+WACC!$E$34)^120)*(1/(1+WACC!$E$35)^137) | IZ13: =(1/(1+WACC!$E$34)^120)*(1/(1+WACC!$E$35)^138) | JA13: =(1/(1+WACC!$E$34)^120)*(1/(1+WACC!$E$35)^139) | JB13: =(1/(1+WACC!$E$34)^120)*(1/(1+WACC!$E$35)^140) | JC13: =(1/(1+WACC!$E$34)^120)*(1/(1+WACC!$E$35)^141) | JD13: =(1/(1+WACC!$E$34)^120)*(1/(1+WACC!$E$35)^142) | JE13: =(1/(1+WACC!$E$34)^120)*(1/(1+WACC!$E$35)^143) | JF13: =(1/(1+WACC!$E$34)^120)*(1/(1+WACC!$E$35)^144) | JG13: =(1/(1+WACC!$E$34)^120)*(1/(1+WACC!$E$35)^145) | JH13: =(1/(1+WACC!$E$34)^120)*(1/(1+WACC!$E$35)^146) | JI13: =(1/(1+WACC!$E$34)^120)*(1/(1+WACC!$E$35)^147) | JJ13: =(1/(1+WACC!$E$34)^120)*(1/(1+WACC!$E$35)^148) | JK13: =(1/(1+WACC!$E$34)^120)*(1/(1+WACC!$E$35)^149) | JL13: =(1/(1+WACC!$E$34)^120)*(1/(1+WACC!$E$35)^150) | JM13: =(1/(1+WACC!$E$34)^120)*(1/(1+WACC!$E$35)^151) | JN13: =(1/(1+WACC!$E$34)^120)*(1/(1+WACC!$E$35)^152) | JO13: =(1/(1+WACC!$E$34)^120)*(1/(1+WACC!$E$35)^153) | JP13: =(1/(1+WACC!$E$34)^120)*(1/(1+WACC!$E$35)^154) | JQ13: =(1/(1+WACC!$E$34)^120)*(1/(1+WACC!$E$35)^155) | JR13: =(1/(1+WACC!$E$34)^120)*(1/(1+WACC!$E$35)^156) | JS13: =(1/(1+WACC!$E$34)^120)*(1/(1+WACC!$E$35)^157) | JT13: =(1/(1+WACC!$E$34)^120)*(1/(1+WACC!$E$35)^158) | JU13: =(1/(1+WACC!$E$34)^120)*(1/(1+WACC!$E$35)^159) | JV13: =(1/(1+WACC!$E$34)^120)*(1/(1+WACC!$E$35)^160) | JW13: =(1/(1+WACC!$E$34)^120)*(1/(1+WACC!$E$35)^161) | JX13: =(1/(1+WACC!$E$34)^120)*(1/(1+WACC!$E$35)^162) | JY13: =(1/(1+WACC!$E$34)^120)*(1/(1+WACC!$E$35)^163) | JZ13: =(1/(1+WACC!$E$34)^120)*(1/(1+WACC!$E$35)^164) | KA13: =(1/(1+WACC!$E$34)^120)*(1/(1+WACC!$E$35)^165) | KB13: =(1/(1+WACC!$E$34)^120)*(1/(1+WACC!$E$35)^166) | KC13: =(1/(1+WACC!$E$34)^120)*(1/(1+WACC!$E$35)^167) | KD13: =(1/(1+WACC!$E$34)^120)*(1/(1+WACC!$E$35)^168) | KE13: =(1/(1+WACC!$E$34)^120)*(1/(1+WACC!$E$35)^169) | KF13: =(1/(1+WACC!$E$34)^120)*(1/(1+WACC!$E$35)^170) | KG13: =(1/(1+WACC!$E$34)^120)*(1/(1+WACC!$E$35)^171) | KH13: =(1/(1+WACC!$E$34)^120)*(1/(1+WACC!$E$35)^172) | KI13: =(1/(1+WACC!$E$34)^120)*(1/(1+WACC!$E$35)^173) | KJ13: =(1/(1+WACC!$E$34)^120)*(1/(1+WACC!$E$35)^174) | KK13: =(1/(1+WACC!$E$34)^120)*(1/(1+WACC!$E$35)^175) | KL13: =(1/(1+WACC!$E$34)^120)*(1/(1+WACC!$E$35)^176) | KM13: =(1/(1+WACC!$E$34)^120)*(1/(1+WACC!$E$35)^177) | KN13: =(1/(1+WACC!$E$34)^120)*(1/(1+WACC!$E$35)^178) | KO13: =(1/(1+WACC!$E$34)^120)*(1/(1+WACC!$E$35)^179) | KP13: =(1/(1+WACC!$E$34)^120)*(1/(1+WACC!$E$35)^180)
A14: Discounted FCFF | B14: EURk | C14: =C12*C13 | D14: =D12*D13 | E14: =E12*E13 | F14: =F12*F13 | G14: =G12*G13 | H14: =H12*H13 | I14: =I12*I13 | J14: =J12*J13 | ... KP14: =KP12*KP13
A15: Cumulative NPV | B15: EURk | C15: =C14-Assumptions!$E$31 | D15: =C15+D14 | E15: =D15+E14 | F15: =E15+F14 | G15: =F15+G14 | H15: =G15+H14 | I15: =H15+I14 | J15: =I15+J14 | K15: =J15+K14 | ... KP15: =KO15+KP14
A17: P90 — Conservative
A18: Production (MWh) | B18: MWh | C18: =Assumptions!$E$16*(1-Assumptions!$E$23)^0 | D18: =Assumptions!$E$16*(1-Assumptions!$E$23)^0 | E18: =Assumptions!$E$16*(1-Assumptions!$E$23)^0 | F18: =Assumptions!$E$16*(1-Assumptions!$E$23)^0 | G18: =Assumptions!$E$16*(1-Assumptions!$E$23)^0 | H18: =Assumptions!$E$16*(1-Assumptions!$E$23)^0 | I18: =Assumptions!$E$16*(1-Assumptions!$E$23)^0 | J18: =Assumptions!$E$16*(1-Assumptions!$E$23)^0 | ... N18: =Assumptions!$E$16*(1-Assumptions!$E$23)^0 | O18: =Assumptions!$E$16*(1-Assumptions!$E$23)^1 | P18: =Assumptions!$E$16*(1-Assumptions!$E$23)^1 | Q18: =Assumptions!$E$16*(1-Assumptions!$E$23)^1 | R18: =Assumptions!$E$16*(1-Assumptions!$E$23)^1 | S18: =Assumptions!$E$16*(1-Assumptions!$E$23)^1 | T18: =Assumptions!$E$16*(1-Assumptions!$E$23)^1 | U18: =Assumptions!$E$16*(1-Assumptions!$E$23)^1 | V18: =Assumptions!$E$16*(1-Assumptions!$E$23)^1 | ... Z18: =Assumptions!$E$16*(1-Assumptions!$E$23)^1 | AA18: =Assumptions!$E$16*(1-Assumptions!$E$23)^2 | AB18: =Assumptions!$E$16*(1-Assumptions!$E$23)^2 | AC18: =Assumptions!$E$16*(1-Assumptions!$E$23)^2 | AD18: =Assumptions!$E$16*(1-Assumptions!$E$23)^2 | AE18: =Assumptions!$E$16*(1-Assumptions!$E$23)^2 | AF18: =Assumptions!$E$16*(1-Assumptions!$E$23)^2 | AG18: =Assumptions!$E$16*(1-Assumptions!$E$23)^2 | AH18: =Assumptions!$E$16*(1-Assumptions!$E$23)^2 | ... AL18: =Assumptions!$E$16*(1-Assumptions!$E$23)^2 | AM18: =Assumptions!$E$16*(1-Assumptions!$E$23)^3 | AN18: =Assumptions!$E$16*(1-Assumptions!$E$23)^3 | AO18: =Assumptions!$E$16*(1-Assumptions!$E$23)^3 | AP18: =Assumptions!$E$16*(1-Assumptions!$E$23)^3 | AQ18: =Assumptions!$E$16*(1-Assumptions!$E$23)^3 | AR18: =Assumptions!$E$16*(1-Assumptions!$E$23)^3 | AS18: =Assumptions!$E$16*(1-Assumptions!$E$23)^3 | AT18: =Assumptions!$E$16*(1-Assumptions!$E$23)^3 | ... AX18: =Assumptions!$E$16*(1-Assumptions!$E$23)^3 | AY18: =Assumptions!$E$16*(1-Assumptions!$E$23)^4 | AZ18: =Assumptions!$E$16*(1-Assumptions!$E$23)^4 | BA18: =Assumptions!$E$16*(1-Assumptions!$E$23)^4 | BB18: =Assumptions!$E$16*(1-Assumptions!$E$23)^4 | BC18: =Assumptions!$E$16*(1-Assumptions!$E$23)^4 | BD18: =Assumptions!$E$16*(1-Assumptions!$E$23)^4 | BE18: =Assumptions!$E$16*(1-Assumptions!$E$23)^4 | BF18: =Assumptions!$E$16*(1-Assumptions!$E$23)^4 | ... BJ18: =Assumptions!$E$16*(1-Assumptions!$E$23)^4 | BK18: =Assumptions!$E$16*(1-Assumptions!$E$23)^5 | BL18: =Assumptions!$E$16*(1-Assumptions!$E$23)^5 | BM18: =Assumptions!$E$16*(1-Assumptions!$E$23)^5 | BN18: =Assumptions!$E$16*(1-Assumptions!$E$23)^5 | BO18: =Assumptions!$E$16*(1-Assumptions!$E$23)^5 | BP18: =Assumptions!$E$16*(1-Assumptions!$E$23)^5 | BQ18: =Assumptions!$E$16*(1-Assumptions!$E$23)^5 | BR18: =Assumptions!$E$16*(1-Assumptions!$E$23)^5 | ... BV18: =Assumptions!$E$16*(1-Assumptions!$E$23)^5 | BW18: =Assumptions!$E$16*(1-Assumptions!$E$23)^6 | BX18: =Assumptions!$E$16*(1-Assumptions!$E$23)^6 | BY18: =Assumptions!$E$16*(1-Assumptions!$E$23)^6 | BZ18: =Assumptions!$E$16*(1-Assumptions!$E$23)^6 | CA18: =Assumptions!$E$16*(1-Assumptions!$E$23)^6 | CB18: =Assumptions!$E$16*(1-Assumptions!$E$23)^6 | CC18: =Assumptions!$E$16*(1-Assumptions!$E$23)^6 | CD18: =Assumptions!$E$16*(1-Assumptions!$E$23)^6 | ... CH18: =Assumptions!$E$16*(1-Assumptions!$E$23)^6 | CI18: =Assumptions!$E$16*(1-Assumptions!$E$23)^7 | CJ18: =Assumptions!$E$16*(1-Assumptions!$E$23)^7 | CK18: =Assumptions!$E$16*(1-Assumptions!$E$23)^7 | CL18: =Assumptions!$E$16*(1-Assumptions!$E$23)^7 | CM18: =Assumptions!$E$16*(1-Assumptions!$E$23)^7 | CN18: =Assumptions!$E$16*(1-Assumptions!$E$23)^7 | CO18: =Assumptions!$E$16*(1-Assumptions!$E$23)^7 | CP18: =Assumptions!$E$16*(1-Assumptions!$E$23)^7 | ... CT18: =Assumptions!$E$16*(1-Assumptions!$E$23)^7 | CU18: =Assumptions!$E$16*(1-Assumptions!$E$23)^8 | CV18: =Assumptions!$E$16*(1-Assumptions!$E$23)^8 | CW18: =Assumptions!$E$16*(1-Assumptions!$E$23)^8 | CX18: =Assumptions!$E$16*(1-Assumptions!$E$23)^8 | CY18: =Assumptions!$E$16*(1-Assumptions!$E$23)^8 | CZ18: =Assumptions!$E$16*(1-Assumptions!$E$23)^8 | DA18: =Assumptions!$E$16*(1-Assumptions!$E$23)^8 | DB18: =Assumptions!$E$16*(1-Assumptions!$E$23)^8 | ... DF18: =Assumptions!$E$16*(1-Assumptions!$E$23)^8 | DG18: =Assumptions!$E$16*(1-Assumptions!$E$23)^9 | DH18: =Assumptions!$E$16*(1-Assumptions!$E$23)^9 | DI18: =Assumptions!$E$16*(1-Assumptions!$E$23)^9 | DJ18: =Assumptions!$E$16*(1-Assumptions!$E$23)^9 | DK18: =Assumptions!$E$16*(1-Assumptions!$E$23)^9 | DL18: =Assumptions!$E$16*(1-Assumptions!$E$23)^9 | DM18: =Assumptions!$E$16*(1-Assumptions!$E$23)^9 | DN18: =Assumptions!$E$16*(1-Assumptions!$E$23)^9 | ... DR18: =Assumptions!$E$16*(1-Assumptions!$E$23)^9 | DS18: =Assumptions!$E$16*(1-Assumptions!$E$23)^10 | DT18: =Assumptions!$E$16*(1-Assumptions!$E$23)^10 | DU18: =Assumptions!$E$16*(1-Assumptions!$E$23)^10 | DV18: =Assumptions!$E$16*(1-Assumptions!$E$23)^10 | DW18: =Assumptions!$E$16*(1-Assumptions!$E$23)^10 | DX18: =Assumptions!$E$16*(1-Assumptions!$E$23)^10 | DY18: =Assumptions!$E$16*(1-Assumptions!$E$23)^10 | DZ18: =Assumptions!$E$16*(1-Assumptions!$E$23)^10 | ... ED18: =Assumptions!$E$16*(1-Assumptions!$E$23)^10 | EE18: =Assumptions!$E$16*(1-Assumptions!$E$23)^11 | EF18: =Assumptions!$E$16*(1-Assumptions!$E$23)^11 | EG18: =Assumptions!$E$16*(1-Assumptions!$E$23)^11 | EH18: =Assumptions!$E$16*(1-Assumptions!$E$23)^11 | EI18: =Assumptions!$E$16*(1-Assumptions!$E$23)^11 | EJ18: =Assumptions!$E$16*(1-Assumptions!$E$23)^11 | EK18: =Assumptions!$E$16*(1-Assumptions!$E$23)^11 | EL18: =Assumptions!$E$16*(1-Assumptions!$E$23)^11 | ... EP18: =Assumptions!$E$16*(1-Assumptions!$E$23)^11 | EQ18: =Assumptions!$E$16*(1-Assumptions!$E$23)^12 | ER18: =Assumptions!$E$16*(1-Assumptions!$E$23)^12 | ES18: =Assumptions!$E$16*(1-Assumptions!$E$23)^12 | ET18: =Assumptions!$E$16*(1-Assumptions!$E$23)^12 | EU18: =Assumptions!$E$16*(1-Assumptions!$E$23)^12 | EV18: =Assumptions!$E$16*(1-Assumptions!$E$23)^12 | EW18: =Assumptions!$E$16*(1-Assumptions!$E$23)^12 | EX18: =Assumptions!$E$16*(1-Assumptions!$E$23)^12 | ... FB18: =Assumptions!$E$16*(1-Assumptions!$E$23)^12 | FC18: =Assumptions!$E$16*(1-Assumptions!$E$23)^13 | FD18: =Assumptions!$E$16*(1-Assumptions!$E$23)^13 | FE18: =Assumptions!$E$16*(1-Assumptions!$E$23)^13 | FF18: =Assumptions!$E$16*(1-Assumptions!$E$23)^13 | FG18: =Assumptions!$E$16*(1-Assumptions!$E$23)^13 | FH18: =Assumptions!$E$16*(1-Assumptions!$E$23)^13 | FI18: =Assumptions!$E$16*(1-Assumptions!$E$23)^13 | FJ18: =Assumptions!$E$16*(1-Assumptions!$E$23)^13 | ... FN18: =Assumptions!$E$16*(1-Assumptions!$E$23)^13 | FO18: =Assumptions!$E$16*(1-Assumptions!$E$23)^14 | FP18: =Assumptions!$E$16*(1-Assumptions!$E$23)^14 | FQ18: =Assumptions!$E$16*(1-Assumptions!$E$23)^14 | FR18: =Assumptions!$E$16*(1-Assumptions!$E$23)^14 | FS18: =Assumptions!$E$16*(1-Assumptions!$E$23)^14 | FT18: =Assumptions!$E$16*(1-Assumptions!$E$23)^14 | FU18: =Assumptions!$E$16*(1-Assumptions!$E$23)^14 | FV18: =Assumptions!$E$16*(1-Assumptions!$E$23)^14 | ... FZ18: =Assumptions!$E$16*(1-Assumptions!$E$23)^14 | GA18: =Assumptions!$E$16*(1-Assumptions!$E$23)^15 | GB18: =Assumptions!$E$16*(1-Assumptions!$E$23)^15 | GC18: =Assumptions!$E$16*(1-Assumptions!$E$23)^15 | GD18: =Assumptions!$E$16*(1-Assumptions!$E$23)^15 | GE18: =Assumptions!$E$16*(1-Assumptions!$E$23)^15 | GF18: =Assumptions!$E$16*(1-Assumptions!$E$23)^15 | GG18: =Assumptions!$E$16*(1-Assumptions!$E$23)^15 | GH18: =Assumptions!$E$16*(1-Assumptions!$E$23)^15 | ... GL18: =Assumptions!$E$16*(1-Assumptions!$E$23)^15 | GM18: =Assumptions!$E$16*(1-Assumptions!$E$23)^16 | GN18: =Assumptions!$E$16*(1-Assumptions!$E$23)^16 | GO18: =Assumptions!$E$16*(1-Assumptions!$E$23)^16 | GP18: =Assumptions!$E$16*(1-Assumptions!$E$23)^16 | GQ18: =Assumptions!$E$16*(1-Assumptions!$E$23)^16 | GR18: =Assumptions!$E$16*(1-Assumptions!$E$23)^16 | GS18: =Assumptions!$E$16*(1-Assumptions!$E$23)^16 | GT18: =Assumptions!$E$16*(1-Assumptions!$E$23)^16 | ... GX18: =Assumptions!$E$16*(1-Assumptions!$E$23)^16 | GY18: =Assumptions!$E$16*(1-Assumptions!$E$23)^17 | GZ18: =Assumptions!$E$16*(1-Assumptions!$E$23)^17 | HA18: =Assumptions!$E$16*(1-Assumptions!$E$23)^17 | HB18: =Assumptions!$E$16*(1-Assumptions!$E$23)^17 | HC18: =Assumptions!$E$16*(1-Assumptions!$E$23)^17 | HD18: =Assumptions!$E$16*(1-Assumptions!$E$23)^17 | HE18: =Assumptions!$E$16*(1-Assumptions!$E$23)^17 | HF18: =Assumptions!$E$16*(1-Assumptions!$E$23)^17 | ... HJ18: =Assumptions!$E$16*(1-Assumptions!$E$23)^17 | HK18: =Assumptions!$E$16*(1-Assumptions!$E$23)^18 | HL18: =Assumptions!$E$16*(1-Assumptions!$E$23)^18 | HM18: =Assumptions!$E$16*(1-Assumptions!$E$23)^18 | HN18: =Assumptions!$E$16*(1-Assumptions!$E$23)^18 | HO18: =Assumptions!$E$16*(1-Assumptions!$E$23)^18 | HP18: =Assumptions!$E$16*(1-Assumptions!$E$23)^18 | HQ18: =Assumptions!$E$16*(1-Assumptions!$E$23)^18 | HR18: =Assumptions!$E$16*(1-Assumptions!$E$23)^18 | ... HV18: =Assumptions!$E$16*(1-Assumptions!$E$23)^18 | HW18: =Assumptions!$E$16*(1-Assumptions!$E$23)^19 | HX18: =Assumptions!$E$16*(1-Assumptions!$E$23)^19 | HY18: =Assumptions!$E$16*(1-Assumptions!$E$23)^19 | HZ18: =Assumptions!$E$16*(1-Assumptions!$E$23)^19 | IA18: =Assumptions!$E$16*(1-Assumptions!$E$23)^19 | IB18: =Assumptions!$E$16*(1-Assumptions!$E$23)^19 | IC18: =Assumptions!$E$16*(1-Assumptions!$E$23)^19 | ID18: =Assumptions!$E$16*(1-Assumptions!$E$23)^19 | ... IH18: =Assumptions!$E$16*(1-Assumptions!$E$23)^19 | II18: =Assumptions!$E$16*(1-Assumptions!$E$23)^20 | IJ18: =Assumptions!$E$16*(1-Assumptions!$E$23)^20 | IK18: =Assumptions!$E$16*(1-Assumptions!$E$23)^20 | IL18: =Assumptions!$E$16*(1-Assumptions!$E$23)^20 | IM18: =Assumptions!$E$16*(1-Assumptions!$E$23)^20 | IN18: =Assumptions!$E$16*(1-Assumptions!$E$23)^20 | IO18: =Assumptions!$E$16*(1-Assumptions!$E$23)^20 | IP18: =Assumptions!$E$16*(1-Assumptions!$E$23)^20 | ... IT18: =Assumptions!$E$16*(1-Assumptions!$E$23)^20 | IU18: =Assumptions!$E$16*(1-Assumptions!$E$23)^21 | IV18: =Assumptions!$E$16*(1-Assumptions!$E$23)^21 | IW18: =Assumptions!$E$16*(1-Assumptions!$E$23)^21 | IX18: =Assumptions!$E$16*(1-Assumptions!$E$23)^21 | IY18: =Assumptions!$E$16*(1-Assumptions!$E$23)^21 | IZ18: =Assumptions!$E$16*(1-Assumptions!$E$23)^21 | JA18: =Assumptions!$E$16*(1-Assumptions!$E$23)^21 | JB18: =Assumptions!$E$16*(1-Assumptions!$E$23)^21 | ... JF18: =Assumptions!$E$16*(1-Assumptions!$E$23)^21 | JG18: =Assumptions!$E$16*(1-Assumptions!$E$23)^22 | JH18: =Assumptions!$E$16*(1-Assumptions!$E$23)^22 | JI18: =Assumptions!$E$16*(1-Assumptions!$E$23)^22 | JJ18: =Assumptions!$E$16*(1-Assumptions!$E$23)^22 | JK18: =Assumptions!$E$16*(1-Assumptions!$E$23)^22 | JL18: =Assumptions!$E$16*(1-Assumptions!$E$23)^22 | JM18: =Assumptions!$E$16*(1-Assumptions!$E$23)^22 | JN18: =Assumptions!$E$16*(1-Assumptions!$E$23)^22 | ... JR18: =Assumptions!$E$16*(1-Assumptions!$E$23)^22 | JS18: =Assumptions!$E$16*(1-Assumptions!$E$23)^23 | JT18: =Assumptions!$E$16*(1-Assumptions!$E$23)^23 | JU18: =Assumptions!$E$16*(1-Assumptions!$E$23)^23 | JV18: =Assumptions!$E$16*(1-Assumptions!$E$23)^23 | JW18: =Assumptions!$E$16*(1-Assumptions!$E$23)^23 | JX18: =Assumptions!$E$16*(1-Assumptions!$E$23)^23 | JY18: =Assumptions!$E$16*(1-Assumptions!$E$23)^23 | JZ18: =Assumptions!$E$16*(1-Assumptions!$E$23)^23 | ... KD18: =Assumptions!$E$16*(1-Assumptions!$E$23)^23 | KE18: =Assumptions!$E$16*(1-Assumptions!$E$23)^24 | KF18: =Assumptions!$E$16*(1-Assumptions!$E$23)^24 | KG18: =Assumptions!$E$16*(1-Assumptions!$E$23)^24 | KH18: =Assumptions!$E$16*(1-Assumptions!$E$23)^24 | KI18: =Assumptions!$E$16*(1-Assumptions!$E$23)^24 | KJ18: =Assumptions!$E$16*(1-Assumptions!$E$23)^24 | KK18: =Assumptions!$E$16*(1-Assumptions!$E$23)^24 | KL18: =Assumptions!$E$16*(1-Assumptions!$E$23)^24 | ... KP18: =Assumptions!$E$16*(1-Assumptions!$E$23)^24
A19: Price (EUR/MWh) | B19: EUR/MWh | C19: =Assumptions!$E$40 | D19: =Assumptions!$E$40 | E19: =Assumptions!$E$40 | F19: =Assumptions!$E$40 | G19: =Assumptions!$E$40 | H19: =Assumptions!$E$40 | I19: =Assumptions!$E$40 | J19: =Assumptions!$E$40 | ... DR19: =Assumptions!$E$40 | DS19: =Simulation!$I$127 | DT19: =Simulation!$I$128 | DU19: =Simulation!$I$129 | DV19: =Simulation!$I$130 | DW19: =Simulation!$I$131 | DX19: =Simulation!$I$132 | DY19: =Simulation!$I$133 | DZ19: =Simulation!$I$134 | EA19: =Simulation!$I$135 | EB19: =Simulation!$I$136 | EC19: =Simulation!$I$137 | ED19: =Simulation!$I$138 | EE19: =Simulation!$I$139 | EF19: =Simulation!$I$140 | EG19: =Simulation!$I$141 | EH19: =Simulation!$I$142 | EI19: =Simulation!$I$143 | EJ19: =Simulation!$I$144 | EK19: =Simulation!$I$145 | EL19: =Simulation!$I$146 | EM19: =Simulation!$I$147 | EN19: =Simulation!$I$148 | EO19: =Simulation!$I$149 | EP19: =Simulation!$I$150 | EQ19: =Simulation!$I$151 | ER19: =Simulation!$I$152 | ES19: =Simulation!$I$153 | ET19: =Simulation!$I$154 | EU19: =Simulation!$I$155 | EV19: =Simulation!$I$156 | EW19: =Simulation!$I$157 | EX19: =Simulation!$I$158 | EY19: =Simulation!$I$159 | EZ19: =Simulation!$I$160 | FA19: =Simulation!$I$161 | FB19: =Simulation!$I$162 | FC19: =Simulation!$I$163 | FD19: =Simulation!$I$164 | FE19: =Simulation!$I$165 | FF19: =Simulation!$I$166 | FG19: =Simulation!$I$167 | FH19: =Simulation!$I$168 | FI19: =Simulation!$I$169 | FJ19: =Simulation!$I$170 | FK19: =Simulation!$I$171 | FL19: =Simulation!$I$172 | FM19: =Simulation!$I$173 | FN19: =Simulation!$I$174 | FO19: =Simulation!$I$175 | FP19: =Simulation!$I$176 | FQ19: =Simulation!$I$177 | FR19: =Simulation!$I$178 | FS19: =Simulation!$I$179 | FT19: =Simulation!$I$180 | FU19: =Simulation!$I$181 | FV19: =Simulation!$I$182 | FW19: =Simulation!$I$183 | FX19: =Simulation!$I$184 | FY19: =Simulation!$I$185 | FZ19: =Simulation!$I$186 | GA19: =Simulation!$I$187 | GB19: =Simulation!$I$188 | GC19: =Simulation!$I$189 | GD19: =Simulation!$I$190 | GE19: =Simulation!$I$191 | GF19: =Simulation!$I$192 | GG19: =Simulation!$I$193 | GH19: =Simulation!$I$194 | GI19: =Simulation!$I$195 | GJ19: =Simulation!$I$196 | GK19: =Simulation!$I$197 | GL19: =Simulation!$I$198 | GM19: =Simulation!$I$199 | GN19: =Simulation!$I$200 | GO19: =Simulation!$I$201 | GP19: =Simulation!$I$202 | GQ19: =Simulation!$I$203 | GR19: =Simulation!$I$204 | GS19: =Simulation!$I$205 | GT19: =Simulation!$I$206 | GU19: =Simulation!$I$207 | GV19: =Simulation!$I$208 | GW19: =Simulation!$I$209 | GX19: =Simulation!$I$210 | GY19: =Simulation!$I$211 | GZ19: =Simulation!$I$212 | HA19: =Simulation!$I$213 | HB19: =Simulation!$I$214 | HC19: =Simulation!$I$215 | HD19: =Simulation!$I$216 | HE19: =Simulation!$I$217 | HF19: =Simulation!$I$218 | HG19: =Simulation!$I$219 | HH19: =Simulation!$I$220 | HI19: =Simulation!$I$221 | HJ19: =Simulation!$I$222 | HK19: =Simulation!$I$223 | HL19: =Simulation!$I$224 | HM19: =Simulation!$I$225 | HN19: =Simulation!$I$226 | HO19: =Simulation!$I$227 | HP19: =Simulation!$I$228 | HQ19: =Simulation!$I$229 | HR19: =Simulation!$I$230 | HS19: =Simulation!$I$231 | HT19: =Simulation!$I$232 | HU19: =Simulation!$I$233 | HV19: =Simulation!$I$234 | HW19: =Simulation!$I$235 | HX19: =Simulation!$I$236 | HY19: =Simulation!$I$237 | HZ19: =Simulation!$I$238 | IA19: =Simulation!$I$239 | IB19: =Simulation!$I$240 | IC19: =Simulation!$I$241 | ID19: =Simulation!$I$242 | IE19: =Simulation!$I$243 | IF19: =Simulation!$I$244 | IG19: =Simulation!$I$245 | IH19: =Simulation!$I$246 | II19: =Simulation!$I$247 | IJ19: =Simulation!$I$248 | IK19: =Simulation!$I$249 | IL19: =Simulation!$I$250 | IM19: =Simulation!$I$251 | IN19: =Simulation!$I$252 | IO19: =Simulation!$I$253 | IP19: =Simulation!$I$254 | IQ19: =Simulation!$I$255 | IR19: =Simulation!$I$256 | IS19: =Simulation!$I$257 | IT19: =Simulation!$I$258 | IU19: =Simulation!$I$259 | IV19: =Simulation!$I$260 | IW19: =Simulation!$I$261 | IX19: =Simulation!$I$262 | IY19: =Simulation!$I$263 | IZ19: =Simulation!$I$264 | JA19: =Simulation!$I$265 | JB19: =Simulation!$I$266 | JC19: =Simulation!$I$267 | JD19: =Simulation!$I$268 | JE19: =Simulation!$I$269 | JF19: =Simulation!$I$270 | JG19: =Simulation!$I$271 | JH19: =Simulation!$I$272 | JI19: =Simulation!$I$273 | JJ19: =Simulation!$I$274 | JK19: =Simulation!$I$275 | JL19: =Simulation!$I$276 | JM19: =Simulation!$I$277 | JN19: =Simulation!$I$278 | JO19: =Simulation!$I$279 | JP19: =Simulation!$I$280 | JQ19: =Simulation!$I$281 | JR19: =Simulation!$I$282 | JS19: =Simulation!$I$283 | JT19: =Simulation!$I$284 | JU19: =Simulation!$I$285 | JV19: =Simulation!$I$286 | JW19: =Simulation!$I$287 | JX19: =Simulation!$I$288 | JY19: =Simulation!$I$289 | JZ19: =Simulation!$I$290 | KA19: =Simulation!$I$291 | KB19: =Simulation!$I$292 | KC19: =Simulation!$I$293 | KD19: =Simulation!$I$294 | KE19: =Simulation!$I$295 | KF19: =Simulation!$I$296 | KG19: =Simulation!$I$297 | KH19: =Simulation!$I$298 | KI19: =Simulation!$I$299 | KJ19: =Simulation!$I$300 | KK19: =Simulation!$I$301 | KL19: =Simulation!$I$302 | KM19: =Simulation!$I$303 | KN19: =Simulation!$I$304 | KO19: =Simulation!$I$305 | KP19: =Simulation!$I$306
A20: Revenue (EURk) | B20: EURk | C20: =C18*C19/1000 | D20: =D18*D19/1000 | E20: =E18*E19/1000 | F20: =F18*F19/1000 | G20: =G18*G19/1000 | H20: =H18*H19/1000 | I20: =I18*I19/1000 | J20: =J18*J19/1000 | ... KP20: =KP18*KP19/1000
A21: OPEX (EURk) | B21: EURk | C21: =-Assumptions!$E$35*(1+Assumptions!$E$36)^0/12 | D21: =-Assumptions!$E$35*(1+Assumptions!$E$36)^0/12 | E21: =-Assumptions!$E$35*(1+Assumptions!$E$36)^0/12 | F21: =-Assumptions!$E$35*(1+Assumptions!$E$36)^0/12 | G21: =-Assumptions!$E$35*(1+Assumptions!$E$36)^0/12 | H21: =-Assumptions!$E$35*(1+Assumptions!$E$36)^0/12 | I21: =-Assumptions!$E$35*(1+Assumptions!$E$36)^0/12 | J21: =-Assumptions!$E$35*(1+Assumptions!$E$36)^0/12 | ... N21: =-Assumptions!$E$35*(1+Assumptions!$E$36)^0/12 | O21: =-Assumptions!$E$35*(1+Assumptions!$E$36)^1/12 | P21: =-Assumptions!$E$35*(1+Assumptions!$E$36)^1/12 | Q21: =-Assumptions!$E$35*(1+Assumptions!$E$36)^1/12 | R21: =-Assumptions!$E$35*(1+Assumptions!$E$36)^1/12 | S21: =-Assumptions!$E$35*(1+Assumptions!$E$36)^1/12 | T21: =-Assumptions!$E$35*(1+Assumptions!$E$36)^1/12 | U21: =-Assumptions!$E$35*(1+Assumptions!$E$36)^1/12 | V21: =-Assumptions!$E$35*(1+Assumptions!$E$36)^1/12 | ... Z21: =-Assumptions!$E$35*(1+Assumptions!$E$36)^1/12 | AA21: =-Assumptions!$E$35*(1+Assumptions!$E$36)^2/12 | AB21: =-Assumptions!$E$35*(1+Assumptions!$E$36)^2/12 | AC21: =-Assumptions!$E$35*(1+Assumptions!$E$36)^2/12 | AD21: =-Assumptions!$E$35*(1+Assumptions!$E$36)^2/12 | AE21: =-Assumptions!$E$35*(1+Assumptions!$E$36)^2/12 | AF21: =-Assumptions!$E$35*(1+Assumptions!$E$36)^2/12 | AG21: =-Assumptions!$E$35*(1+Assumptions!$E$36)^2/12 | AH21: =-Assumptions!$E$35*(1+Assumptions!$E$36)^2/12 | ... AL21: =-Assumptions!$E$35*(1+Assumptions!$E$36)^2/12 | AM21: =-Assumptions!$E$35*(1+Assumptions!$E$36)^3/12 | AN21: =-Assumptions!$E$35*(1+Assumptions!$E$36)^3/12 | AO21: =-Assumptions!$E$35*(1+Assumptions!$E$36)^3/12 | AP21: =-Assumptions!$E$35*(1+Assumptions!$E$36)^3/12 | AQ21: =-Assumptions!$E$35*(1+Assumptions!$E$36)^3/12 | AR21: =-Assumptions!$E$35*(1+Assumptions!$E$36)^3/12 | AS21: =-Assumptions!$E$35*(1+Assumptions!$E$36)^3/12 | AT21: =-Assumptions!$E$35*(1+Assumptions!$E$36)^3/12 | ... AX21: =-Assumptions!$E$35*(1+Assumptions!$E$36)^3/12 | AY21: =-Assumptions!$E$35*(1+Assumptions!$E$36)^4/12 | AZ21: =-Assumptions!$E$35*(1+Assumptions!$E$36)^4/12 | BA21: =-Assumptions!$E$35*(1+Assumptions!$E$36)^4/12 | BB21: =-Assumptions!$E$35*(1+Assumptions!$E$36)^4/12 | BC21: =-Assumptions!$E$35*(1+Assumptions!$E$36)^4/12 | BD21: =-Assumptions!$E$35*(1+Assumptions!$E$36)^4/12 | BE21: =-Assumptions!$E$35*(1+Assumptions!$E$36)^4/12 | BF21: =-Assumptions!$E$35*(1+Assumptions!$E$36)^4/12 | ... BJ21: =-Assumptions!$E$35*(1+Assumptions!$E$36)^4/12 | BK21: =-Assumptions!$E$35*(1+Assumptions!$E$36)^5/12 | BL21: =-Assumptions!$E$35*(1+Assumptions!$E$36)^5/12 | BM21: =-Assumptions!$E$35*(1+Assumptions!$E$36)^5/12 | BN21: =-Assumptions!$E$35*(1+Assumptions!$E$36)^5/12 | BO21: =-Assumptions!$E$35*(1+Assumptions!$E$36)^5/12 | BP21: =-Assumptions!$E$35*(1+Assumptions!$E$36)^5/12 | BQ21: =-Assumptions!$E$35*(1+Assumptions!$E$36)^5/12 | BR21: =-Assumptions!$E$35*(1+Assumptions!$E$36)^5/12 | ... BV21: =-Assumptions!$E$35*(1+Assumptions!$E$36)^5/12 | BW21: =-Assumptions!$E$35*(1+Assumptions!$E$36)^6/12 | BX21: =-Assumptions!$E$35*(1+Assumptions!$E$36)^6/12 | BY21: =-Assumptions!$E$35*(1+Assumptions!$E$36)^6/12 | BZ21: =-Assumptions!$E$35*(1+Assumptions!$E$36)^6/12 | CA21: =-Assumptions!$E$35*(1+Assumptions!$E$36)^6/12 | CB21: =-Assumptions!$E$35*(1+Assumptions!$E$36)^6/12 | CC21: =-Assumptions!$E$35*(1+Assumptions!$E$36)^6/12 | CD21: =-Assumptions!$E$35*(1+Assumptions!$E$36)^6/12 | ... CH21: =-Assumptions!$E$35*(1+Assumptions!$E$36)^6/12 | CI21: =-Assumptions!$E$35*(1+Assumptions!$E$36)^7/12 | CJ21: =-Assumptions!$E$35*(1+Assumptions!$E$36)^7/12 | CK21: =-Assumptions!$E$35*(1+Assumptions!$E$36)^7/12 | CL21: =-Assumptions!$E$35*(1+Assumptions!$E$36)^7/12 | CM21: =-Assumptions!$E$35*(1+Assumptions!$E$36)^7/12 | CN21: =-Assumptions!$E$35*(1+Assumptions!$E$36)^7/12 | CO21: =-Assumptions!$E$35*(1+Assumptions!$E$36)^7/12 | CP21: =-Assumptions!$E$35*(1+Assumptions!$E$36)^7/12 | ... CT21: =-Assumptions!$E$35*(1+Assumptions!$E$36)^7/12 | CU21: =-Assumptions!$E$35*(1+Assumptions!$E$36)^8/12 | CV21: =-Assumptions!$E$35*(1+Assumptions!$E$36)^8/12 | CW21: =-Assumptions!$E$35*(1+Assumptions!$E$36)^8/12 | CX21: =-Assumptions!$E$35*(1+Assumptions!$E$36)^8/12 | CY21: =-Assumptions!$E$35*(1+Assumptions!$E$36)^8/12 | CZ21: =-Assumptions!$E$35*(1+Assumptions!$E$36)^8/12 | DA21: =-Assumptions!$E$35*(1+Assumptions!$E$36)^8/12 | DB21: =-Assumptions!$E$35*(1+Assumptions!$E$36)^8/12 | ... DF21: =-Assumptions!$E$35*(1+Assumptions!$E$36)^8/12 | DG21: =-Assumptions!$E$35*(1+Assumptions!$E$36)^9/12 | DH21: =-Assumptions!$E$35*(1+Assumptions!$E$36)^9/12 | DI21: =-Assumptions!$E$35*(1+Assumptions!$E$36)^9/12 | DJ21: =-Assumptions!$E$35*(1+Assumptions!$E$36)^9/12 | DK21: =-Assumptions!$E$35*(1+Assumptions!$E$36)^9/12 | DL21: =-Assumptions!$E$35*(1+Assumptions!$E$36)^9/12 | DM21: =-Assumptions!$E$35*(1+Assumptions!$E$36)^9/12 | DN21: =-Assumptions!$E$35*(1+Assumptions!$E$36)^9/12 | ... DR21: =-Assumptions!$E$35*(1+Assumptions!$E$36)^9/12 | DS21: =-Assumptions!$E$35*(1+Assumptions!$E$36)^10/12 | DT21: =-Assumptions!$E$35*(1+Assumptions!$E$36)^10/12 | DU21: =-Assumptions!$E$35*(1+Assumptions!$E$36)^10/12 | DV21: =-Assumptions!$E$35*(1+Assumptions!$E$36)^10/12 | DW21: =-Assumptions!$E$35*(1+Assumptions!$E$36)^10/12 | DX21: =-Assumptions!$E$35*(1+Assumptions!$E$36)^10/12 | DY21: =-Assumptions!$E$35*(1+Assumptions!$E$36)^10/12 | DZ21: =-Assumptions!$E$35*(1+Assumptions!$E$36)^10/12 | ... ED21: =-Assumptions!$E$35*(1+Assumptions!$E$36)^10/12 | EE21: =-Assumptions!$E$35*(1+Assumptions!$E$36)^11/12 | EF21: =-Assumptions!$E$35*(1+Assumptions!$E$36)^11/12 | EG21: =-Assumptions!$E$35*(1+Assumptions!$E$36)^11/12 | EH21: =-Assumptions!$E$35*(1+Assumptions!$E$36)^11/12 | EI21: =-Assumptions!$E$35*(1+Assumptions!$E$36)^11/12 | EJ21: =-Assumptions!$E$35*(1+Assumptions!$E$36)^11/12 | EK21: =-Assumptions!$E$35*(1+Assumptions!$E$36)^11/12 | EL21: =-Assumptions!$E$35*(1+Assumptions!$E$36)^11/12 | ... EP21: =-Assumptions!$E$35*(1+Assumptions!$E$36)^11/12 | EQ21: =-Assumptions!$E$35*(1+Assumptions!$E$36)^12/12 | ER21: =-Assumptions!$E$35*(1+Assumptions!$E$36)^12/12 | ES21: =-Assumptions!$E$35*(1+Assumptions!$E$36)^12/12 | ET21: =-Assumptions!$E$35*(1+Assumptions!$E$36)^12/12 | EU21: =-Assumptions!$E$35*(1+Assumptions!$E$36)^12/12 | EV21: =-Assumptions!$E$35*(1+Assumptions!$E$36)^12/12 | EW21: =-Assumptions!$E$35*(1+Assumptions!$E$36)^12/12 | EX21: =-Assumptions!$E$35*(1+Assumptions!$E$36)^12/12 | ... FB21: =-Assumptions!$E$35*(1+Assumptions!$E$36)^12/12 | FC21: =-Assumptions!$E$35*(1+Assumptions!$E$36)^13/12 | FD21: =-Assumptions!$E$35*(1+Assumptions!$E$36)^13/12 | FE21: =-Assumptions!$E$35*(1+Assumptions!$E$36)^13/12 | FF21: =-Assumptions!$E$35*(1+Assumptions!$E$36)^13/12 | FG21: =-Assumptions!$E$35*(1+Assumptions!$E$36)^13/12 | FH21: =-Assumptions!$E$35*(1+Assumptions!$E$36)^13/12 | FI21: =-Assumptions!$E$35*(1+Assumptions!$E$36)^13/12 | FJ21: =-Assumptions!$E$35*(1+Assumptions!$E$36)^13/12 | ... FN21: =-Assumptions!$E$35*(1+Assumptions!$E$36)^13/12 | FO21: =-Assumptions!$E$35*(1+Assumptions!$E$36)^14/12 | FP21: =-Assumptions!$E$35*(1+Assumptions!$E$36)^14/12 | FQ21: =-Assumptions!$E$35*(1+Assumptions!$E$36)^14/12 | FR21: =-Assumptions!$E$35*(1+Assumptions!$E$36)^14/12 | FS21: =-Assumptions!$E$35*(1+Assumptions!$E$36)^14/12 | FT21: =-Assumptions!$E$35*(1+Assumptions!$E$36)^14/12 | FU21: =-Assumptions!$E$35*(1+Assumptions!$E$36)^14/12 | FV21: =-Assumptions!$E$35*(1+Assumptions!$E$36)^14/12 | ... FZ21: =-Assumptions!$E$35*(1+Assumptions!$E$36)^14/12 | GA21: =-Assumptions!$E$35*(1+Assumptions!$E$36)^15/12 | GB21: =-Assumptions!$E$35*(1+Assumptions!$E$36)^15/12 | GC21: =-Assumptions!$E$35*(1+Assumptions!$E$36)^15/12 | GD21: =-Assumptions!$E$35*(1+Assumptions!$E$36)^15/12 | GE21: =-Assumptions!$E$35*(1+Assumptions!$E$36)^15/12 | GF21: =-Assumptions!$E$35*(1+Assumptions!$E$36)^15/12 | GG21: =-Assumptions!$E$35*(1+Assumptions!$E$36)^15/12 | GH21: =-Assumptions!$E$35*(1+Assumptions!$E$36)^15/12 | ... GL21: =-Assumptions!$E$35*(1+Assumptions!$E$36)^15/12 | GM21: =-Assumptions!$E$35*(1+Assumptions!$E$36)^16/12 | GN21: =-Assumptions!$E$35*(1+Assumptions!$E$36)^16/12 | GO21: =-Assumptions!$E$35*(1+Assumptions!$E$36)^16/12 | GP21: =-Assumptions!$E$35*(1+Assumptions!$E$36)^16/12 | GQ21: =-Assumptions!$E$35*(1+Assumptions!$E$36)^16/12 | GR21: =-Assumptions!$E$35*(1+Assumptions!$E$36)^16/12 | GS21: =-Assumptions!$E$35*(1+Assumptions!$E$36)^16/12 | GT21: =-Assumptions!$E$35*(1+Assumptions!$E$36)^16/12 | ... GX21: =-Assumptions!$E$35*(1+Assumptions!$E$36)^16/12 | GY21: =-Assumptions!$E$35*(1+Assumptions!$E$36)^17/12 | GZ21: =-Assumptions!$E$35*(1+Assumptions!$E$36)^17/12 | HA21: =-Assumptions!$E$35*(1+Assumptions!$E$36)^17/12 | HB21: =-Assumptions!$E$35*(1+Assumptions!$E$36)^17/12 | HC21: =-Assumptions!$E$35*(1+Assumptions!$E$36)^17/12 | HD21: =-Assumptions!$E$35*(1+Assumptions!$E$36)^17/12 | HE21: =-Assumptions!$E$35*(1+Assumptions!$E$36)^17/12 | HF21: =-Assumptions!$E$35*(1+Assumptions!$E$36)^17/12 | ... HJ21: =-Assumptions!$E$35*(1+Assumptions!$E$36)^17/12 | HK21: =-Assumptions!$E$35*(1+Assumptions!$E$36)^18/12 | HL21: =-Assumptions!$E$35*(1+Assumptions!$E$36)^18/12 | HM21: =-Assumptions!$E$35*(1+Assumptions!$E$36)^18/12 | HN21: =-Assumptions!$E$35*(1+Assumptions!$E$36)^18/12 | HO21: =-Assumptions!$E$35*(1+Assumptions!$E$36)^18/12 | HP21: =-Assumptions!$E$35*(1+Assumptions!$E$36)^18/12 | HQ21: =-Assumptions!$E$35*(1+Assumptions!$E$36)^18/12 | HR21: =-Assumptions!$E$35*(1+Assumptions!$E$36)^18/12 | ... HV21: =-Assumptions!$E$35*(1+Assumptions!$E$36)^18/12 | HW21: =-Assumptions!$E$35*(1+Assumptions!$E$36)^19/12 | HX21: =-Assumptions!$E$35*(1+Assumptions!$E$36)^19/12 | HY21: =-Assumptions!$E$35*(1+Assumptions!$E$36)^19/12 | HZ21: =-Assumptions!$E$35*(1+Assumptions!$E$36)^19/12 | IA21: =-Assumptions!$E$35*(1+Assumptions!$E$36)^19/12 | IB21: =-Assumptions!$E$35*(1+Assumptions!$E$36)^19/12 | IC21: =-Assumptions!$E$35*(1+Assumptions!$E$36)^19/12 | ID21: =-Assumptions!$E$35*(1+Assumptions!$E$36)^19/12 | ... IH21: =-Assumptions!$E$35*(1+Assumptions!$E$36)^19/12 | II21: =-Assumptions!$E$35*(1+Assumptions!$E$36)^20/12 | IJ21: =-Assumptions!$E$35*(1+Assumptions!$E$36)^20/12 | IK21: =-Assumptions!$E$35*(1+Assumptions!$E$36)^20/12 | IL21: =-Assumptions!$E$35*(1+Assumptions!$E$36)^20/12 | IM21: =-Assumptions!$E$35*(1+Assumptions!$E$36)^20/12 | IN21: =-Assumptions!$E$35*(1+Assumptions!$E$36)^20/12 | IO21: =-Assumptions!$E$35*(1+Assumptions!$E$36)^20/12 | IP21: =-Assumptions!$E$35*(1+Assumptions!$E$36)^20/12 | ... IT21: =-Assumptions!$E$35*(1+Assumptions!$E$36)^20/12 | IU21: =-Assumptions!$E$35*(1+Assumptions!$E$36)^21/12 | IV21: =-Assumptions!$E$35*(1+Assumptions!$E$36)^21/12 | IW21: =-Assumptions!$E$35*(1+Assumptions!$E$36)^21/12 | IX21: =-Assumptions!$E$35*(1+Assumptions!$E$36)^21/12 | IY21: =-Assumptions!$E$35*(1+Assumptions!$E$36)^21/12 | IZ21: =-Assumptions!$E$35*(1+Assumptions!$E$36)^21/12 | JA21: =-Assumptions!$E$35*(1+Assumptions!$E$36)^21/12 | JB21: =-Assumptions!$E$35*(1+Assumptions!$E$36)^21/12 | ... JF21: =-Assumptions!$E$35*(1+Assumptions!$E$36)^21/12 | JG21: =-Assumptions!$E$35*(1+Assumptions!$E$36)^22/12 | JH21: =-Assumptions!$E$35*(1+Assumptions!$E$36)^22/12 | JI21: =-Assumptions!$E$35*(1+Assumptions!$E$36)^22/12 | JJ21: =-Assumptions!$E$35*(1+Assumptions!$E$36)^22/12 | JK21: =-Assumptions!$E$35*(1+Assumptions!$E$36)^22/12 | JL21: =-Assumptions!$E$35*(1+Assumptions!$E$36)^22/12 | JM21: =-Assumptions!$E$35*(1+Assumptions!$E$36)^22/12 | JN21: =-Assumptions!$E$35*(1+Assumptions!$E$36)^22/12 | ... JR21: =-Assumptions!$E$35*(1+Assumptions!$E$36)^22/12 | JS21: =-Assumptions!$E$35*(1+Assumptions!$E$36)^23/12 | JT21: =-Assumptions!$E$35*(1+Assumptions!$E$36)^23/12 | JU21: =-Assumptions!$E$35*(1+Assumptions!$E$36)^23/12 | JV21: =-Assumptions!$E$35*(1+Assumptions!$E$36)^23/12 | JW21: =-Assumptions!$E$35*(1+Assumptions!$E$36)^23/12 | JX21: =-Assumptions!$E$35*(1+Assumptions!$E$36)^23/12 | JY21: =-Assumptions!$E$35*(1+Assumptions!$E$36)^23/12 | JZ21: =-Assumptions!$E$35*(1+Assumptions!$E$36)^23/12 | ... KD21: =-Assumptions!$E$35*(1+Assumptions!$E$36)^23/12 | KE21: =-Assumptions!$E$35*(1+Assumptions!$E$36)^24/12 | KF21: =-Assumptions!$E$35*(1+Assumptions!$E$36)^24/12 | KG21: =-Assumptions!$E$35*(1+Assumptions!$E$36)^24/12 | KH21: =-Assumptions!$E$35*(1+Assumptions!$E$36)^24/12 | KI21: =-Assumptions!$E$35*(1+Assumptions!$E$36)^24/12 | KJ21: =-Assumptions!$E$35*(1+Assumptions!$E$36)^24/12 | KK21: =-Assumptions!$E$35*(1+Assumptions!$E$36)^24/12 | KL21: =-Assumptions!$E$35*(1+Assumptions!$E$36)^24/12 | ... KP21: =-Assumptions!$E$35*(1+Assumptions!$E$36)^24/12
A22: EBITDA (EURk) | B22: EURk | C22: =C20+C21 | D22: =D20+D21 | E22: =E20+E21 | F22: =F20+F21 | G22: =G20+G21 | H22: =H20+H21 | I22: =I20+I21 | J22: =J20+J21 | ... KP22: =KP20+KP21
A23: Tax (EURk) | B23: EURk | C23: =IF(C22>0,-C22*Assumptions!$E$47,0) | D23: =IF(D22>0,-D22*Assumptions!$E$47,0) | E23: =IF(E22>0,-E22*Assumptions!$E$47,0) | F23: =IF(F22>0,-F22*Assumptions!$E$47,0) | G23: =IF(G22>0,-G22*Assumptions!$E$47,0) | H23: =IF(H22>0,-H22*Assumptions!$E$47,0) | I23: =IF(I22>0,-I22*Assumptions!$E$47,0) | J23: =IF(J22>0,-J22*Assumptions!$E$47,0) | ... KP23: =IF(KP22>0,-KP22*Assumptions!$E$47,0)
A24: FCFF (EURk) | B24: EURk | C24: =C22+C23 | D24: =D22+D23 | E24: =E22+E23 | F24: =F22+F23 | G24: =G22+G23 | H24: =H22+H23 | I24: =I22+I23 | J24: =J22+J23 | ... KP24: =KP22+KP23
A25: Discount Factor | B25: - | C25: =1/(1+WACC!$E$34)^1 | D25: =1/(1+WACC!$E$34)^2 | E25: =1/(1+WACC!$E$34)^3 | F25: =1/(1+WACC!$E$34)^4 | G25: =1/(1+WACC!$E$34)^5 | H25: =1/(1+WACC!$E$34)^6 | I25: =1/(1+WACC!$E$34)^7 | J25: =1/(1+WACC!$E$34)^8 | K25: =1/(1+WACC!$E$34)^9 | L25: =1/(1+WACC!$E$34)^10 | M25: =1/(1+WACC!$E$34)^11 | N25: =1/(1+WACC!$E$34)^12 | O25: =1/(1+WACC!$E$34)^13 | P25: =1/(1+WACC!$E$34)^14 | Q25: =1/(1+WACC!$E$34)^15 | R25: =1/(1+WACC!$E$34)^16 | S25: =1/(1+WACC!$E$34)^17 | T25: =1/(1+WACC!$E$34)^18 | U25: =1/(1+WACC!$E$34)^19 | V25: =1/(1+WACC!$E$34)^20 | W25: =1/(1+WACC!$E$34)^21 | X25: =1/(1+WACC!$E$34)^22 | Y25: =1/(1+WACC!$E$34)^23 | Z25: =1/(1+WACC!$E$34)^24 | AA25: =1/(1+WACC!$E$34)^25 | AB25: =1/(1+WACC!$E$34)^26 | AC25: =1/(1+WACC!$E$34)^27 | AD25: =1/(1+WACC!$E$34)^28 | AE25: =1/(1+WACC!$E$34)^29 | AF25: =1/(1+WACC!$E$34)^30 | AG25: =1/(1+WACC!$E$34)^31 | AH25: =1/(1+WACC!$E$34)^32 | AI25: =1/(1+WACC!$E$34)^33 | AJ25: =1/(1+WACC!$E$34)^34 | AK25: =1/(1+WACC!$E$34)^35 | AL25: =1/(1+WACC!$E$34)^36 | AM25: =1/(1+WACC!$E$34)^37 | AN25: =1/(1+WACC!$E$34)^38 | AO25: =1/(1+WACC!$E$34)^39 | AP25: =1/(1+WACC!$E$34)^40 | AQ25: =1/(1+WACC!$E$34)^41 | AR25: =1/(1+WACC!$E$34)^42 | AS25: =1/(1+WACC!$E$34)^43 | AT25: =1/(1+WACC!$E$34)^44 | AU25: =1/(1+WACC!$E$34)^45 | AV25: =1/(1+WACC!$E$34)^46 | AW25: =1/(1+WACC!$E$34)^47 | AX25: =1/(1+WACC!$E$34)^48 | AY25: =1/(1+WACC!$E$34)^49 | AZ25: =1/(1+WACC!$E$34)^50 | BA25: =1/(1+WACC!$E$34)^51 | BB25: =1/(1+WACC!$E$34)^52 | BC25: =1/(1+WACC!$E$34)^53 | BD25: =1/(1+WACC!$E$34)^54 | BE25: =1/(1+WACC!$E$34)^55 | BF25: =1/(1+WACC!$E$34)^56 | BG25: =1/(1+WACC!$E$34)^57 | BH25: =1/(1+WACC!$E$34)^58 | BI25: =1/(1+WACC!$E$34)^59 | BJ25: =1/(1+WACC!$E$34)^60 | BK25: =1/(1+WACC!$E$34)^61 | BL25: =1/(1+WACC!$E$34)^62 | BM25: =1/(1+WACC!$E$34)^63 | BN25: =1/(1+WACC!$E$34)^64 | BO25: =1/(1+WACC!$E$34)^65 | BP25: =1/(1+WACC!$E$34)^66 | BQ25: =1/(1+WACC!$E$34)^67 | BR25: =1/(1+WACC!$E$34)^68 | BS25: =1/(1+WACC!$E$34)^69 | BT25: =1/(1+WACC!$E$34)^70 | BU25: =1/(1+WACC!$E$34)^71 | BV25: =1/(1+WACC!$E$34)^72 | BW25: =1/(1+WACC!$E$34)^73 | BX25: =1/(1+WACC!$E$34)^74 | BY25: =1/(1+WACC!$E$34)^75 | BZ25: =1/(1+WACC!$E$34)^76 | CA25: =1/(1+WACC!$E$34)^77 | CB25: =1/(1+WACC!$E$34)^78 | CC25: =1/(1+WACC!$E$34)^79 | CD25: =1/(1+WACC!$E$34)^80 | CE25: =1/(1+WACC!$E$34)^81 | CF25: =1/(1+WACC!$E$34)^82 | CG25: =1/(1+WACC!$E$34)^83 | CH25: =1/(1+WACC!$E$34)^84 | CI25: =1/(1+WACC!$E$34)^85 | CJ25: =1/(1+WACC!$E$34)^86 | CK25: =1/(1+WACC!$E$34)^87 | CL25: =1/(1+WACC!$E$34)^88 | CM25: =1/(1+WACC!$E$34)^89 | CN25: =1/(1+WACC!$E$34)^90 | CO25: =1/(1+WACC!$E$34)^91 | CP25: =1/(1+WACC!$E$34)^92 | CQ25: =1/(1+WACC!$E$34)^93 | CR25: =1/(1+WACC!$E$34)^94 | CS25: =1/(1+WACC!$E$34)^95 | CT25: =1/(1+WACC!$E$34)^96 | CU25: =1/(1+WACC!$E$34)^97 | CV25: =1/(1+WACC!$E$34)^98 | CW25: =1/(1+WACC!$E$34)^99 | CX25: =1/(1+WACC!$E$34)^100 | CY25: =1/(1+WACC!$E$34)^101 | CZ25: =1/(1+WACC!$E$34)^102 | DA25: =1/(1+WACC!$E$34)^103 | DB25: =1/(1+WACC!$E$34)^104 | DC25: =1/(1+WACC!$E$34)^105 | DD25: =1/(1+WACC!$E$34)^106 | DE25: =1/(1+WACC!$E$34)^107 | DF25: =1/(1+WACC!$E$34)^108 | DG25: =1/(1+WACC!$E$34)^109 | DH25: =1/(1+WACC!$E$34)^110 | DI25: =1/(1+WACC!$E$34)^111 | DJ25: =1/(1+WACC!$E$34)^112 | DK25: =1/(1+WACC!$E$34)^113 | DL25: =1/(1+WACC!$E$34)^114 | DM25: =1/(1+WACC!$E$34)^115 | DN25: =1/(1+WACC!$E$34)^116 | DO25: =1/(1+WACC!$E$34)^117 | DP25: =1/(1+WACC!$E$34)^118 | DQ25: =1/(1+WACC!$E$34)^119 | DR25: =1/(1+WACC!$E$34)^120 | DS25: =(1/(1+WACC!$E$34)^120)*(1/(1+WACC!$E$35)^1) | DT25: =(1/(1+WACC!$E$34)^120)*(1/(1+WACC!$E$35)^2) | DU25: =(1/(1+WACC!$E$34)^120)*(1/(1+WACC!$E$35)^3) | DV25: =(1/(1+WACC!$E$34)^120)*(1/(1+WACC!$E$35)^4) | DW25: =(1/(1+WACC!$E$34)^120)*(1/(1+WACC!$E$35)^5) | DX25: =(1/(1+WACC!$E$34)^120)*(1/(1+WACC!$E$35)^6) | DY25: =(1/(1+WACC!$E$34)^120)*(1/(1+WACC!$E$35)^7) | DZ25: =(1/(1+WACC!$E$34)^120)*(1/(1+WACC!$E$35)^8) | EA25: =(1/(1+WACC!$E$34)^120)*(1/(1+WACC!$E$35)^9) | EB25: =(1/(1+WACC!$E$34)^120)*(1/(1+WACC!$E$35)^10) | EC25: =(1/(1+WACC!$E$34)^120)*(1/(1+WACC!$E$35)^11) | ED25: =(1/(1+WACC!$E$34)^120)*(1/(1+WACC!$E$35)^12) | EE25: =(1/(1+WACC!$E$34)^120)*(1/(1+WACC!$E$35)^13) | EF25: =(1/(1+WACC!$E$34)^120)*(1/(1+WACC!$E$35)^14) | EG25: =(1/(1+WACC!$E$34)^120)*(1/(1+WACC!$E$35)^15) | EH25: =(1/(1+WACC!$E$34)^120)*(1/(1+WACC!$E$35)^16) | EI25: =(1/(1+WACC!$E$34)^120)*(1/(1+WACC!$E$35)^17) | EJ25: =(1/(1+WACC!$E$34)^120)*(1/(1+WACC!$E$35)^18) | EK25: =(1/(1+WACC!$E$34)^120)*(1/(1+WACC!$E$35)^19) | EL25: =(1/(1+WACC!$E$34)^120)*(1/(1+WACC!$E$35)^20) | EM25: =(1/(1+WACC!$E$34)^120)*(1/(1+WACC!$E$35)^21) | EN25: =(1/(1+WACC!$E$34)^120)*(1/(1+WACC!$E$35)^22) | EO25: =(1/(1+WACC!$E$34)^120)*(1/(1+WACC!$E$35)^23) | EP25: =(1/(1+WACC!$E$34)^120)*(1/(1+WACC!$E$35)^24) | EQ25: =(1/(1+WACC!$E$34)^120)*(1/(1+WACC!$E$35)^25) | ER25: =(1/(1+WACC!$E$34)^120)*(1/(1+WACC!$E$35)^26) | ES25: =(1/(1+WACC!$E$34)^120)*(1/(1+WACC!$E$35)^27) | ET25: =(1/(1+WACC!$E$34)^120)*(1/(1+WACC!$E$35)^28) | EU25: =(1/(1+WACC!$E$34)^120)*(1/(1+WACC!$E$35)^29) | EV25: =(1/(1+WACC!$E$34)^120)*(1/(1+WACC!$E$35)^30) | EW25: =(1/(1+WACC!$E$34)^120)*(1/(1+WACC!$E$35)^31) | EX25: =(1/(1+WACC!$E$34)^120)*(1/(1+WACC!$E$35)^32) | EY25: =(1/(1+WACC!$E$34)^120)*(1/(1+WACC!$E$35)^33) | EZ25: =(1/(1+WACC!$E$34)^120)*(1/(1+WACC!$E$35)^34) | FA25: =(1/(1+WACC!$E$34)^120)*(1/(1+WACC!$E$35)^35) | FB25: =(1/(1+WACC!$E$34)^120)*(1/(1+WACC!$E$35)^36) | FC25: =(1/(1+WACC!$E$34)^120)*(1/(1+WACC!$E$35)^37) | FD25: =(1/(1+WACC!$E$34)^120)*(1/(1+WACC!$E$35)^38) | FE25: =(1/(1+WACC!$E$34)^120)*(1/(1+WACC!$E$35)^39) | FF25: =(1/(1+WACC!$E$34)^120)*(1/(1+WACC!$E$35)^40) | FG25: =(1/(1+WACC!$E$34)^120)*(1/(1+WACC!$E$35)^41) | FH25: =(1/(1+WACC!$E$34)^120)*(1/(1+WACC!$E$35)^42) | FI25: =(1/(1+WACC!$E$34)^120)*(1/(1+WACC!$E$35)^43) | FJ25: =(1/(1+WACC!$E$34)^120)*(1/(1+WACC!$E$35)^44) | FK25: =(1/(1+WACC!$E$34)^120)*(1/(1+WACC!$E$35)^45) | FL25: =(1/(1+WACC!$E$34)^120)*(1/(1+WACC!$E$35)^46) | FM25: =(1/(1+WACC!$E$34)^120)*(1/(1+WACC!$E$35)^47) | FN25: =(1/(1+WACC!$E$34)^120)*(1/(1+WACC!$E$35)^48) | FO25: =(1/(1+WACC!$E$34)^120)*(1/(1+WACC!$E$35)^49) | FP25: =(1/(1+WACC!$E$34)^120)*(1/(1+WACC!$E$35)^50) | FQ25: =(1/(1+WACC!$E$34)^120)*(1/(1+WACC!$E$35)^51) | FR25: =(1/(1+WACC!$E$34)^120)*(1/(1+WACC!$E$35)^52) | FS25: =(1/(1+WACC!$E$34)^120)*(1/(1+WACC!$E$35)^53) | FT25: =(1/(1+WACC!$E$34)^120)*(1/(1+WACC!$E$35)^54) | FU25: =(1/(1+WACC!$E$34)^120)*(1/(1+WACC!$E$35)^55) | FV25: =(1/(1+WACC!$E$34)^120)*(1/(1+WACC!$E$35)^56) | FW25: =(1/(1+WACC!$E$34)^120)*(1/(1+WACC!$E$35)^57) | FX25: =(1/(1+WACC!$E$34)^120)*(1/(1+WACC!$E$35)^58) | FY25: =(1/(1+WACC!$E$34)^120)*(1/(1+WACC!$E$35)^59) | FZ25: =(1/(1+WACC!$E$34)^120)*(1/(1+WACC!$E$35)^60) | GA25: =(1/(1+WACC!$E$34)^120)*(1/(1+WACC!$E$35)^61) | GB25: =(1/(1+WACC!$E$34)^120)*(1/(1+WACC!$E$35)^62) | GC25: =(1/(1+WACC!$E$34)^120)*(1/(1+WACC!$E$35)^63) | GD25: =(1/(1+WACC!$E$34)^120)*(1/(1+WACC!$E$35)^64) | GE25: =(1/(1+WACC!$E$34)^120)*(1/(1+WACC!$E$35)^65) | GF25: =(1/(1+WACC!$E$34)^120)*(1/(1+WACC!$E$35)^66) | GG25: =(1/(1+WACC!$E$34)^120)*(1/(1+WACC!$E$35)^67) | GH25: =(1/(1+WACC!$E$34)^120)*(1/(1+WACC!$E$35)^68) | GI25: =(1/(1+WACC!$E$34)^120)*(1/(1+WACC!$E$35)^69) | GJ25: =(1/(1+WACC!$E$34)^120)*(1/(1+WACC!$E$35)^70) | GK25: =(1/(1+WACC!$E$34)^120)*(1/(1+WACC!$E$35)^71) | GL25: =(1/(1+WACC!$E$34)^120)*(1/(1+WACC!$E$35)^72) | GM25: =(1/(1+WACC!$E$34)^120)*(1/(1+WACC!$E$35)^73) | GN25: =(1/(1+WACC!$E$34)^120)*(1/(1+WACC!$E$35)^74) | GO25: =(1/(1+WACC!$E$34)^120)*(1/(1+WACC!$E$35)^75) | GP25: =(1/(1+WACC!$E$34)^120)*(1/(1+WACC!$E$35)^76) | GQ25: =(1/(1+WACC!$E$34)^120)*(1/(1+WACC!$E$35)^77) | GR25: =(1/(1+WACC!$E$34)^120)*(1/(1+WACC!$E$35)^78) | GS25: =(1/(1+WACC!$E$34)^120)*(1/(1+WACC!$E$35)^79) | GT25: =(1/(1+WACC!$E$34)^120)*(1/(1+WACC!$E$35)^80) | GU25: =(1/(1+WACC!$E$34)^120)*(1/(1+WACC!$E$35)^81) | GV25: =(1/(1+WACC!$E$34)^120)*(1/(1+WACC!$E$35)^82) | GW25: =(1/(1+WACC!$E$34)^120)*(1/(1+WACC!$E$35)^83) | GX25: =(1/(1+WACC!$E$34)^120)*(1/(1+WACC!$E$35)^84) | GY25: =(1/(1+WACC!$E$34)^120)*(1/(1+WACC!$E$35)^85) | GZ25: =(1/(1+WACC!$E$34)^120)*(1/(1+WACC!$E$35)^86) | HA25: =(1/(1+WACC!$E$34)^120)*(1/(1+WACC!$E$35)^87) | HB25: =(1/(1+WACC!$E$34)^120)*(1/(1+WACC!$E$35)^88) | HC25: =(1/(1+WACC!$E$34)^120)*(1/(1+WACC!$E$35)^89) | HD25: =(1/(1+WACC!$E$34)^120)*(1/(1+WACC!$E$35)^90) | HE25: =(1/(1+WACC!$E$34)^120)*(1/(1+WACC!$E$35)^91) | HF25: =(1/(1+WACC!$E$34)^120)*(1/(1+WACC!$E$35)^92) | HG25: =(1/(1+WACC!$E$34)^120)*(1/(1+WACC!$E$35)^93) | HH25: =(1/(1+WACC!$E$34)^120)*(1/(1+WACC!$E$35)^94) | HI25: =(1/(1+WACC!$E$34)^120)*(1/(1+WACC!$E$35)^95) | HJ25: =(1/(1+WACC!$E$34)^120)*(1/(1+WACC!$E$35)^96) | HK25: =(1/(1+WACC!$E$34)^120)*(1/(1+WACC!$E$35)^97) | HL25: =(1/(1+WACC!$E$34)^120)*(1/(1+WACC!$E$35)^98) | HM25: =(1/(1+WACC!$E$34)^120)*(1/(1+WACC!$E$35)^99) | HN25: =(1/(1+WACC!$E$34)^120)*(1/(1+WACC!$E$35)^100) | HO25: =(1/(1+WACC!$E$34)^120)*(1/(1+WACC!$E$35)^101) | HP25: =(1/(1+WACC!$E$34)^120)*(1/(1+WACC!$E$35)^102) | HQ25: =(1/(1+WACC!$E$34)^120)*(1/(1+WACC!$E$35)^103) | HR25: =(1/(1+WACC!$E$34)^120)*(1/(1+WACC!$E$35)^104) | HS25: =(1/(1+WACC!$E$34)^120)*(1/(1+WACC!$E$35)^105) | HT25: =(1/(1+WACC!$E$34)^120)*(1/(1+WACC!$E$35)^106) | HU25: =(1/(1+WACC!$E$34)^120)*(1/(1+WACC!$E$35)^107) | HV25: =(1/(1+WACC!$E$34)^120)*(1/(1+WACC!$E$35)^108) | HW25: =(1/(1+WACC!$E$34)^120)*(1/(1+WACC!$E$35)^109) | HX25: =(1/(1+WACC!$E$34)^120)*(1/(1+WACC!$E$35)^110) | HY25: =(1/(1+WACC!$E$34)^120)*(1/(1+WACC!$E$35)^111) | HZ25: =(1/(1+WACC!$E$34)^120)*(1/(1+WACC!$E$35)^112) | IA25: =(1/(1+WACC!$E$34)^120)*(1/(1+WACC!$E$35)^113) | IB25: =(1/(1+WACC!$E$34)^120)*(1/(1+WACC!$E$35)^114) | IC25: =(1/(1+WACC!$E$34)^120)*(1/(1+WACC!$E$35)^115) | ID25: =(1/(1+WACC!$E$34)^120)*(1/(1+WACC!$E$35)^116) | IE25: =(1/(1+WACC!$E$34)^120)*(1/(1+WACC!$E$35)^117) | IF25: =(1/(1+WACC!$E$34)^120)*(1/(1+WACC!$E$35)^118) | IG25: =(1/(1+WACC!$E$34)^120)*(1/(1+WACC!$E$35)^119) | IH25: =(1/(1+WACC!$E$34)^120)*(1/(1+WACC!$E$35)^120) | II25: =(1/(1+WACC!$E$34)^120)*(1/(1+WACC!$E$35)^121) | IJ25: =(1/(1+WACC!$E$34)^120)*(1/(1+WACC!$E$35)^122) | IK25: =(1/(1+WACC!$E$34)^120)*(1/(1+WACC!$E$35)^123) | IL25: =(1/(1+WACC!$E$34)^120)*(1/(1+WACC!$E$35)^124) | IM25: =(1/(1+WACC!$E$34)^120)*(1/(1+WACC!$E$35)^125) | IN25: =(1/(1+WACC!$E$34)^120)*(1/(1+WACC!$E$35)^126) | IO25: =(1/(1+WACC!$E$34)^120)*(1/(1+WACC!$E$35)^127) | IP25: =(1/(1+WACC!$E$34)^120)*(1/(1+WACC!$E$35)^128) | IQ25: =(1/(1+WACC!$E$34)^120)*(1/(1+WACC!$E$35)^129) | IR25: =(1/(1+WACC!$E$34)^120)*(1/(1+WACC!$E$35)^130) | IS25: =(1/(1+WACC!$E$34)^120)*(1/(1+WACC!$E$35)^131) | IT25: =(1/(1+WACC!$E$34)^120)*(1/(1+WACC!$E$35)^132) | IU25: =(1/(1+WACC!$E$34)^120)*(1/(1+WACC!$E$35)^133) | IV25: =(1/(1+WACC!$E$34)^120)*(1/(1+WACC!$E$35)^134) | IW25: =(1/(1+WACC!$E$34)^120)*(1/(1+WACC!$E$35)^135) | IX25: =(1/(1+WACC!$E$34)^120)*(1/(1+WACC!$E$35)^136) | IY25: =(1/(1+WACC!$E$34)^120)*(1/(1+WACC!$E$35)^137) | IZ25: =(1/(1+WACC!$E$34)^120)*(1/(1+WACC!$E$35)^138) | JA25: =(1/(1+WACC!$E$34)^120)*(1/(1+WACC!$E$35)^139) | JB25: =(1/(1+WACC!$E$34)^120)*(1/(1+WACC!$E$35)^140) | JC25: =(1/(1+WACC!$E$34)^120)*(1/(1+WACC!$E$35)^141) | JD25: =(1/(1+WACC!$E$34)^120)*(1/(1+WACC!$E$35)^142) | JE25: =(1/(1+WACC!$E$34)^120)*(1/(1+WACC!$E$35)^143) | JF25: =(1/(1+WACC!$E$34)^120)*(1/(1+WACC!$E$35)^144) | JG25: =(1/(1+WACC!$E$34)^120)*(1/(1+WACC!$E$35)^145) | JH25: =(1/(1+WACC!$E$34)^120)*(1/(1+WACC!$E$35)^146) | JI25: =(1/(1+WACC!$E$34)^120)*(1/(1+WACC!$E$35)^147) | JJ25: =(1/(1+WACC!$E$34)^120)*(1/(1+WACC!$E$35)^148) | JK25: =(1/(1+WACC!$E$34)^120)*(1/(1+WACC!$E$35)^149) | JL25: =(1/(1+WACC!$E$34)^120)*(1/(1+WACC!$E$35)^150) | JM25: =(1/(1+WACC!$E$34)^120)*(1/(1+WACC!$E$35)^151) | JN25: =(1/(1+WACC!$E$34)^120)*(1/(1+WACC!$E$35)^152) | JO25: =(1/(1+WACC!$E$34)^120)*(1/(1+WACC!$E$35)^153) | JP25: =(1/(1+WACC!$E$34)^120)*(1/(1+WACC!$E$35)^154) | JQ25: =(1/(1+WACC!$E$34)^120)*(1/(1+WACC!$E$35)^155) | JR25: =(1/(1+WACC!$E$34)^120)*(1/(1+WACC!$E$35)^156) | JS25: =(1/(1+WACC!$E$34)^120)*(1/(1+WACC!$E$35)^157) | JT25: =(1/(1+WACC!$E$34)^120)*(1/(1+WACC!$E$35)^158) | JU25: =(1/(1+WACC!$E$34)^120)*(1/(1+WACC!$E$35)^159) | JV25: =(1/(1+WACC!$E$34)^120)*(1/(1+WACC!$E$35)^160) | JW25: =(1/(1+WACC!$E$34)^120)*(1/(1+WACC!$E$35)^161) | JX25: =(1/(1+WACC!$E$34)^120)*(1/(1+WACC!$E$35)^162) | JY25: =(1/(1+WACC!$E$34)^120)*(1/(1+WACC!$E$35)^163) | JZ25: =(1/(1+WACC!$E$34)^120)*(1/(1+WACC!$E$35)^164) | KA25: =(1/(1+WACC!$E$34)^120)*(1/(1+WACC!$E$35)^165) | KB25: =(1/(1+WACC!$E$34)^120)*(1/(1+WACC!$E$35)^166) | KC25: =(1/(1+WACC!$E$34)^120)*(1/(1+WACC!$E$35)^167) | KD25: =(1/(1+WACC!$E$34)^120)*(1/(1+WACC!$E$35)^168) | KE25: =(1/(1+WACC!$E$34)^120)*(1/(1+WACC!$E$35)^169) | KF25: =(1/(1+WACC!$E$34)^120)*(1/(1+WACC!$E$35)^170) | KG25: =(1/(1+WACC!$E$34)^120)*(1/(1+WACC!$E$35)^171) | KH25: =(1/(1+WACC!$E$34)^120)*(1/(1+WACC!$E$35)^172) | KI25: =(1/(1+WACC!$E$34)^120)*(1/(1+WACC!$E$35)^173) | KJ25: =(1/(1+WACC!$E$34)^120)*(1/(1+WACC!$E$35)^174) | KK25: =(1/(1+WACC!$E$34)^120)*(1/(1+WACC!$E$35)^175) | KL25: =(1/(1+WACC!$E$34)^120)*(1/(1+WACC!$E$35)^176) | KM25: =(1/(1+WACC!$E$34)^120)*(1/(1+WACC!$E$35)^177) | KN25: =(1/(1+WACC!$E$34)^120)*(1/(1+WACC!$E$35)^178) | KO25: =(1/(1+WACC!$E$34)^120)*(1/(1+WACC!$E$35)^179) | KP25: =(1/(1+WACC!$E$34)^120)*(1/(1+WACC!$E$35)^180)
A26: Discounted FCFF | B26: EURk | C26: =C24*C25 | D26: =D24*D25 | E26: =E24*E25 | F26: =F24*F25 | G26: =G24*G25 | H26: =H24*H25 | I26: =I24*I25 | J26: =J24*J25 | ... KP26: =KP24*KP25
A27: Cumulative NPV | B27: EURk | C27: =C26-Assumptions!$E$31 | D27: =C27+D26 | E27: =D27+E26 | F27: =E27+F26 | G27: =F27+G26 | H27: =G27+H26 | I27: =H27+I26 | J27: =I27+J26 | K27: =J27+K26 | ... KP27: =KO27+KP26
A29: P99 — Extreme Stress
A30: Production (MWh) | B30: MWh | C30: =Assumptions!$E$16*(1-Assumptions!$E$23)^0 | D30: =Assumptions!$E$16*(1-Assumptions!$E$23)^0 | E30: =Assumptions!$E$16*(1-Assumptions!$E$23)^0 | F30: =Assumptions!$E$16*(1-Assumptions!$E$23)^0 | G30: =Assumptions!$E$16*(1-Assumptions!$E$23)^0 | H30: =Assumptions!$E$16*(1-Assumptions!$E$23)^0 | I30: =Assumptions!$E$16*(1-Assumptions!$E$23)^0 | J30: =Assumptions!$E$16*(1-Assumptions!$E$23)^0 | ... N30: =Assumptions!$E$16*(1-Assumptions!$E$23)^0 | O30: =Assumptions!$E$16*(1-Assumptions!$E$23)^1 | P30: =Assumptions!$E$16*(1-Assumptions!$E$23)^1 | Q30: =Assumptions!$E$16*(1-Assumptions!$E$23)^1 | R30: =Assumptions!$E$16*(1-Assumptions!$E$23)^1 | S30: =Assumptions!$E$16*(1-Assumptions!$E$23)^1 | T30: =Assumptions!$E$16*(1-Assumptions!$E$23)^1 | U30: =Assumptions!$E$16*(1-Assumptions!$E$23)^1 | V30: =Assumptions!$E$16*(1-Assumptions!$E$23)^1 | ... Z30: =Assumptions!$E$16*(1-Assumptions!$E$23)^1 | AA30: =Assumptions!$E$16*(1-Assumptions!$E$23)^2 | AB30: =Assumptions!$E$16*(1-Assumptions!$E$23)^2 | AC30: =Assumptions!$E$16*(1-Assumptions!$E$23)^2 | AD30: =Assumptions!$E$16*(1-Assumptions!$E$23)^2 | AE30: =Assumptions!$E$16*(1-Assumptions!$E$23)^2 | AF30: =Assumptions!$E$16*(1-Assumptions!$E$23)^2 | AG30: =Assumptions!$E$16*(1-Assumptions!$E$23)^2 | AH30: =Assumptions!$E$16*(1-Assumptions!$E$23)^2 | ... AL30: =Assumptions!$E$16*(1-Assumptions!$E$23)^2 | AM30: =Assumptions!$E$16*(1-Assumptions!$E$23)^3 | AN30: =Assumptions!$E$16*(1-Assumptions!$E$23)^3 | AO30: =Assumptions!$E$16*(1-Assumptions!$E$23)^3 | AP30: =Assumptions!$E$16*(1-Assumptions!$E$23)^3 | AQ30: =Assumptions!$E$16*(1-Assumptions!$E$23)^3 | AR30: =Assumptions!$E$16*(1-Assumptions!$E$23)^3 | AS30: =Assumptions!$E$16*(1-Assumptions!$E$23)^3 | AT30: =Assumptions!$E$16*(1-Assumptions!$E$23)^3 | ... AX30: =Assumptions!$E$16*(1-Assumptions!$E$23)^3 | AY30: =Assumptions!$E$16*(1-Assumptions!$E$23)^4 | AZ30: =Assumptions!$E$16*(1-Assumptions!$E$23)^4 | BA30: =Assumptions!$E$16*(1-Assumptions!$E$23)^4 | BB30: =Assumptions!$E$16*(1-Assumptions!$E$23)^4 | BC30: =Assumptions!$E$16*(1-Assumptions!$E$23)^4 | BD30: =Assumptions!$E$16*(1-Assumptions!$E$23)^4 | BE30: =Assumptions!$E$16*(1-Assumptions!$E$23)^4 | BF30: =Assumptions!$E$16*(1-Assumptions!$E$23)^4 | ... BJ30: =Assumptions!$E$16*(1-Assumptions!$E$23)^4 | BK30: =Assumptions!$E$16*(1-Assumptions!$E$23)^5 | BL30: =Assumptions!$E$16*(1-Assumptions!$E$23)^5 | BM30: =Assumptions!$E$16*(1-Assumptions!$E$23)^5 | BN30: =Assumptions!$E$16*(1-Assumptions!$E$23)^5 | BO30: =Assumptions!$E$16*(1-Assumptions!$E$23)^5 | BP30: =Assumptions!$E$16*(1-Assumptions!$E$23)^5 | BQ30: =Assumptions!$E$16*(1-Assumptions!$E$23)^5 | BR30: =Assumptions!$E$16*(1-Assumptions!$E$23)^5 | ... BV30: =Assumptions!$E$16*(1-Assumptions!$E$23)^5 | BW30: =Assumptions!$E$16*(1-Assumptions!$E$23)^6 | BX30: =Assumptions!$E$16*(1-Assumptions!$E$23)^6 | BY30: =Assumptions!$E$16*(1-Assumptions!$E$23)^6 | BZ30: =Assumptions!$E$16*(1-Assumptions!$E$23)^6 | CA30: =Assumptions!$E$16*(1-Assumptions!$E$23)^6 | CB30: =Assumptions!$E$16*(1-Assumptions!$E$23)^6 | CC30: =Assumptions!$E$16*(1-Assumptions!$E$23)^6 | CD30: =Assumptions!$E$16*(1-Assumptions!$E$23)^6 | ... CH30: =Assumptions!$E$16*(1-Assumptions!$E$23)^6 | CI30: =Assumptions!$E$16*(1-Assumptions!$E$23)^7 | CJ30: =Assumptions!$E$16*(1-Assumptions!$E$23)^7 | CK30: =Assumptions!$E$16*(1-Assumptions!$E$23)^7 | CL30: =Assumptions!$E$16*(1-Assumptions!$E$23)^7 | CM30: =Assumptions!$E$16*(1-Assumptions!$E$23)^7 | CN30: =Assumptions!$E$16*(1-Assumptions!$E$23)^7 | CO30: =Assumptions!$E$16*(1-Assumptions!$E$23)^7 | CP30: =Assumptions!$E$16*(1-Assumptions!$E$23)^7 | ... CT30: =Assumptions!$E$16*(1-Assumptions!$E$23)^7 | CU30: =Assumptions!$E$16*(1-Assumptions!$E$23)^8 | CV30: =Assumptions!$E$16*(1-Assumptions!$E$23)^8 | CW30: =Assumptions!$E$16*(1-Assumptions!$E$23)^8 | CX30: =Assumptions!$E$16*(1-Assumptions!$E$23)^8 | CY30: =Assumptions!$E$16*(1-Assumptions!$E$23)^8 | CZ30: =Assumptions!$E$16*(1-Assumptions!$E$23)^8 | DA30: =Assumptions!$E$16*(1-Assumptions!$E$23)^8 | DB30: =Assumptions!$E$16*(1-Assumptions!$E$23)^8 | ... DF30: =Assumptions!$E$16*(1-Assumptions!$E$23)^8 | DG30: =Assumptions!$E$16*(1-Assumptions!$E$23)^9 | DH30: =Assumptions!$E$16*(1-Assumptions!$E$23)^9 | DI30: =Assumptions!$E$16*(1-Assumptions!$E$23)^9 | DJ30: =Assumptions!$E$16*(1-Assumptions!$E$23)^9 | DK30: =Assumptions!$E$16*(1-Assumptions!$E$23)^9 | DL30: =Assumptions!$E$16*(1-Assumptions!$E$23)^9 | DM30: =Assumptions!$E$16*(1-Assumptions!$E$23)^9 | DN30: =Assumptions!$E$16*(1-Assumptions!$E$23)^9 | ... DR30: =Assumptions!$E$16*(1-Assumptions!$E$23)^9 | DS30: =Assumptions!$E$16*(1-Assumptions!$E$23)^10 | DT30: =Assumptions!$E$16*(1-Assumptions!$E$23)^10 | DU30: =Assumptions!$E$16*(1-Assumptions!$E$23)^10 | DV30: =Assumptions!$E$16*(1-Assumptions!$E$23)^10 | DW30: =Assumptions!$E$16*(1-Assumptions!$E$23)^10 | DX30: =Assumptions!$E$16*(1-Assumptions!$E$23)^10 | DY30: =Assumptions!$E$16*(1-Assumptions!$E$23)^10 | DZ30: =Assumptions!$E$16*(1-Assumptions!$E$23)^10 | ... ED30: =Assumptions!$E$16*(1-Assumptions!$E$23)^10 | EE30: =Assumptions!$E$16*(1-Assumptions!$E$23)^11 | EF30: =Assumptions!$E$16*(1-Assumptions!$E$23)^11 | EG30: =Assumptions!$E$16*(1-Assumptions!$E$23)^11 | EH30: =Assumptions!$E$16*(1-Assumptions!$E$23)^11 | EI30: =Assumptions!$E$16*(1-Assumptions!$E$23)^11 | EJ30: =Assumptions!$E$16*(1-Assumptions!$E$23)^11 | EK30: =Assumptions!$E$16*(1-Assumptions!$E$23)^11 | EL30: =Assumptions!$E$16*(1-Assumptions!$E$23)^11 | ... EP30: =Assumptions!$E$16*(1-Assumptions!$E$23)^11 | EQ30: =Assumptions!$E$16*(1-Assumptions!$E$23)^12 | ER30: =Assumptions!$E$16*(1-Assumptions!$E$23)^12 | ES30: =Assumptions!$E$16*(1-Assumptions!$E$23)^12 | ET30: =Assumptions!$E$16*(1-Assumptions!$E$23)^12 | EU30: =Assumptions!$E$16*(1-Assumptions!$E$23)^12 | EV30: =Assumptions!$E$16*(1-Assumptions!$E$23)^12 | EW30: =Assumptions!$E$16*(1-Assumptions!$E$23)^12 | EX30: =Assumptions!$E$16*(1-Assumptions!$E$23)^12 | ... FB30: =Assumptions!$E$16*(1-Assumptions!$E$23)^12 | FC30: =Assumptions!$E$16*(1-Assumptions!$E$23)^13 | FD30: =Assumptions!$E$16*(1-Assumptions!$E$23)^13 | FE30: =Assumptions!$E$16*(1-Assumptions!$E$23)^13 | FF30: =Assumptions!$E$16*(1-Assumptions!$E$23)^13 | FG30: =Assumptions!$E$16*(1-Assumptions!$E$23)^13 | FH30: =Assumptions!$E$16*(1-Assumptions!$E$23)^13 | FI30: =Assumptions!$E$16*(1-Assumptions!$E$23)^13 | FJ30: =Assumptions!$E$16*(1-Assumptions!$E$23)^13 | ... FN30: =Assumptions!$E$16*(1-Assumptions!$E$23)^13 | FO30: =Assumptions!$E$16*(1-Assumptions!$E$23)^14 | FP30: =Assumptions!$E$16*(1-Assumptions!$E$23)^14 | FQ30: =Assumptions!$E$16*(1-Assumptions!$E$23)^14 | FR30: =Assumptions!$E$16*(1-Assumptions!$E$23)^14 | FS30: =Assumptions!$E$16*(1-Assumptions!$E$23)^14 | FT30: =Assumptions!$E$16*(1-Assumptions!$E$23)^14 | FU30: =Assumptions!$E$16*(1-Assumptions!$E$23)^14 | FV30: =Assumptions!$E$16*(1-Assumptions!$E$23)^14 | ... FZ30: =Assumptions!$E$16*(1-Assumptions!$E$23)^14 | GA30: =Assumptions!$E$16*(1-Assumptions!$E$23)^15 | GB30: =Assumptions!$E$16*(1-Assumptions!$E$23)^15 | GC30: =Assumptions!$E$16*(1-Assumptions!$E$23)^15 | GD30: =Assumptions!$E$16*(1-Assumptions!$E$23)^15 | GE30: =Assumptions!$E$16*(1-Assumptions!$E$23)^15 | GF30: =Assumptions!$E$16*(1-Assumptions!$E$23)^15 | GG30: =Assumptions!$E$16*(1-Assumptions!$E$23)^15 | GH30: =Assumptions!$E$16*(1-Assumptions!$E$23)^15 | ... GL30: =Assumptions!$E$16*(1-Assumptions!$E$23)^15 | GM30: =Assumptions!$E$16*(1-Assumptions!$E$23)^16 | GN30: =Assumptions!$E$16*(1-Assumptions!$E$23)^16 | GO30: =Assumptions!$E$16*(1-Assumptions!$E$23)^16 | GP30: =Assumptions!$E$16*(1-Assumptions!$E$23)^16 | GQ30: =Assumptions!$E$16*(1-Assumptions!$E$23)^16 | GR30: =Assumptions!$E$16*(1-Assumptions!$E$23)^16 | GS30: =Assumptions!$E$16*(1-Assumptions!$E$23)^16 | GT30: =Assumptions!$E$16*(1-Assumptions!$E$23)^16 | ... GX30: =Assumptions!$E$16*(1-Assumptions!$E$23)^16 | GY30: =Assumptions!$E$16*(1-Assumptions!$E$23)^17 | GZ30: =Assumptions!$E$16*(1-Assumptions!$E$23)^17 | HA30: =Assumptions!$E$16*(1-Assumptions!$E$23)^17 | HB30: =Assumptions!$E$16*(1-Assumptions!$E$23)^17 | HC30: =Assumptions!$E$16*(1-Assumptions!$E$23)^17 | HD30: =Assumptions!$E$16*(1-Assumptions!$E$23)^17 | HE30: =Assumptions!$E$16*(1-Assumptions!$E$23)^17 | HF30: =Assumptions!$E$16*(1-Assumptions!$E$23)^17 | ... HJ30: =Assumptions!$E$16*(1-Assumptions!$E$23)^17 | HK30: =Assumptions!$E$16*(1-Assumptions!$E$23)^18 | HL30: =Assumptions!$E$16*(1-Assumptions!$E$23)^18 | HM30: =Assumptions!$E$16*(1-Assumptions!$E$23)^18 | HN30: =Assumptions!$E$16*(1-Assumptions!$E$23)^18 | HO30: =Assumptions!$E$16*(1-Assumptions!$E$23)^18 | HP30: =Assumptions!$E$16*(1-Assumptions!$E$23)^18 | HQ30: =Assumptions!$E$16*(1-Assumptions!$E$23)^18 | HR30: =Assumptions!$E$16*(1-Assumptions!$E$23)^18 | ... HV30: =Assumptions!$E$16*(1-Assumptions!$E$23)^18 | HW30: =Assumptions!$E$16*(1-Assumptions!$E$23)^19 | HX30: =Assumptions!$E$16*(1-Assumptions!$E$23)^19 | HY30: =Assumptions!$E$16*(1-Assumptions!$E$23)^19 | HZ30: =Assumptions!$E$16*(1-Assumptions!$E$23)^19 | IA30: =Assumptions!$E$16*(1-Assumptions!$E$23)^19 | IB30: =Assumptions!$E$16*(1-Assumptions!$E$23)^19 | IC30: =Assumptions!$E$16*(1-Assumptions!$E$23)^19 | ID30: =Assumptions!$E$16*(1-Assumptions!$E$23)^19 | ... IH30: =Assumptions!$E$16*(1-Assumptions!$E$23)^19 | II30: =Assumptions!$E$16*(1-Assumptions!$E$23)^20 | IJ30: =Assumptions!$E$16*(1-Assumptions!$E$23)^20 | IK30: =Assumptions!$E$16*(1-Assumptions!$E$23)^20 | IL30: =Assumptions!$E$16*(1-Assumptions!$E$23)^20 | IM30: =Assumptions!$E$16*(1-Assumptions!$E$23)^20 | IN30: =Assumptions!$E$16*(1-Assumptions!$E$23)^20 | IO30: =Assumptions!$E$16*(1-Assumptions!$E$23)^20 | IP30: =Assumptions!$E$16*(1-Assumptions!$E$23)^20 | ... IT30: =Assumptions!$E$16*(1-Assumptions!$E$23)^20 | IU30: =Assumptions!$E$16*(1-Assumptions!$E$23)^21 | IV30: =Assumptions!$E$16*(1-Assumptions!$E$23)^21 | IW30: =Assumptions!$E$16*(1-Assumptions!$E$23)^21 | IX30: =Assumptions!$E$16*(1-Assumptions!$E$23)^21 | IY30: =Assumptions!$E$16*(1-Assumptions!$E$23)^21 | IZ30: =Assumptions!$E$16*(1-Assumptions!$E$23)^21 | JA30: =Assumptions!$E$16*(1-Assumptions!$E$23)^21 | JB30: =Assumptions!$E$16*(1-Assumptions!$E$23)^21 | ... JF30: =Assumptions!$E$16*(1-Assumptions!$E$23)^21 | JG30: =Assumptions!$E$16*(1-Assumptions!$E$23)^22 | JH30: =Assumptions!$E$16*(1-Assumptions!$E$23)^22 | JI30: =Assumptions!$E$16*(1-Assumptions!$E$23)^22 | JJ30: =Assumptions!$E$16*(1-Assumptions!$E$23)^22 | JK30: =Assumptions!$E$16*(1-Assumptions!$E$23)^22 | JL30: =Assumptions!$E$16*(1-Assumptions!$E$23)^22 | JM30: =Assumptions!$E$16*(1-Assumptions!$E$23)^22 | JN30: =Assumptions!$E$16*(1-Assumptions!$E$23)^22 | ... JR30: =Assumptions!$E$16*(1-Assumptions!$E$23)^22 | JS30: =Assumptions!$E$16*(1-Assumptions!$E$23)^23 | JT30: =Assumptions!$E$16*(1-Assumptions!$E$23)^23 | JU30: =Assumptions!$E$16*(1-Assumptions!$E$23)^23 | JV30: =Assumptions!$E$16*(1-Assumptions!$E$23)^23 | JW30: =Assumptions!$E$16*(1-Assumptions!$E$23)^23 | JX30: =Assumptions!$E$16*(1-Assumptions!$E$23)^23 | JY30: =Assumptions!$E$16*(1-Assumptions!$E$23)^23 | JZ30: =Assumptions!$E$16*(1-Assumptions!$E$23)^23 | ... KD30: =Assumptions!$E$16*(1-Assumptions!$E$23)^23 | KE30: =Assumptions!$E$16*(1-Assumptions!$E$23)^24 | KF30: =Assumptions!$E$16*(1-Assumptions!$E$23)^24 | KG30: =Assumptions!$E$16*(1-Assumptions!$E$23)^24 | KH30: =Assumptions!$E$16*(1-Assumptions!$E$23)^24 | KI30: =Assumptions!$E$16*(1-Assumptions!$E$23)^24 | KJ30: =Assumptions!$E$16*(1-Assumptions!$E$23)^24 | KK30: =Assumptions!$E$16*(1-Assumptions!$E$23)^24 | KL30: =Assumptions!$E$16*(1-Assumptions!$E$23)^24 | ... KP30: =Assumptions!$E$16*(1-Assumptions!$E$23)^24
A31: Price (EUR/MWh) | B31: EUR/MWh | C31: =Assumptions!$E$40 | D31: =Assumptions!$E$40 | E31: =Assumptions!$E$40 | F31: =Assumptions!$E$40 | G31: =Assumptions!$E$40 | H31: =Assumptions!$E$40 | I31: =Assumptions!$E$40 | J31: =Assumptions!$E$40 | ... DR31: =Assumptions!$E$40 | DS31: =Simulation!$J$127 | DT31: =Simulation!$J$128 | DU31: =Simulation!$J$129 | DV31: =Simulation!$J$130 | DW31: =Simulation!$J$131 | DX31: =Simulation!$J$132 | DY31: =Simulation!$J$133 | DZ31: =Simulation!$J$134 | EA31: =Simulation!$J$135 | EB31: =Simulation!$J$136 | EC31: =Simulation!$J$137 | ED31: =Simulation!$J$138 | EE31: =Simulation!$J$139 | EF31: =Simulation!$J$140 | EG31: =Simulation!$J$141 | EH31: =Simulation!$J$142 | EI31: =Simulation!$J$143 | EJ31: =Simulation!$J$144 | EK31: =Simulation!$J$145 | EL31: =Simulation!$J$146 | EM31: =Simulation!$J$147 | EN31: =Simulation!$J$148 | EO31: =Simulation!$J$149 | EP31: =Simulation!$J$150 | EQ31: =Simulation!$J$151 | ER31: =Simulation!$J$152 | ES31: =Simulation!$J$153 | ET31: =Simulation!$J$154 | EU31: =Simulation!$J$155 | EV31: =Simulation!$J$156 | EW31: =Simulation!$J$157 | EX31: =Simulation!$J$158 | EY31: =Simulation!$J$159 | EZ31: =Simulation!$J$160 | FA31: =Simulation!$J$161 | FB31: =Simulation!$J$162 | FC31: =Simulation!$J$163 | FD31: =Simulation!$J$164 | FE31: =Simulation!$J$165 | FF31: =Simulation!$J$166 | FG31: =Simulation!$J$167 | FH31: =Simulation!$J$168 | FI31: =Simulation!$J$169 | FJ31: =Simulation!$J$170 | FK31: =Simulation!$J$171 | FL31: =Simulation!$J$172 | FM31: =Simulation!$J$173 | FN31: =Simulation!$J$174 | FO31: =Simulation!$J$175 | FP31: =Simulation!$J$176 | FQ31: =Simulation!$J$177 | FR31: =Simulation!$J$178 | FS31: =Simulation!$J$179 | FT31: =Simulation!$J$180 | FU31: =Simulation!$J$181 | FV31: =Simulation!$J$182 | FW31: =Simulation!$J$183 | FX31: =Simulation!$J$184 | FY31: =Simulation!$J$185 | FZ31: =Simulation!$J$186 | GA31: =Simulation!$J$187 | GB31: =Simulation!$J$188 | GC31: =Simulation!$J$189 | GD31: =Simulation!$J$190 | GE31: =Simulation!$J$191 | GF31: =Simulation!$J$192 | GG31: =Simulation!$J$193 | GH31: =Simulation!$J$194 | GI31: =Simulation!$J$195 | GJ31: =Simulation!$J$196 | GK31: =Simulation!$J$197 | GL31: =Simulation!$J$198 | GM31: =Simulation!$J$199 | GN31: =Simulation!$J$200 | GO31: =Simulation!$J$201 | GP31: =Simulation!$J$202 | GQ31: =Simulation!$J$203 | GR31: =Simulation!$J$204 | GS31: =Simulation!$J$205 | GT31: =Simulation!$J$206 | GU31: =Simulation!$J$207 | GV31: =Simulation!$J$208 | GW31: =Simulation!$J$209 | GX31: =Simulation!$J$210 | GY31: =Simulation!$J$211 | GZ31: =Simulation!$J$212 | HA31: =Simulation!$J$213 | HB31: =Simulation!$J$214 | HC31: =Simulation!$J$215 | HD31: =Simulation!$J$216 | HE31: =Simulation!$J$217 | HF31: =Simulation!$J$218 | HG31: =Simulation!$J$219 | HH31: =Simulation!$J$220 | HI31: =Simulation!$J$221 | HJ31: =Simulation!$J$222 | HK31: =Simulation!$J$223 | HL31: =Simulation!$J$224 | HM31: =Simulation!$J$225 | HN31: =Simulation!$J$226 | HO31: =Simulation!$J$227 | HP31: =Simulation!$J$228 | HQ31: =Simulation!$J$229 | HR31: =Simulation!$J$230 | HS31: =Simulation!$J$231 | HT31: =Simulation!$J$232 | HU31: =Simulation!$J$233 | HV31: =Simulation!$J$234 | HW31: =Simulation!$J$235 | HX31: =Simulation!$J$236 | HY31: =Simulation!$J$237 | HZ31: =Simulation!$J$238 | IA31: =Simulation!$J$239 | IB31: =Simulation!$J$240 | IC31: =Simulation!$J$241 | ID31: =Simulation!$J$242 | IE31: =Simulation!$J$243 | IF31: =Simulation!$J$244 | IG31: =Simulation!$J$245 | IH31: =Simulation!$J$246 | II31: =Simulation!$J$247 | IJ31: =Simulation!$J$248 | IK31: =Simulation!$J$249 | IL31: =Simulation!$J$250 | IM31: =Simulation!$J$251 | IN31: =Simulation!$J$252 | IO31: =Simulation!$J$253 | IP31: =Simulation!$J$254 | IQ31: =Simulation!$J$255 | IR31: =Simulation!$J$256 | IS31: =Simulation!$J$257 | IT31: =Simulation!$J$258 | IU31: =Simulation!$J$259 | IV31: =Simulation!$J$260 | IW31: =Simulation!$J$261 | IX31: =Simulation!$J$262 | IY31: =Simulation!$J$263 | IZ31: =Simulation!$J$264 | JA31: =Simulation!$J$265 | JB31: =Simulation!$J$266 | JC31: =Simulation!$J$267 | JD31: =Simulation!$J$268 | JE31: =Simulation!$J$269 | JF31: =Simulation!$J$270 | JG31: =Simulation!$J$271 | JH31: =Simulation!$J$272 | JI31: =Simulation!$J$273 | JJ31: =Simulation!$J$274 | JK31: =Simulation!$J$275 | JL31: =Simulation!$J$276 | JM31: =Simulation!$J$277 | JN31: =Simulation!$J$278 | JO31: =Simulation!$J$279 | JP31: =Simulation!$J$280 | JQ31: =Simulation!$J$281 | JR31: =Simulation!$J$282 | JS31: =Simulation!$J$283 | JT31: =Simulation!$J$284 | JU31: =Simulation!$J$285 | JV31: =Simulation!$J$286 | JW31: =Simulation!$J$287 | JX31: =Simulation!$J$288 | JY31: =Simulation!$J$289 | JZ31: =Simulation!$J$290 | KA31: =Simulation!$J$291 | KB31: =Simulation!$J$292 | KC31: =Simulation!$J$293 | KD31: =Simulation!$J$294 | KE31: =Simulation!$J$295 | KF31: =Simulation!$J$296 | KG31: =Simulation!$J$297 | KH31: =Simulation!$J$298 | KI31: =Simulation!$J$299 | KJ31: =Simulation!$J$300 | KK31: =Simulation!$J$301 | KL31: =Simulation!$J$302 | KM31: =Simulation!$J$303 | KN31: =Simulation!$J$304 | KO31: =Simulation!$J$305 | KP31: =Simulation!$J$306
A32: Revenue (EURk) | B32: EURk | C32: =C30*C31/1000 | D32: =D30*D31/1000 | E32: =E30*E31/1000 | F32: =F30*F31/1000 | G32: =G30*G31/1000 | H32: =H30*H31/1000 | I32: =I30*I31/1000 | J32: =J30*J31/1000 | ... KP32: =KP30*KP31/1000
A33: OPEX (EURk) | B33: EURk | C33: =-Assumptions!$E$35*(1+Assumptions!$E$36)^0/12 | D33: =-Assumptions!$E$35*(1+Assumptions!$E$36)^0/12 | E33: =-Assumptions!$E$35*(1+Assumptions!$E$36)^0/12 | F33: =-Assumptions!$E$35*(1+Assumptions!$E$36)^0/12 | G33: =-Assumptions!$E$35*(1+Assumptions!$E$36)^0/12 | H33: =-Assumptions!$E$35*(1+Assumptions!$E$36)^0/12 | I33: =-Assumptions!$E$35*(1+Assumptions!$E$36)^0/12 | J33: =-Assumptions!$E$35*(1+Assumptions!$E$36)^0/12 | ... N33: =-Assumptions!$E$35*(1+Assumptions!$E$36)^0/12 | O33: =-Assumptions!$E$35*(1+Assumptions!$E$36)^1/12 | P33: =-Assumptions!$E$35*(1+Assumptions!$E$36)^1/12 | Q33: =-Assumptions!$E$35*(1+Assumptions!$E$36)^1/12 | R33: =-Assumptions!$E$35*(1+Assumptions!$E$36)^1/12 | S33: =-Assumptions!$E$35*(1+Assumptions!$E$36)^1/12 | T33: =-Assumptions!$E$35*(1+Assumptions!$E$36)^1/12 | U33: =-Assumptions!$E$35*(1+Assumptions!$E$36)^1/12 | V33: =-Assumptions!$E$35*(1+Assumptions!$E$36)^1/12 | ... Z33: =-Assumptions!$E$35*(1+Assumptions!$E$36)^1/12 | AA33: =-Assumptions!$E$35*(1+Assumptions!$E$36)^2/12 | AB33: =-Assumptions!$E$35*(1+Assumptions!$E$36)^2/12 | AC33: =-Assumptions!$E$35*(1+Assumptions!$E$36)^2/12 | AD33: =-Assumptions!$E$35*(1+Assumptions!$E$36)^2/12 | AE33: =-Assumptions!$E$35*(1+Assumptions!$E$36)^2/12 | AF33: =-Assumptions!$E$35*(1+Assumptions!$E$36)^2/12 | AG33: =-Assumptions!$E$35*(1+Assumptions!$E$36)^2/12 | AH33: =-Assumptions!$E$35*(1+Assumptions!$E$36)^2/12 | ... AL33: =-Assumptions!$E$35*(1+Assumptions!$E$36)^2/12 | AM33: =-Assumptions!$E$35*(1+Assumptions!$E$36)^3/12 | AN33: =-Assumptions!$E$35*(1+Assumptions!$E$36)^3/12 | AO33: =-Assumptions!$E$35*(1+Assumptions!$E$36)^3/12 | AP33: =-Assumptions!$E$35*(1+Assumptions!$E$36)^3/12 | AQ33: =-Assumptions!$E$35*(1+Assumptions!$E$36)^3/12 | AR33: =-Assumptions!$E$35*(1+Assumptions!$E$36)^3/12 | AS33: =-Assumptions!$E$35*(1+Assumptions!$E$36)^3/12 | AT33: =-Assumptions!$E$35*(1+Assumptions!$E$36)^3/12 | ... AX33: =-Assumptions!$E$35*(1+Assumptions!$E$36)^3/12 | AY33: =-Assumptions!$E$35*(1+Assumptions!$E$36)^4/12 | AZ33: =-Assumptions!$E$35*(1+Assumptions!$E$36)^4/12 | BA33: =-Assumptions!$E$35*(1+Assumptions!$E$36)^4/12 | BB33: =-Assumptions!$E$35*(1+Assumptions!$E$36)^4/12 | BC33: =-Assumptions!$E$35*(1+Assumptions!$E$36)^4/12 | BD33: =-Assumptions!$E$35*(1+Assumptions!$E$36)^4/12 | BE33: =-Assumptions!$E$35*(1+Assumptions!$E$36)^4/12 | BF33: =-Assumptions!$E$35*(1+Assumptions!$E$36)^4/12 | ... BJ33: =-Assumptions!$E$35*(1+Assumptions!$E$36)^4/12 | BK33: =-Assumptions!$E$35*(1+Assumptions!$E$36)^5/12 | BL33: =-Assumptions!$E$35*(1+Assumptions!$E$36)^5/12 | BM33: =-Assumptions!$E$35*(1+Assumptions!$E$36)^5/12 | BN33: =-Assumptions!$E$35*(1+Assumptions!$E$36)^5/12 | BO33: =-Assumptions!$E$35*(1+Assumptions!$E$36)^5/12 | BP33: =-Assumptions!$E$35*(1+Assumptions!$E$36)^5/12 | BQ33: =-Assumptions!$E$35*(1+Assumptions!$E$36)^5/12 | BR33: =-Assumptions!$E$35*(1+Assumptions!$E$36)^5/12 | ... BV33: =-Assumptions!$E$35*(1+Assumptions!$E$36)^5/12 | BW33: =-Assumptions!$E$35*(1+Assumptions!$E$36)^6/12 | BX33: =-Assumptions!$E$35*(1+Assumptions!$E$36)^6/12 | BY33: =-Assumptions!$E$35*(1+Assumptions!$E$36)^6/12 | BZ33: =-Assumptions!$E$35*(1+Assumptions!$E$36)^6/12 | CA33: =-Assumptions!$E$35*(1+Assumptions!$E$36)^6/12 | CB33: =-Assumptions!$E$35*(1+Assumptions!$E$36)^6/12 | CC33: =-Assumptions!$E$35*(1+Assumptions!$E$36)^6/12 | CD33: =-Assumptions!$E$35*(1+Assumptions!$E$36)^6/12 | ... CH33: =-Assumptions!$E$35*(1+Assumptions!$E$36)^6/12 | CI33: =-Assumptions!$E$35*(1+Assumptions!$E$36)^7/12 | CJ33: =-Assumptions!$E$35*(1+Assumptions!$E$36)^7/12 | CK33: =-Assumptions!$E$35*(1+Assumptions!$E$36)^7/12 | CL33: =-Assumptions!$E$35*(1+Assumptions!$E$36)^7/12 | CM33: =-Assumptions!$E$35*(1+Assumptions!$E$36)^7/12 | CN33: =-Assumptions!$E$35*(1+Assumptions!$E$36)^7/12 | CO33: =-Assumptions!$E$35*(1+Assumptions!$E$36)^7/12 | CP33: =-Assumptions!$E$35*(1+Assumptions!$E$36)^7/12 | ... CT33: =-Assumptions!$E$35*(1+Assumptions!$E$36)^7/12 | CU33: =-Assumptions!$E$35*(1+Assumptions!$E$36)^8/12 | CV33: =-Assumptions!$E$35*(1+Assumptions!$E$36)^8/12 | CW33: =-Assumptions!$E$35*(1+Assumptions!$E$36)^8/12 | CX33: =-Assumptions!$E$35*(1+Assumptions!$E$36)^8/12 | CY33: =-Assumptions!$E$35*(1+Assumptions!$E$36)^8/12 | CZ33: =-Assumptions!$E$35*(1+Assumptions!$E$36)^8/12 | DA33: =-Assumptions!$E$35*(1+Assumptions!$E$36)^8/12 | DB33: =-Assumptions!$E$35*(1+Assumptions!$E$36)^8/12 | ... DF33: =-Assumptions!$E$35*(1+Assumptions!$E$36)^8/12 | DG33: =-Assumptions!$E$35*(1+Assumptions!$E$36)^9/12 | DH33: =-Assumptions!$E$35*(1+Assumptions!$E$36)^9/12 | DI33: =-Assumptions!$E$35*(1+Assumptions!$E$36)^9/12 | DJ33: =-Assumptions!$E$35*(1+Assumptions!$E$36)^9/12 | DK33: =-Assumptions!$E$35*(1+Assumptions!$E$36)^9/12 | DL33: =-Assumptions!$E$35*(1+Assumptions!$E$36)^9/12 | DM33: =-Assumptions!$E$35*(1+Assumptions!$E$36)^9/12 | DN33: =-Assumptions!$E$35*(1+Assumptions!$E$36)^9/12 | ... DR33: =-Assumptions!$E$35*(1+Assumptions!$E$36)^9/12 | DS33: =-Assumptions!$E$35*(1+Assumptions!$E$36)^10/12 | DT33: =-Assumptions!$E$35*(1+Assumptions!$E$36)^10/12 | DU33: =-Assumptions!$E$35*(1+Assumptions!$E$36)^10/12 | DV33: =-Assumptions!$E$35*(1+Assumptions!$E$36)^10/12 | DW33: =-Assumptions!$E$35*(1+Assumptions!$E$36)^10/12 | DX33: =-Assumptions!$E$35*(1+Assumptions!$E$36)^10/12 | DY33: =-Assumptions!$E$35*(1+Assumptions!$E$36)^10/12 | DZ33: =-Assumptions!$E$35*(1+Assumptions!$E$36)^10/12 | ... ED33: =-Assumptions!$E$35*(1+Assumptions!$E$36)^10/12 | EE33: =-Assumptions!$E$35*(1+Assumptions!$E$36)^11/12 | EF33: =-Assumptions!$E$35*(1+Assumptions!$E$36)^11/12 | EG33: =-Assumptions!$E$35*(1+Assumptions!$E$36)^11/12 | EH33: =-Assumptions!$E$35*(1+Assumptions!$E$36)^11/12 | EI33: =-Assumptions!$E$35*(1+Assumptions!$E$36)^11/12 | EJ33: =-Assumptions!$E$35*(1+Assumptions!$E$36)^11/12 | EK33: =-Assumptions!$E$35*(1+Assumptions!$E$36)^11/12 | EL33: =-Assumptions!$E$35*(1+Assumptions!$E$36)^11/12 | ... EP33: =-Assumptions!$E$35*(1+Assumptions!$E$36)^11/12 | EQ33: =-Assumptions!$E$35*(1+Assumptions!$E$36)^12/12 | ER33: =-Assumptions!$E$35*(1+Assumptions!$E$36)^12/12 | ES33: =-Assumptions!$E$35*(1+Assumptions!$E$36)^12/12 | ET33: =-Assumptions!$E$35*(1+Assumptions!$E$36)^12/12 | EU33: =-Assumptions!$E$35*(1+Assumptions!$E$36)^12/12 | EV33: =-Assumptions!$E$35*(1+Assumptions!$E$36)^12/12 | EW33: =-Assumptions!$E$35*(1+Assumptions!$E$36)^12/12 | EX33: =-Assumptions!$E$35*(1+Assumptions!$E$36)^12/12 | ... FB33: =-Assumptions!$E$35*(1+Assumptions!$E$36)^12/12 | FC33: =-Assumptions!$E$35*(1+Assumptions!$E$36)^13/12 | FD33: =-Assumptions!$E$35*(1+Assumptions!$E$36)^13/12 | FE33: =-Assumptions!$E$35*(1+Assumptions!$E$36)^13/12 | FF33: =-Assumptions!$E$35*(1+Assumptions!$E$36)^13/12 | FG33: =-Assumptions!$E$35*(1+Assumptions!$E$36)^13/12 | FH33: =-Assumptions!$E$35*(1+Assumptions!$E$36)^13/12 | FI33: =-Assumptions!$E$35*(1+Assumptions!$E$36)^13/12 | FJ33: =-Assumptions!$E$35*(1+Assumptions!$E$36)^13/12 | ... FN33: =-Assumptions!$E$35*(1+Assumptions!$E$36)^13/12 | FO33: =-Assumptions!$E$35*(1+Assumptions!$E$36)^14/12 | FP33: =-Assumptions!$E$35*(1+Assumptions!$E$36)^14/12 | FQ33: =-Assumptions!$E$35*(1+Assumptions!$E$36)^14/12 | FR33: =-Assumptions!$E$35*(1+Assumptions!$E$36)^14/12 | FS33: =-Assumptions!$E$35*(1+Assumptions!$E$36)^14/12 | FT33: =-Assumptions!$E$35*(1+Assumptions!$E$36)^14/12 | FU33: =-Assumptions!$E$35*(1+Assumptions!$E$36)^14/12 | FV33: =-Assumptions!$E$35*(1+Assumptions!$E$36)^14/12 | ... FZ33: =-Assumptions!$E$35*(1+Assumptions!$E$36)^14/12 | GA33: =-Assumptions!$E$35*(1+Assumptions!$E$36)^15/12 | GB33: =-Assumptions!$E$35*(1+Assumptions!$E$36)^15/12 | GC33: =-Assumptions!$E$35*(1+Assumptions!$E$36)^15/12 | GD33: =-Assumptions!$E$35*(1+Assumptions!$E$36)^15/12 | GE33: =-Assumptions!$E$35*(1+Assumptions!$E$36)^15/12 | GF33: =-Assumptions!$E$35*(1+Assumptions!$E$36)^15/12 | GG33: =-Assumptions!$E$35*(1+Assumptions!$E$36)^15/12 | GH33: =-Assumptions!$E$35*(1+Assumptions!$E$36)^15/12 | ... GL33: =-Assumptions!$E$35*(1+Assumptions!$E$36)^15/12 | GM33: =-Assumptions!$E$35*(1+Assumptions!$E$36)^16/12 | GN33: =-Assumptions!$E$35*(1+Assumptions!$E$36)^16/12 | GO33: =-Assumptions!$E$35*(1+Assumptions!$E$36)^16/12 | GP33: =-Assumptions!$E$35*(1+Assumptions!$E$36)^16/12 | GQ33: =-Assumptions!$E$35*(1+Assumptions!$E$36)^16/12 | GR33: =-Assumptions!$E$35*(1+Assumptions!$E$36)^16/12 | GS33: =-Assumptions!$E$35*(1+Assumptions!$E$36)^16/12 | GT33: =-Assumptions!$E$35*(1+Assumptions!$E$36)^16/12 | ... GX33: =-Assumptions!$E$35*(1+Assumptions!$E$36)^16/12 | GY33: =-Assumptions!$E$35*(1+Assumptions!$E$36)^17/12 | GZ33: =-Assumptions!$E$35*(1+Assumptions!$E$36)^17/12 | HA33: =-Assumptions!$E$35*(1+Assumptions!$E$36)^17/12 | HB33: =-Assumptions!$E$35*(1+Assumptions!$E$36)^17/12 | HC33: =-Assumptions!$E$35*(1+Assumptions!$E$36)^17/12 | HD33: =-Assumptions!$E$35*(1+Assumptions!$E$36)^17/12 | HE33: =-Assumptions!$E$35*(1+Assumptions!$E$36)^17/12 | HF33: =-Assumptions!$E$35*(1+Assumptions!$E$36)^17/12 | ... HJ33: =-Assumptions!$E$35*(1+Assumptions!$E$36)^17/12 | HK33: =-Assumptions!$E$35*(1+Assumptions!$E$36)^18/12 | HL33: =-Assumptions!$E$35*(1+Assumptions!$E$36)^18/12 | HM33: =-Assumptions!$E$35*(1+Assumptions!$E$36)^18/12 | HN33: =-Assumptions!$E$35*(1+Assumptions!$E$36)^18/12 | HO33: =-Assumptions!$E$35*(1+Assumptions!$E$36)^18/12 | HP33: =-Assumptions!$E$35*(1+Assumptions!$E$36)^18/12 | HQ33: =-Assumptions!$E$35*(1+Assumptions!$E$36)^18/12 | HR33: =-Assumptions!$E$35*(1+Assumptions!$E$36)^18/12 | ... HV33: =-Assumptions!$E$35*(1+Assumptions!$E$36)^18/12 | HW33: =-Assumptions!$E$35*(1+Assumptions!$E$36)^19/12 | HX33: =-Assumptions!$E$35*(1+Assumptions!$E$36)^19/12 | HY33: =-Assumptions!$E$35*(1+Assumptions!$E$36)^19/12 | HZ33: =-Assumptions!$E$35*(1+Assumptions!$E$36)^19/12 | IA33: =-Assumptions!$E$35*(1+Assumptions!$E$36)^19/12 | IB33: =-Assumptions!$E$35*(1+Assumptions!$E$36)^19/12 | IC33: =-Assumptions!$E$35*(1+Assumptions!$E$36)^19/12 | ID33: =-Assumptions!$E$35*(1+Assumptions!$E$36)^19/12 | ... IH33: =-Assumptions!$E$35*(1+Assumptions!$E$36)^19/12 | II33: =-Assumptions!$E$35*(1+Assumptions!$E$36)^20/12 | IJ33: =-Assumptions!$E$35*(1+Assumptions!$E$36)^20/12 | IK33: =-Assumptions!$E$35*(1+Assumptions!$E$36)^20/12 | IL33: =-Assumptions!$E$35*(1+Assumptions!$E$36)^20/12 | IM33: =-Assumptions!$E$35*(1+Assumptions!$E$36)^20/12 | IN33: =-Assumptions!$E$35*(1+Assumptions!$E$36)^20/12 | IO33: =-Assumptions!$E$35*(1+Assumptions!$E$36)^20/12 | IP33: =-Assumptions!$E$35*(1+Assumptions!$E$36)^20/12 | ... IT33: =-Assumptions!$E$35*(1+Assumptions!$E$36)^20/12 | IU33: =-Assumptions!$E$35*(1+Assumptions!$E$36)^21/12 | IV33: =-Assumptions!$E$35*(1+Assumptions!$E$36)^21/12 | IW33: =-Assumptions!$E$35*(1+Assumptions!$E$36)^21/12 | IX33: =-Assumptions!$E$35*(1+Assumptions!$E$36)^21/12 | IY33: =-Assumptions!$E$35*(1+Assumptions!$E$36)^21/12 | IZ33: =-Assumptions!$E$35*(1+Assumptions!$E$36)^21/12 | JA33: =-Assumptions!$E$35*(1+Assumptions!$E$36)^21/12 | JB33: =-Assumptions!$E$35*(1+Assumptions!$E$36)^21/12 | ... JF33: =-Assumptions!$E$35*(1+Assumptions!$E$36)^21/12 | JG33: =-Assumptions!$E$35*(1+Assumptions!$E$36)^22/12 | JH33: =-Assumptions!$E$35*(1+Assumptions!$E$36)^22/12 | JI33: =-Assumptions!$E$35*(1+Assumptions!$E$36)^22/12 | JJ33: =-Assumptions!$E$35*(1+Assumptions!$E$36)^22/12 | JK33: =-Assumptions!$E$35*(1+Assumptions!$E$36)^22/12 | JL33: =-Assumptions!$E$35*(1+Assumptions!$E$36)^22/12 | JM33: =-Assumptions!$E$35*(1+Assumptions!$E$36)^22/12 | JN33: =-Assumptions!$E$35*(1+Assumptions!$E$36)^22/12 | ... JR33: =-Assumptions!$E$35*(1+Assumptions!$E$36)^22/12 | JS33: =-Assumptions!$E$35*(1+Assumptions!$E$36)^23/12 | JT33: =-Assumptions!$E$35*(1+Assumptions!$E$36)^23/12 | JU33: =-Assumptions!$E$35*(1+Assumptions!$E$36)^23/12 | JV33: =-Assumptions!$E$35*(1+Assumptions!$E$36)^23/12 | JW33: =-Assumptions!$E$35*(1+Assumptions!$E$36)^23/12 | JX33: =-Assumptions!$E$35*(1+Assumptions!$E$36)^23/12 | JY33: =-Assumptions!$E$35*(1+Assumptions!$E$36)^23/12 | JZ33: =-Assumptions!$E$35*(1+Assumptions!$E$36)^23/12 | ... KD33: =-Assumptions!$E$35*(1+Assumptions!$E$36)^23/12 | KE33: =-Assumptions!$E$35*(1+Assumptions!$E$36)^24/12 | KF33: =-Assumptions!$E$35*(1+Assumptions!$E$36)^24/12 | KG33: =-Assumptions!$E$35*(1+Assumptions!$E$36)^24/12 | KH33: =-Assumptions!$E$35*(1+Assumptions!$E$36)^24/12 | KI33: =-Assumptions!$E$35*(1+Assumptions!$E$36)^24/12 | KJ33: =-Assumptions!$E$35*(1+Assumptions!$E$36)^24/12 | KK33: =-Assumptions!$E$35*(1+Assumptions!$E$36)^24/12 | KL33: =-Assumptions!$E$35*(1+Assumptions!$E$36)^24/12 | ... KP33: =-Assumptions!$E$35*(1+Assumptions!$E$36)^24/12
A34: EBITDA (EURk) | B34: EURk | C34: =C32+C33 | D34: =D32+D33 | E34: =E32+E33 | F34: =F32+F33 | G34: =G32+G33 | H34: =H32+H33 | I34: =I32+I33 | J34: =J32+J33 | ... KP34: =KP32+KP33
A35: Tax (EURk) | B35: EURk | C35: =IF(C34>0,-C34*Assumptions!$E$47,0) | D35: =IF(D34>0,-D34*Assumptions!$E$47,0) | E35: =IF(E34>0,-E34*Assumptions!$E$47,0) | F35: =IF(F34>0,-F34*Assumptions!$E$47,0) | G35: =IF(G34>0,-G34*Assumptions!$E$47,0) | H35: =IF(H34>0,-H34*Assumptions!$E$47,0) | I35: =IF(I34>0,-I34*Assumptions!$E$47,0) | J35: =IF(J34>0,-J34*Assumptions!$E$47,0) | ... KP35: =IF(KP34>0,-KP34*Assumptions!$E$47,0)
A36: FCFF (EURk) | B36: EURk | C36: =C34+C35 | D36: =D34+D35 | E36: =E34+E35 | F36: =F34+F35 | G36: =G34+G35 | H36: =H34+H35 | I36: =I34+I35 | J36: =J34+J35 | ... KP36: =KP34+KP35
A37: Discount Factor | B37: - | C37: =1/(1+WACC!$E$34)^1 | D37: =1/(1+WACC!$E$34)^2 | E37: =1/(1+WACC!$E$34)^3 | F37: =1/(1+WACC!$E$34)^4 | G37: =1/(1+WACC!$E$34)^5 | H37: =1/(1+WACC!$E$34)^6 | I37: =1/(1+WACC!$E$34)^7 | J37: =1/(1+WACC!$E$34)^8 | K37: =1/(1+WACC!$E$34)^9 | L37: =1/(1+WACC!$E$34)^10 | M37: =1/(1+WACC!$E$34)^11 | N37: =1/(1+WACC!$E$34)^12 | O37: =1/(1+WACC!$E$34)^13 | P37: =1/(1+WACC!$E$34)^14 | Q37: =1/(1+WACC!$E$34)^15 | R37: =1/(1+WACC!$E$34)^16 | S37: =1/(1+WACC!$E$34)^17 | T37: =1/(1+WACC!$E$34)^18 | U37: =1/(1+WACC!$E$34)^19 | V37: =1/(1+WACC!$E$34)^20 | W37: =1/(1+WACC!$E$34)^21 | X37: =1/(1+WACC!$E$34)^22 | Y37: =1/(1+WACC!$E$34)^23 | Z37: =1/(1+WACC!$E$34)^24 | AA37: =1/(1+WACC!$E$34)^25 | AB37: =1/(1+WACC!$E$34)^26 | AC37: =1/(1+WACC!$E$34)^27 | AD37: =1/(1+WACC!$E$34)^28 | AE37: =1/(1+WACC!$E$34)^29 | AF37: =1/(1+WACC!$E$34)^30 | AG37: =1/(1+WACC!$E$34)^31 | AH37: =1/(1+WACC!$E$34)^32 | AI37: =1/(1+WACC!$E$34)^33 | AJ37: =1/(1+WACC!$E$34)^34 | AK37: =1/(1+WACC!$E$34)^35 | AL37: =1/(1+WACC!$E$34)^36 | AM37: =1/(1+WACC!$E$34)^37 | AN37: =1/(1+WACC!$E$34)^38 | AO37: =1/(1+WACC!$E$34)^39 | AP37: =1/(1+WACC!$E$34)^40 | AQ37: =1/(1+WACC!$E$34)^41 | AR37: =1/(1+WACC!$E$34)^42 | AS37: =1/(1+WACC!$E$34)^43 | AT37: =1/(1+WACC!$E$34)^44 | AU37: =1/(1+WACC!$E$34)^45 | AV37: =1/(1+WACC!$E$34)^46 | AW37: =1/(1+WACC!$E$34)^47 | AX37: =1/(1+WACC!$E$34)^48 | AY37: =1/(1+WACC!$E$34)^49 | AZ37: =1/(1+WACC!$E$34)^50 | BA37: =1/(1+WACC!$E$34)^51 | BB37: =1/(1+WACC!$E$34)^52 | BC37: =1/(1+WACC!$E$34)^53 | BD37: =1/(1+WACC!$E$34)^54 | BE37: =1/(1+WACC!$E$34)^55 | BF37: =1/(1+WACC!$E$34)^56 | BG37: =1/(1+WACC!$E$34)^57 | BH37: =1/(1+WACC!$E$34)^58 | BI37: =1/(1+WACC!$E$34)^59 | BJ37: =1/(1+WACC!$E$34)^60 | BK37: =1/(1+WACC!$E$34)^61 | BL37: =1/(1+WACC!$E$34)^62 | BM37: =1/(1+WACC!$E$34)^63 | BN37: =1/(1+WACC!$E$34)^64 | BO37: =1/(1+WACC!$E$34)^65 | BP37: =1/(1+WACC!$E$34)^66 | BQ37: =1/(1+WACC!$E$34)^67 | BR37: =1/(1+WACC!$E$34)^68 | BS37: =1/(1+WACC!$E$34)^69 | BT37: =1/(1+WACC!$E$34)^70 | BU37: =1/(1+WACC!$E$34)^71 | BV37: =1/(1+WACC!$E$34)^72 | BW37: =1/(1+WACC!$E$34)^73 | BX37: =1/(1+WACC!$E$34)^74 | BY37: =1/(1+WACC!$E$34)^75 | BZ37: =1/(1+WACC!$E$34)^76 | CA37: =1/(1+WACC!$E$34)^77 | CB37: =1/(1+WACC!$E$34)^78 | CC37: =1/(1+WACC!$E$34)^79 | CD37: =1/(1+WACC!$E$34)^80 | CE37: =1/(1+WACC!$E$34)^81 | CF37: =1/(1+WACC!$E$34)^82 | CG37: =1/(1+WACC!$E$34)^83 | CH37: =1/(1+WACC!$E$34)^84 | CI37: =1/(1+WACC!$E$34)^85 | CJ37: =1/(1+WACC!$E$34)^86 | CK37: =1/(1+WACC!$E$34)^87 | CL37: =1/(1+WACC!$E$34)^88 | CM37: =1/(1+WACC!$E$34)^89 | CN37: =1/(1+WACC!$E$34)^90 | CO37: =1/(1+WACC!$E$34)^91 | CP37: =1/(1+WACC!$E$34)^92 | CQ37: =1/(1+WACC!$E$34)^93 | CR37: =1/(1+WACC!$E$34)^94 | CS37: =1/(1+WACC!$E$34)^95 | CT37: =1/(1+WACC!$E$34)^96 | CU37: =1/(1+WACC!$E$34)^97 | CV37: =1/(1+WACC!$E$34)^98 | CW37: =1/(1+WACC!$E$34)^99 | CX37: =1/(1+WACC!$E$34)^100 | CY37: =1/(1+WACC!$E$34)^101 | CZ37: =1/(1+WACC!$E$34)^102 | DA37: =1/(1+WACC!$E$34)^103 | DB37: =1/(1+WACC!$E$34)^104 | DC37: =1/(1+WACC!$E$34)^105 | DD37: =1/(1+WACC!$E$34)^106 | DE37: =1/(1+WACC!$E$34)^107 | DF37: =1/(1+WACC!$E$34)^108 | DG37: =1/(1+WACC!$E$34)^109 | DH37: =1/(1+WACC!$E$34)^110 | DI37: =1/(1+WACC!$E$34)^111 | DJ37: =1/(1+WACC!$E$34)^112 | DK37: =1/(1+WACC!$E$34)^113 | DL37: =1/(1+WACC!$E$34)^114 | DM37: =1/(1+WACC!$E$34)^115 | DN37: =1/(1+WACC!$E$34)^116 | DO37: =1/(1+WACC!$E$34)^117 | DP37: =1/(1+WACC!$E$34)^118 | DQ37: =1/(1+WACC!$E$34)^119 | DR37: =1/(1+WACC!$E$34)^120 | DS37: =(1/(1+WACC!$E$34)^120)*(1/(1+WACC!$E$35)^1) | DT37: =(1/(1+WACC!$E$34)^120)*(1/(1+WACC!$E$35)^2) | DU37: =(1/(1+WACC!$E$34)^120)*(1/(1+WACC!$E$35)^3) | DV37: =(1/(1+WACC!$E$34)^120)*(1/(1+WACC!$E$35)^4) | DW37: =(1/(1+WACC!$E$34)^120)*(1/(1+WACC!$E$35)^5) | DX37: =(1/(1+WACC!$E$34)^120)*(1/(1+WACC!$E$35)^6) | DY37: =(1/(1+WACC!$E$34)^120)*(1/(1+WACC!$E$35)^7) | DZ37: =(1/(1+WACC!$E$34)^120)*(1/(1+WACC!$E$35)^8) | EA37: =(1/(1+WACC!$E$34)^120)*(1/(1+WACC!$E$35)^9) | EB37: =(1/(1+WACC!$E$34)^120)*(1/(1+WACC!$E$35)^10) | EC37: =(1/(1+WACC!$E$34)^120)*(1/(1+WACC!$E$35)^11) | ED37: =(1/(1+WACC!$E$34)^120)*(1/(1+WACC!$E$35)^12) | EE37: =(1/(1+WACC!$E$34)^120)*(1/(1+WACC!$E$35)^13) | EF37: =(1/(1+WACC!$E$34)^120)*(1/(1+WACC!$E$35)^14) | EG37: =(1/(1+WACC!$E$34)^120)*(1/(1+WACC!$E$35)^15) | EH37: =(1/(1+WACC!$E$34)^120)*(1/(1+WACC!$E$35)^16) | EI37: =(1/(1+WACC!$E$34)^120)*(1/(1+WACC!$E$35)^17) | EJ37: =(1/(1+WACC!$E$34)^120)*(1/(1+WACC!$E$35)^18) | EK37: =(1/(1+WACC!$E$34)^120)*(1/(1+WACC!$E$35)^19) | EL37: =(1/(1+WACC!$E$34)^120)*(1/(1+WACC!$E$35)^20) | EM37: =(1/(1+WACC!$E$34)^120)*(1/(1+WACC!$E$35)^21) | EN37: =(1/(1+WACC!$E$34)^120)*(1/(1+WACC!$E$35)^22) | EO37: =(1/(1+WACC!$E$34)^120)*(1/(1+WACC!$E$35)^23) | EP37: =(1/(1+WACC!$E$34)^120)*(1/(1+WACC!$E$35)^24) | EQ37: =(1/(1+WACC!$E$34)^120)*(1/(1+WACC!$E$35)^25) | ER37: =(1/(1+WACC!$E$34)^120)*(1/(1+WACC!$E$35)^26) | ES37: =(1/(1+WACC!$E$34)^120)*(1/(1+WACC!$E$35)^27) | ET37: =(1/(1+WACC!$E$34)^120)*(1/(1+WACC!$E$35)^28) | EU37: =(1/(1+WACC!$E$34)^120)*(1/(1+WACC!$E$35)^29) | EV37: =(1/(1+WACC!$E$34)^120)*(1/(1+WACC!$E$35)^30) | EW37: =(1/(1+WACC!$E$34)^120)*(1/(1+WACC!$E$35)^31) | EX37: =(1/(1+WACC!$E$34)^120)*(1/(1+WACC!$E$35)^32) | EY37: =(1/(1+WACC!$E$34)^120)*(1/(1+WACC!$E$35)^33) | EZ37: =(1/(1+WACC!$E$34)^120)*(1/(1+WACC!$E$35)^34) | FA37: =(1/(1+WACC!$E$34)^120)*(1/(1+WACC!$E$35)^35) | FB37: =(1/(1+WACC!$E$34)^120)*(1/(1+WACC!$E$35)^36) | FC37: =(1/(1+WACC!$E$34)^120)*(1/(1+WACC!$E$35)^37) | FD37: =(1/(1+WACC!$E$34)^120)*(1/(1+WACC!$E$35)^38) | FE37: =(1/(1+WACC!$E$34)^120)*(1/(1+WACC!$E$35)^39) | FF37: =(1/(1+WACC!$E$34)^120)*(1/(1+WACC!$E$35)^40) | FG37: =(1/(1+WACC!$E$34)^120)*(1/(1+WACC!$E$35)^41) | FH37: =(1/(1+WACC!$E$34)^120)*(1/(1+WACC!$E$35)^42) | FI37: =(1/(1+WACC!$E$34)^120)*(1/(1+WACC!$E$35)^43) | FJ37: =(1/(1+WACC!$E$34)^120)*(1/(1+WACC!$E$35)^44) | FK37: =(1/(1+WACC!$E$34)^120)*(1/(1+WACC!$E$35)^45) | FL37: =(1/(1+WACC!$E$34)^120)*(1/(1+WACC!$E$35)^46) | FM37: =(1/(1+WACC!$E$34)^120)*(1/(1+WACC!$E$35)^47) | FN37: =(1/(1+WACC!$E$34)^120)*(1/(1+WACC!$E$35)^48) | FO37: =(1/(1+WACC!$E$34)^120)*(1/(1+WACC!$E$35)^49) | FP37: =(1/(1+WACC!$E$34)^120)*(1/(1+WACC!$E$35)^50) | FQ37: =(1/(1+WACC!$E$34)^120)*(1/(1+WACC!$E$35)^51) | FR37: =(1/(1+WACC!$E$34)^120)*(1/(1+WACC!$E$35)^52) | FS37: =(1/(1+WACC!$E$34)^120)*(1/(1+WACC!$E$35)^53) | FT37: =(1/(1+WACC!$E$34)^120)*(1/(1+WACC!$E$35)^54) | FU37: =(1/(1+WACC!$E$34)^120)*(1/(1+WACC!$E$35)^55) | FV37: =(1/(1+WACC!$E$34)^120)*(1/(1+WACC!$E$35)^56) | FW37: =(1/(1+WACC!$E$34)^120)*(1/(1+WACC!$E$35)^57) | FX37: =(1/(1+WACC!$E$34)^120)*(1/(1+WACC!$E$35)^58) | FY37: =(1/(1+WACC!$E$34)^120)*(1/(1+WACC!$E$35)^59) | FZ37: =(1/(1+WACC!$E$34)^120)*(1/(1+WACC!$E$35)^60) | GA37: =(1/(1+WACC!$E$34)^120)*(1/(1+WACC!$E$35)^61) | GB37: =(1/(1+WACC!$E$34)^120)*(1/(1+WACC!$E$35)^62) | GC37: =(1/(1+WACC!$E$34)^120)*(1/(1+WACC!$E$35)^63) | GD37: =(1/(1+WACC!$E$34)^120)*(1/(1+WACC!$E$35)^64) | GE37: =(1/(1+WACC!$E$34)^120)*(1/(1+WACC!$E$35)^65) | GF37: =(1/(1+WACC!$E$34)^120)*(1/(1+WACC!$E$35)^66) | GG37: =(1/(1+WACC!$E$34)^120)*(1/(1+WACC!$E$35)^67) | GH37: =(1/(1+WACC!$E$34)^120)*(1/(1+WACC!$E$35)^68) | GI37: =(1/(1+WACC!$E$34)^120)*(1/(1+WACC!$E$35)^69) | GJ37: =(1/(1+WACC!$E$34)^120)*(1/(1+WACC!$E$35)^70) | GK37: =(1/(1+WACC!$E$34)^120)*(1/(1+WACC!$E$35)^71) | GL37: =(1/(1+WACC!$E$34)^120)*(1/(1+WACC!$E$35)^72) | GM37: =(1/(1+WACC!$E$34)^120)*(1/(1+WACC!$E$35)^73) | GN37: =(1/(1+WACC!$E$34)^120)*(1/(1+WACC!$E$35)^74) | GO37: =(1/(1+WACC!$E$34)^120)*(1/(1+WACC!$E$35)^75) | GP37: =(1/(1+WACC!$E$34)^120)*(1/(1+WACC!$E$35)^76) | GQ37: =(1/(1+WACC!$E$34)^120)*(1/(1+WACC!$E$35)^77) | GR37: =(1/(1+WACC!$E$34)^120)*(1/(1+WACC!$E$35)^78) | GS37: =(1/(1+WACC!$E$34)^120)*(1/(1+WACC!$E$35)^79) | GT37: =(1/(1+WACC!$E$34)^120)*(1/(1+WACC!$E$35)^80) | GU37: =(1/(1+WACC!$E$34)^120)*(1/(1+WACC!$E$35)^81) | GV37: =(1/(1+WACC!$E$34)^120)*(1/(1+WACC!$E$35)^82) | GW37: =(1/(1+WACC!$E$34)^120)*(1/(1+WACC!$E$35)^83) | GX37: =(1/(1+WACC!$E$34)^120)*(1/(1+WACC!$E$35)^84) | GY37: =(1/(1+WACC!$E$34)^120)*(1/(1+WACC!$E$35)^85) | GZ37: =(1/(1+WACC!$E$34)^120)*(1/(1+WACC!$E$35)^86) | HA37: =(1/(1+WACC!$E$34)^120)*(1/(1+WACC!$E$35)^87) | HB37: =(1/(1+WACC!$E$34)^120)*(1/(1+WACC!$E$35)^88) | HC37: =(1/(1+WACC!$E$34)^120)*(1/(1+WACC!$E$35)^89) | HD37: =(1/(1+WACC!$E$34)^120)*(1/(1+WACC!$E$35)^90) | HE37: =(1/(1+WACC!$E$34)^120)*(1/(1+WACC!$E$35)^91) | HF37: =(1/(1+WACC!$E$34)^120)*(1/(1+WACC!$E$35)^92) | HG37: =(1/(1+WACC!$E$34)^120)*(1/(1+WACC!$E$35)^93) | HH37: =(1/(1+WACC!$E$34)^120)*(1/(1+WACC!$E$35)^94) | HI37: =(1/(1+WACC!$E$34)^120)*(1/(1+WACC!$E$35)^95) | HJ37: =(1/(1+WACC!$E$34)^120)*(1/(1+WACC!$E$35)^96) | HK37: =(1/(1+WACC!$E$34)^120)*(1/(1+WACC!$E$35)^97) | HL37: =(1/(1+WACC!$E$34)^120)*(1/(1+WACC!$E$35)^98) | HM37: =(1/(1+WACC!$E$34)^120)*(1/(1+WACC!$E$35)^99) | HN37: =(1/(1+WACC!$E$34)^120)*(1/(1+WACC!$E$35)^100) | HO37: =(1/(1+WACC!$E$34)^120)*(1/(1+WACC!$E$35)^101) | HP37: =(1/(1+WACC!$E$34)^120)*(1/(1+WACC!$E$35)^102) | HQ37: =(1/(1+WACC!$E$34)^120)*(1/(1+WACC!$E$35)^103) | HR37: =(1/(1+WACC!$E$34)^120)*(1/(1+WACC!$E$35)^104) | HS37: =(1/(1+WACC!$E$34)^120)*(1/(1+WACC!$E$35)^105) | HT37: =(1/(1+WACC!$E$34)^120)*(1/(1+WACC!$E$35)^106) | HU37: =(1/(1+WACC!$E$34)^120)*(1/(1+WACC!$E$35)^107) | HV37: =(1/(1+WACC!$E$34)^120)*(1/(1+WACC!$E$35)^108) | HW37: =(1/(1+WACC!$E$34)^120)*(1/(1+WACC!$E$35)^109) | HX37: =(1/(1+WACC!$E$34)^120)*(1/(1+WACC!$E$35)^110) | HY37: =(1/(1+WACC!$E$34)^120)*(1/(1+WACC!$E$35)^111) | HZ37: =(1/(1+WACC!$E$34)^120)*(1/(1+WACC!$E$35)^112) | IA37: =(1/(1+WACC!$E$34)^120)*(1/(1+WACC!$E$35)^113) | IB37: =(1/(1+WACC!$E$34)^120)*(1/(1+WACC!$E$35)^114) | IC37: =(1/(1+WACC!$E$34)^120)*(1/(1+WACC!$E$35)^115) | ID37: =(1/(1+WACC!$E$34)^120)*(1/(1+WACC!$E$35)^116) | IE37: =(1/(1+WACC!$E$34)^120)*(1/(1+WACC!$E$35)^117) | IF37: =(1/(1+WACC!$E$34)^120)*(1/(1+WACC!$E$35)^118) | IG37: =(1/(1+WACC!$E$34)^120)*(1/(1+WACC!$E$35)^119) | IH37: =(1/(1+WACC!$E$34)^120)*(1/(1+WACC!$E$35)^120) | II37: =(1/(1+WACC!$E$34)^120)*(1/(1+WACC!$E$35)^121) | IJ37: =(1/(1+WACC!$E$34)^120)*(1/(1+WACC!$E$35)^122) | IK37: =(1/(1+WACC!$E$34)^120)*(1/(1+WACC!$E$35)^123) | IL37: =(1/(1+WACC!$E$34)^120)*(1/(1+WACC!$E$35)^124) | IM37: =(1/(1+WACC!$E$34)^120)*(1/(1+WACC!$E$35)^125) | IN37: =(1/(1+WACC!$E$34)^120)*(1/(1+WACC!$E$35)^126) | IO37: =(1/(1+WACC!$E$34)^120)*(1/(1+WACC!$E$35)^127) | IP37: =(1/(1+WACC!$E$34)^120)*(1/(1+WACC!$E$35)^128) | IQ37: =(1/(1+WACC!$E$34)^120)*(1/(1+WACC!$E$35)^129) | IR37: =(1/(1+WACC!$E$34)^120)*(1/(1+WACC!$E$35)^130) | IS37: =(1/(1+WACC!$E$34)^120)*(1/(1+WACC!$E$35)^131) | IT37: =(1/(1+WACC!$E$34)^120)*(1/(1+WACC!$E$35)^132) | IU37: =(1/(1+WACC!$E$34)^120)*(1/(1+WACC!$E$35)^133) | IV37: =(1/(1+WACC!$E$34)^120)*(1/(1+WACC!$E$35)^134) | IW37: =(1/(1+WACC!$E$34)^120)*(1/(1+WACC!$E$35)^135) | IX37: =(1/(1+WACC!$E$34)^120)*(1/(1+WACC!$E$35)^136) | IY37: =(1/(1+WACC!$E$34)^120)*(1/(1+WACC!$E$35)^137) | IZ37: =(1/(1+WACC!$E$34)^120)*(1/(1+WACC!$E$35)^138) | JA37: =(1/(1+WACC!$E$34)^120)*(1/(1+WACC!$E$35)^139) | JB37: =(1/(1+WACC!$E$34)^120)*(1/(1+WACC!$E$35)^140) | JC37: =(1/(1+WACC!$E$34)^120)*(1/(1+WACC!$E$35)^141) | JD37: =(1/(1+WACC!$E$34)^120)*(1/(1+WACC!$E$35)^142) | JE37: =(1/(1+WACC!$E$34)^120)*(1/(1+WACC!$E$35)^143) | JF37: =(1/(1+WACC!$E$34)^120)*(1/(1+WACC!$E$35)^144) | JG37: =(1/(1+WACC!$E$34)^120)*(1/(1+WACC!$E$35)^145) | JH37: =(1/(1+WACC!$E$34)^120)*(1/(1+WACC!$E$35)^146) | JI37: =(1/(1+WACC!$E$34)^120)*(1/(1+WACC!$E$35)^147) | JJ37: =(1/(1+WACC!$E$34)^120)*(1/(1+WACC!$E$35)^148) | JK37: =(1/(1+WACC!$E$34)^120)*(1/(1+WACC!$E$35)^149) | JL37: =(1/(1+WACC!$E$34)^120)*(1/(1+WACC!$E$35)^150) | JM37: =(1/(1+WACC!$E$34)^120)*(1/(1+WACC!$E$35)^151) | JN37: =(1/(1+WACC!$E$34)^120)*(1/(1+WACC!$E$35)^152) | JO37: =(1/(1+WACC!$E$34)^120)*(1/(1+WACC!$E$35)^153) | JP37: =(1/(1+WACC!$E$34)^120)*(1/(1+WACC!$E$35)^154) | JQ37: =(1/(1+WACC!$E$34)^120)*(1/(1+WACC!$E$35)^155) | JR37: =(1/(1+WACC!$E$34)^120)*(1/(1+WACC!$E$35)^156) | JS37: =(1/(1+WACC!$E$34)^120)*(1/(1+WACC!$E$35)^157) | JT37: =(1/(1+WACC!$E$34)^120)*(1/(1+WACC!$E$35)^158) | JU37: =(1/(1+WACC!$E$34)^120)*(1/(1+WACC!$E$35)^159) | JV37: =(1/(1+WACC!$E$34)^120)*(1/(1+WACC!$E$35)^160) | JW37: =(1/(1+WACC!$E$34)^120)*(1/(1+WACC!$E$35)^161) | JX37: =(1/(1+WACC!$E$34)^120)*(1/(1+WACC!$E$35)^162) | JY37: =(1/(1+WACC!$E$34)^120)*(1/(1+WACC!$E$35)^163) | JZ37: =(1/(1+WACC!$E$34)^120)*(1/(1+WACC!$E$35)^164) | KA37: =(1/(1+WACC!$E$34)^120)*(1/(1+WACC!$E$35)^165) | KB37: =(1/(1+WACC!$E$34)^120)*(1/(1+WACC!$E$35)^166) | KC37: =(1/(1+WACC!$E$34)^120)*(1/(1+WACC!$E$35)^167) | KD37: =(1/(1+WACC!$E$34)^120)*(1/(1+WACC!$E$35)^168) | KE37: =(1/(1+WACC!$E$34)^120)*(1/(1+WACC!$E$35)^169) | KF37: =(1/(1+WACC!$E$34)^120)*(1/(1+WACC!$E$35)^170) | KG37: =(1/(1+WACC!$E$34)^120)*(1/(1+WACC!$E$35)^171) | KH37: =(1/(1+WACC!$E$34)^120)*(1/(1+WACC!$E$35)^172) | KI37: =(1/(1+WACC!$E$34)^120)*(1/(1+WACC!$E$35)^173) | KJ37: =(1/(1+WACC!$E$34)^120)*(1/(1+WACC!$E$35)^174) | KK37: =(1/(1+WACC!$E$34)^120)*(1/(1+WACC!$E$35)^175) | KL37: =(1/(1+WACC!$E$34)^120)*(1/(1+WACC!$E$35)^176) | KM37: =(1/(1+WACC!$E$34)^120)*(1/(1+WACC!$E$35)^177) | KN37: =(1/(1+WACC!$E$34)^120)*(1/(1+WACC!$E$35)^178) | KO37: =(1/(1+WACC!$E$34)^120)*(1/(1+WACC!$E$35)^179) | KP37: =(1/(1+WACC!$E$34)^120)*(1/(1+WACC!$E$35)^180)
A38: Discounted FCFF | B38: EURk | C38: =C36*C37 | D38: =D36*D37 | E38: =E36*E37 | F38: =F36*F37 | G38: =G36*G37 | H38: =H36*H37 | I38: =I36*I37 | J38: =J36*J37 | ... KP38: =KP36*KP37
A39: Cumulative NPV | B39: EURk | C39: =C38-Assumptions!$E$31 | D39: =C39+D38 | E39: =D39+E38 | F39: =E39+F38 | G39: =F39+G38 | H39: =G39+H38 | I39: =H39+I38 | J39: =I39+J38 | K39: =J39+K38 | ... KP39: =KO39+KP38
A41: NPV SUMMARY — Segmented WACC vs Single WACC
A42: Scenario | B42: NPV Segmented (EURk) | C42: NPV Single WACC (EURk) | D42: Difference (EURk) | E42: Difference (%)
A43: P50 — Base Case | B43: =SUM(C14:KP14)-Assumptions!$E$31 | C43: =SUMPRODUCT(C12:KP12,C53:KP53)-Assumptions!$E$31 | D43: =C43-B43 | E43: =IF(B43<>0,D43/ABS(B43),0)
A44: P90 — Conservative | B44: =SUM(C26:KP26)-Assumptions!$E$31 | C44: =SUMPRODUCT(C24:KP24,C53:KP53)-Assumptions!$E$31 | D44: =C44-B44 | E44: =IF(B44<>0,D44/ABS(B44),0)
A45: P99 — Extreme Stress | B45: =SUM(C38:KP38)-Assumptions!$E$31 | C45: =SUMPRODUCT(C36:KP36,C53:KP53)-Assumptions!$E$31 | D45: =C45-B45 | E45: =IF(B45<>0,D45/ABS(B45),0)
C53: =1/(1+(120/300*WACC!$E$34+180/300*WACC!$E$35))^1 | D53: =1/(1+(120/300*WACC!$E$34+180/300*WACC!$E$35))^2 | E53: =1/(1+(120/300*WACC!$E$34+180/300*WACC!$E$35))^3 | F53: =1/(1+(120/300*WACC!$E$34+180/300*WACC!$E$35))^4 | G53: =1/(1+(120/300*WACC!$E$34+180/300*WACC!$E$35))^5 | H53: =1/(1+(120/300*WACC!$E$34+180/300*WACC!$E$35))^6 | I53: =1/(1+(120/300*WACC!$E$34+180/300*WACC!$E$35))^7 | J53: =1/(1+(120/300*WACC!$E$34+180/300*WACC!$E$35))^8 | K53: =1/(1+(120/300*WACC!$E$34+180/300*WACC!$E$35))^9 | L53: =1/(1+(120/300*WACC!$E$34+180/300*WACC!$E$35))^10 | M53: =1/(1+(120/300*WACC!$E$34+180/300*WACC!$E$35))^11 | N53: =1/(1+(120/300*WACC!$E$34+180/300*WACC!$E$35))^12 | O53: =1/(1+(120/300*WACC!$E$34+180/300*WACC!$E$35))^13 | P53: =1/(1+(120/300*WACC!$E$34+180/300*WACC!$E$35))^14 | Q53: =1/(1+(120/300*WACC!$E$34+180/300*WACC!$E$35))^15 | R53: =1/(1+(120/300*WACC!$E$34+180/300*WACC!$E$35))^16 | S53: =1/(1+(120/300*WACC!$E$34+180/300*WACC!$E$35))^17 | T53: =1/(1+(120/300*WACC!$E$34+180/300*WACC!$E$35))^18 | U53: =1/(1+(120/300*WACC!$E$34+180/300*WACC!$E$35))^19 | V53: =1/(1+(120/300*WACC!$E$34+180/300*WACC!$E$35))^20 | W53: =1/(1+(120/300*WACC!$E$34+180/300*WACC!$E$35))^21 | X53: =1/(1+(120/300*WACC!$E$34+180/300*WACC!$E$35))^22 | Y53: =1/(1+(120/300*WACC!$E$34+180/300*WACC!$E$35))^23 | Z53: =1/(1+(120/300*WACC!$E$34+180/300*WACC!$E$35))^24 | AA53: =1/(1+(120/300*WACC!$E$34+180/300*WACC!$E$35))^25 | AB53: =1/(1+(120/300*WACC!$E$34+180/300*WACC!$E$35))^26 | AC53: =1/(1+(120/300*WACC!$E$34+180/300*WACC!$E$35))^27 | AD53: =1/(1+(120/300*WACC!$E$34+180/300*WACC!$E$35))^28 | AE53: =1/(1+(120/300*WACC!$E$34+180/300*WACC!$E$35))^29 | AF53: =1/(1+(120/300*WACC!$E$34+180/300*WACC!$E$35))^30 | AG53: =1/(1+(120/300*WACC!$E$34+180/300*WACC!$E$35))^31 | AH53: =1/(1+(120/300*WACC!$E$34+180/300*WACC!$E$35))^32 | AI53: =1/(1+(120/300*WACC!$E$34+180/300*WACC!$E$35))^33 | AJ53: =1/(1+(120/300*WACC!$E$34+180/300*WACC!$E$35))^34 | AK53: =1/(1+(120/300*WACC!$E$34+180/300*WACC!$E$35))^35 | AL53: =1/(1+(120/300*WACC!$E$34+180/300*WACC!$E$35))^36 | AM53: =1/(1+(120/300*WACC!$E$34+180/300*WACC!$E$35))^37 | AN53: =1/(1+(120/300*WACC!$E$34+180/300*WACC!$E$35))^38 | AO53: =1/(1+(120/300*WACC!$E$34+180/300*WACC!$E$35))^39 | AP53: =1/(1+(120/300*WACC!$E$34+180/300*WACC!$E$35))^40 | AQ53: =1/(1+(120/300*WACC!$E$34+180/300*WACC!$E$35))^41 | AR53: =1/(1+(120/300*WACC!$E$34+180/300*WACC!$E$35))^42 | AS53: =1/(1+(120/300*WACC!$E$34+180/300*WACC!$E$35))^43 | AT53: =1/(1+(120/300*WACC!$E$34+180/300*WACC!$E$35))^44 | AU53: =1/(1+(120/300*WACC!$E$34+180/300*WACC!$E$35))^45 | AV53: =1/(1+(120/300*WACC!$E$34+180/300*WACC!$E$35))^46 | AW53: =1/(1+(120/300*WACC!$E$34+180/300*WACC!$E$35))^47 | AX53: =1/(1+(120/300*WACC!$E$34+180/300*WACC!$E$35))^48 | AY53: =1/(1+(120/300*WACC!$E$34+180/300*WACC!$E$35))^49 | AZ53: =1/(1+(120/300*WACC!$E$34+180/300*WACC!$E$35))^50 | BA53: =1/(1+(120/300*WACC!$E$34+180/300*WACC!$E$35))^51 | BB53: =1/(1+(120/300*WACC!$E$34+180/300*WACC!$E$35))^52 | BC53: =1/(1+(120/300*WACC!$E$34+180/300*WACC!$E$35))^53 | BD53: =1/(1+(120/300*WACC!$E$34+180/300*WACC!$E$35))^54 | BE53: =1/(1+(120/300*WACC!$E$34+180/300*WACC!$E$35))^55 | BF53: =1/(1+(120/300*WACC!$E$34+180/300*WACC!$E$35))^56 | BG53: =1/(1+(120/300*WACC!$E$34+180/300*WACC!$E$35))^57 | BH53: =1/(1+(120/300*WACC!$E$34+180/300*WACC!$E$35))^58 | BI53: =1/(1+(120/300*WACC!$E$34+180/300*WACC!$E$35))^59 | BJ53: =1/(1+(120/300*WACC!$E$34+180/300*WACC!$E$35))^60 | BK53: =1/(1+(120/300*WACC!$E$34+180/300*WACC!$E$35))^61 | BL53: =1/(1+(120/300*WACC!$E$34+180/300*WACC!$E$35))^62 | BM53: =1/(1+(120/300*WACC!$E$34+180/300*WACC!$E$35))^63 | BN53: =1/(1+(120/300*WACC!$E$34+180/300*WACC!$E$35))^64 | BO53: =1/(1+(120/300*WACC!$E$34+180/300*WACC!$E$35))^65 | BP53: =1/(1+(120/300*WACC!$E$34+180/300*WACC!$E$35))^66 | BQ53: =1/(1+(120/300*WACC!$E$34+180/300*WACC!$E$35))^67 | BR53: =1/(1+(120/300*WACC!$E$34+180/300*WACC!$E$35))^68 | BS53: =1/(1+(120/300*WACC!$E$34+180/300*WACC!$E$35))^69 | BT53: =1/(1+(120/300*WACC!$E$34+180/300*WACC!$E$35))^70 | BU53: =1/(1+(120/300*WACC!$E$34+180/300*WACC!$E$35))^71 | BV53: =1/(1+(120/300*WACC!$E$34+180/300*WACC!$E$35))^72 | BW53: =1/(1+(120/300*WACC!$E$34+180/300*WACC!$E$35))^73 | BX53: =1/(1+(120/300*WACC!$E$34+180/300*WACC!$E$35))^74 | BY53: =1/(1+(120/300*WACC!$E$34+180/300*WACC!$E$35))^75 | BZ53: =1/(1+(120/300*WACC!$E$34+180/300*WACC!$E$35))^76 | CA53: =1/(1+(120/300*WACC!$E$34+180/300*WACC!$E$35))^77 | CB53: =1/(1+(120/300*WACC!$E$34+180/300*WACC!$E$35))^78 | CC53: =1/(1+(120/300*WACC!$E$34+180/300*WACC!$E$35))^79 | CD53: =1/(1+(120/300*WACC!$E$34+180/300*WACC!$E$35))^80 | CE53: =1/(1+(120/300*WACC!$E$34+180/300*WACC!$E$35))^81 | CF53: =1/(1+(120/300*WACC!$E$34+180/300*WACC!$E$35))^82 | CG53: =1/(1+(120/300*WACC!$E$34+180/300*WACC!$E$35))^83 | CH53: =1/(1+(120/300*WACC!$E$34+180/300*WACC!$E$35))^84 | CI53: =1/(1+(120/300*WACC!$E$34+180/300*WACC!$E$35))^85 | CJ53: =1/(1+(120/300*WACC!$E$34+180/300*WACC!$E$35))^86 | CK53: =1/(1+(120/300*WACC!$E$34+180/300*WACC!$E$35))^87 | CL53: =1/(1+(120/300*WACC!$E$34+180/300*WACC!$E$35))^88 | CM53: =1/(1+(120/300*WACC!$E$34+180/300*WACC!$E$35))^89 | CN53: =1/(1+(120/300*WACC!$E$34+180/300*WACC!$E$35))^90 | CO53: =1/(1+(120/300*WACC!$E$34+180/300*WACC!$E$35))^91 | CP53: =1/(1+(120/300*WACC!$E$34+180/300*WACC!$E$35))^92 | CQ53: =1/(1+(120/300*WACC!$E$34+180/300*WACC!$E$35))^93 | CR53: =1/(1+(120/300*WACC!$E$34+180/300*WACC!$E$35))^94 | CS53: =1/(1+(120/300*WACC!$E$34+180/300*WACC!$E$35))^95 | CT53: =1/(1+(120/300*WACC!$E$34+180/300*WACC!$E$35))^96 | CU53: =1/(1+(120/300*WACC!$E$34+180/300*WACC!$E$35))^97 | CV53: =1/(1+(120/300*WACC!$E$34+180/300*WACC!$E$35))^98 | CW53: =1/(1+(120/300*WACC!$E$34+180/300*WACC!$E$35))^99 | CX53: =1/(1+(120/300*WACC!$E$34+180/300*WACC!$E$35))^100 | CY53: =1/(1+(120/300*WACC!$E$34+180/300*WACC!$E$35))^101 | CZ53: =1/(1+(120/300*WACC!$E$34+180/300*WACC!$E$35))^102 | DA53: =1/(1+(120/300*WACC!$E$34+180/300*WACC!$E$35))^103 | DB53: =1/(1+(120/300*WACC!$E$34+180/300*WACC!$E$35))^104 | DC53: =1/(1+(120/300*WACC!$E$34+180/300*WACC!$E$35))^105 | DD53: =1/(1+(120/300*WACC!$E$34+180/300*WACC!$E$35))^106 | DE53: =1/(1+(120/300*WACC!$E$34+180/300*WACC!$E$35))^107 | DF53: =1/(1+(120/300*WACC!$E$34+180/300*WACC!$E$35))^108 | DG53: =1/(1+(120/300*WACC!$E$34+180/300*WACC!$E$35))^109 | DH53: =1/(1+(120/300*WACC!$E$34+180/300*WACC!$E$35))^110 | DI53: =1/(1+(120/300*WACC!$E$34+180/300*WACC!$E$35))^111 | DJ53: =1/(1+(120/300*WACC!$E$34+180/300*WACC!$E$35))^112 | DK53: =1/(1+(120/300*WACC!$E$34+180/300*WACC!$E$35))^113 | DL53: =1/(1+(120/300*WACC!$E$34+180/300*WACC!$E$35))^114 | DM53: =1/(1+(120/300*WACC!$E$34+180/300*WACC!$E$35))^115 | DN53: =1/(1+(120/300*WACC!$E$34+180/300*WACC!$E$35))^116 | DO53: =1/(1+(120/300*WACC!$E$34+180/300*WACC!$E$35))^117 | DP53: =1/(1+(120/300*WACC!$E$34+180/300*WACC!$E$35))^118 | DQ53: =1/(1+(120/300*WACC!$E$34+180/300*WACC!$E$35))^119 | DR53: =1/(1+(120/300*WACC!$E$34+180/300*WACC!$E$35))^120 | DS53: =1/(1+(120/300*WACC!$E$34+180/300*WACC!$E$35))^121 | DT53: =1/(1+(120/300*WACC!$E$34+180/300*WACC!$E$35))^122 | DU53: =1/(1+(120/300*WACC!$E$34+180/300*WACC!$E$35))^123 | DV53: =1/(1+(120/300*WACC!$E$34+180/300*WACC!$E$35))^124 | DW53: =1/(1+(120/300*WACC!$E$34+180/300*WACC!$E$35))^125 | DX53: =1/(1+(120/300*WACC!$E$34+180/300*WACC!$E$35))^126 | DY53: =1/(1+(120/300*WACC!$E$34+180/300*WACC!$E$35))^127 | DZ53: =1/(1+(120/300*WACC!$E$34+180/300*WACC!$E$35))^128 | EA53: =1/(1+(120/300*WACC!$E$34+180/300*WACC!$E$35))^129 | EB53: =1/(1+(120/300*WACC!$E$34+180/300*WACC!$E$35))^130 | EC53: =1/(1+(120/300*WACC!$E$34+180/300*WACC!$E$35))^131 | ED53: =1/(1+(120/300*WACC!$E$34+180/300*WACC!$E$35))^132 | EE53: =1/(1+(120/300*WACC!$E$34+180/300*WACC!$E$35))^133 | EF53: =1/(1+(120/300*WACC!$E$34+180/300*WACC!$E$35))^134 | EG53: =1/(1+(120/300*WACC!$E$34+180/300*WACC!$E$35))^135 | EH53: =1/(1+(120/300*WACC!$E$34+180/300*WACC!$E$35))^136 | EI53: =1/(1+(120/300*WACC!$E$34+180/300*WACC!$E$35))^137 | EJ53: =1/(1+(120/300*WACC!$E$34+180/300*WACC!$E$35))^138 | EK53: =1/(1+(120/300*WACC!$E$34+180/300*WACC!$E$35))^139 | EL53: =1/(1+(120/300*WACC!$E$34+180/300*WACC!$E$35))^140 | EM53: =1/(1+(120/300*WACC!$E$34+180/300*WACC!$E$35))^141 | EN53: =1/(1+(120/300*WACC!$E$34+180/300*WACC!$E$35))^142 | EO53: =1/(1+(120/300*WACC!$E$34+180/300*WACC!$E$35))^143 | EP53: =1/(1+(120/300*WACC!$E$34+180/300*WACC!$E$35))^144 | EQ53: =1/(1+(120/300*WACC!$E$34+180/300*WACC!$E$35))^145 | ER53: =1/(1+(120/300*WACC!$E$34+180/300*WACC!$E$35))^146 | ES53: =1/(1+(120/300*WACC!$E$34+180/300*WACC!$E$35))^147 | ET53: =1/(1+(120/300*WACC!$E$34+180/300*WACC!$E$35))^148 | EU53: =1/(1+(120/300*WACC!$E$34+180/300*WACC!$E$35))^149 | EV53: =1/(1+(120/300*WACC!$E$34+180/300*WACC!$E$35))^150 | EW53: =1/(1+(120/300*WACC!$E$34+180/300*WACC!$E$35))^151 | EX53: =1/(1+(120/300*WACC!$E$34+180/300*WACC!$E$35))^152 | EY53: =1/(1+(120/300*WACC!$E$34+180/300*WACC!$E$35))^153 | EZ53: =1/(1+(120/300*WACC!$E$34+180/300*WACC!$E$35))^154 | FA53: =1/(1+(120/300*WACC!$E$34+180/300*WACC!$E$35))^155 | FB53: =1/(1+(120/300*WACC!$E$34+180/300*WACC!$E$35))^156 | FC53: =1/(1+(120/300*WACC!$E$34+180/300*WACC!$E$35))^157 | FD53: =1/(1+(120/300*WACC!$E$34+180/300*WACC!$E$35))^158 | FE53: =1/(1+(120/300*WACC!$E$34+180/300*WACC!$E$35))^159 | FF53: =1/(1+(120/300*WACC!$E$34+180/300*WACC!$E$35))^160 | FG53: =1/(1+(120/300*WACC!$E$34+180/300*WACC!$E$35))^161 | FH53: =1/(1+(120/300*WACC!$E$34+180/300*WACC!$E$35))^162 | FI53: =1/(1+(120/300*WACC!$E$34+180/300*WACC!$E$35))^163 | FJ53: =1/(1+(120/300*WACC!$E$34+180/300*WACC!$E$35))^164 | FK53: =1/(1+(120/300*WACC!$E$34+180/300*WACC!$E$35))^165 | FL53: =1/(1+(120/300*WACC!$E$34+180/300*WACC!$E$35))^166 | FM53: =1/(1+(120/300*WACC!$E$34+180/300*WACC!$E$35))^167 | FN53: =1/(1+(120/300*WACC!$E$34+180/300*WACC!$E$35))^168 | FO53: =1/(1+(120/300*WACC!$E$34+180/300*WACC!$E$35))^169 | FP53: =1/(1+(120/300*WACC!$E$34+180/300*WACC!$E$35))^170 | FQ53: =1/(1+(120/300*WACC!$E$34+180/300*WACC!$E$35))^171 | FR53: =1/(1+(120/300*WACC!$E$34+180/300*WACC!$E$35))^172 | FS53: =1/(1+(120/300*WACC!$E$34+180/300*WACC!$E$35))^173 | FT53: =1/(1+(120/300*WACC!$E$34+180/300*WACC!$E$35))^174 | FU53: =1/(1+(120/300*WACC!$E$34+180/300*WACC!$E$35))^175 | FV53: =1/(1+(120/300*WACC!$E$34+180/300*WACC!$E$35))^176 | FW53: =1/(1+(120/300*WACC!$E$34+180/300*WACC!$E$35))^177 | FX53: =1/(1+(120/300*WACC!$E$34+180/300*WACC!$E$35))^178 | FY53: =1/(1+(120/300*WACC!$E$34+180/300*WACC!$E$35))^179 | FZ53: =1/(1+(120/300*WACC!$E$34+180/300*WACC!$E$35))^180 | GA53: =1/(1+(120/300*WACC!$E$34+180/300*WACC!$E$35))^181 | GB53: =1/(1+(120/300*WACC!$E$34+180/300*WACC!$E$35))^182 | GC53: =1/(1+(120/300*WACC!$E$34+180/300*WACC!$E$35))^183 | GD53: =1/(1+(120/300*WACC!$E$34+180/300*WACC!$E$35))^184 | GE53: =1/(1+(120/300*WACC!$E$34+180/300*WACC!$E$35))^185 | GF53: =1/(1+(120/300*WACC!$E$34+180/300*WACC!$E$35))^186 | GG53: =1/(1+(120/300*WACC!$E$34+180/300*WACC!$E$35))^187 | GH53: =1/(1+(120/300*WACC!$E$34+180/300*WACC!$E$35))^188 | GI53: =1/(1+(120/300*WACC!$E$34+180/300*WACC!$E$35))^189 | GJ53: =1/(1+(120/300*WACC!$E$34+180/300*WACC!$E$35))^190 | GK53: =1/(1+(120/300*WACC!$E$34+180/300*WACC!$E$35))^191 | GL53: =1/(1+(120/300*WACC!$E$34+180/300*WACC!$E$35))^192 | GM53: =1/(1+(120/300*WACC!$E$34+180/300*WACC!$E$35))^193 | GN53: =1/(1+(120/300*WACC!$E$34+180/300*WACC!$E$35))^194 | GO53: =1/(1+(120/300*WACC!$E$34+180/300*WACC!$E$35))^195 | GP53: =1/(1+(120/300*WACC!$E$34+180/300*WACC!$E$35))^196 | GQ53: =1/(1+(120/300*WACC!$E$34+180/300*WACC!$E$35))^197 | GR53: =1/(1+(120/300*WACC!$E$34+180/300*WACC!$E$35))^198 | GS53: =1/(1+(120/300*WACC!$E$34+180/300*WACC!$E$35))^199 | GT53: =1/(1+(120/300*WACC!$E$34+180/300*WACC!$E$35))^200 | GU53: =1/(1+(120/300*WACC!$E$34+180/300*WACC!$E$35))^201 | GV53: =1/(1+(120/300*WACC!$E$34+180/300*WACC!$E$35))^202 | GW53: =1/(1+(120/300*WACC!$E$34+180/300*WACC!$E$35))^203 | GX53: =1/(1+(120/300*WACC!$E$34+180/300*WACC!$E$35))^204 | GY53: =1/(1+(120/300*WACC!$E$34+180/300*WACC!$E$35))^205 | GZ53: =1/(1+(120/300*WACC!$E$34+180/300*WACC!$E$35))^206 | HA53: =1/(1+(120/300*WACC!$E$34+180/300*WACC!$E$35))^207 | HB53: =1/(1+(120/300*WACC!$E$34+180/300*WACC!$E$35))^208 | HC53: =1/(1+(120/300*WACC!$E$34+180/300*WACC!$E$35))^209 | HD53: =1/(1+(120/300*WACC!$E$34+180/300*WACC!$E$35))^210 | HE53: =1/(1+(120/300*WACC!$E$34+180/300*WACC!$E$35))^211 | HF53: =1/(1+(120/300*WACC!$E$34+180/300*WACC!$E$35))^212 | HG53: =1/(1+(120/300*WACC!$E$34+180/300*WACC!$E$35))^213 | HH53: =1/(1+(120/300*WACC!$E$34+180/300*WACC!$E$35))^214 | HI53: =1/(1+(120/300*WACC!$E$34+180/300*WACC!$E$35))^215 | HJ53: =1/(1+(120/300*WACC!$E$34+180/300*WACC!$E$35))^216 | HK53: =1/(1+(120/300*WACC!$E$34+180/300*WACC!$E$35))^217 | HL53: =1/(1+(120/300*WACC!$E$34+180/300*WACC!$E$35))^218 | HM53: =1/(1+(120/300*WACC!$E$34+180/300*WACC!$E$35))^219 | HN53: =1/(1+(120/300*WACC!$E$34+180/300*WACC!$E$35))^220 | HO53: =1/(1+(120/300*WACC!$E$34+180/300*WACC!$E$35))^221 | HP53: =1/(1+(120/300*WACC!$E$34+180/300*WACC!$E$35))^222 | HQ53: =1/(1+(120/300*WACC!$E$34+180/300*WACC!$E$35))^223 | HR53: =1/(1+(120/300*WACC!$E$34+180/300*WACC!$E$35))^224 | HS53: =1/(1+(120/300*WACC!$E$34+180/300*WACC!$E$35))^225 | HT53: =1/(1+(120/300*WACC!$E$34+180/300*WACC!$E$35))^226 | HU53: =1/(1+(120/300*WACC!$E$34+180/300*WACC!$E$35))^227 | HV53: =1/(1+(120/300*WACC!$E$34+180/300*WACC!$E$35))^228 | HW53: =1/(1+(120/300*WACC!$E$34+180/300*WACC!$E$35))^229 | HX53: =1/(1+(120/300*WACC!$E$34+180/300*WACC!$E$35))^230 | HY53: =1/(1+(120/300*WACC!$E$34+180/300*WACC!$E$35))^231 | HZ53: =1/(1+(120/300*WACC!$E$34+180/300*WACC!$E$35))^232 | IA53: =1/(1+(120/300*WACC!$E$34+180/300*WACC!$E$35))^233 | IB53: =1/(1+(120/300*WACC!$E$34+180/300*WACC!$E$35))^234 | IC53: =1/(1+(120/300*WACC!$E$34+180/300*WACC!$E$35))^235 | ID53: =1/(1+(120/300*WACC!$E$34+180/300*WACC!$E$35))^236 | IE53: =1/(1+(120/300*WACC!$E$34+180/300*WACC!$E$35))^237 | IF53: =1/(1+(120/300*WACC!$E$34+180/300*WACC!$E$35))^238 | IG53: =1/(1+(120/300*WACC!$E$34+180/300*WACC!$E$35))^239 | IH53: =1/(1+(120/300*WACC!$E$34+180/300*WACC!$E$35))^240 | II53: =1/(1+(120/300*WACC!$E$34+180/300*WACC!$E$35))^241 | IJ53: =1/(1+(120/300*WACC!$E$34+180/300*WACC!$E$35))^242 | IK53: =1/(1+(120/300*WACC!$E$34+180/300*WACC!$E$35))^243 | IL53: =1/(1+(120/300*WACC!$E$34+180/300*WACC!$E$35))^244 | IM53: =1/(1+(120/300*WACC!$E$34+180/300*WACC!$E$35))^245 | IN53: =1/(1+(120/300*WACC!$E$34+180/300*WACC!$E$35))^246 | IO53: =1/(1+(120/300*WACC!$E$34+180/300*WACC!$E$35))^247 | IP53: =1/(1+(120/300*WACC!$E$34+180/300*WACC!$E$35))^248 | IQ53: =1/(1+(120/300*WACC!$E$34+180/300*WACC!$E$35))^249 | IR53: =1/(1+(120/300*WACC!$E$34+180/300*WACC!$E$35))^250 | IS53: =1/(1+(120/300*WACC!$E$34+180/300*WACC!$E$35))^251 | IT53: =1/(1+(120/300*WACC!$E$34+180/300*WACC!$E$35))^252 | IU53: =1/(1+(120/300*WACC!$E$34+180/300*WACC!$E$35))^253 | IV53: =1/(1+(120/300*WACC!$E$34+180/300*WACC!$E$35))^254 | IW53: =1/(1+(120/300*WACC!$E$34+180/300*WACC!$E$35))^255 | IX53: =1/(1+(120/300*WACC!$E$34+180/300*WACC!$E$35))^256 | IY53: =1/(1+(120/300*WACC!$E$34+180/300*WACC!$E$35))^257 | IZ53: =1/(1+(120/300*WACC!$E$34+180/300*WACC!$E$35))^258 | JA53: =1/(1+(120/300*WACC!$E$34+180/300*WACC!$E$35))^259 | JB53: =1/(1+(120/300*WACC!$E$34+180/300*WACC!$E$35))^260 | JC53: =1/(1+(120/300*WACC!$E$34+180/300*WACC!$E$35))^261 | JD53: =1/(1+(120/300*WACC!$E$34+180/300*WACC!$E$35))^262 | JE53: =1/(1+(120/300*WACC!$E$34+180/300*WACC!$E$35))^263 | JF53: =1/(1+(120/300*WACC!$E$34+180/300*WACC!$E$35))^264 | JG53: =1/(1+(120/300*WACC!$E$34+180/300*WACC!$E$35))^265 | JH53: =1/(1+(120/300*WACC!$E$34+180/300*WACC!$E$35))^266 | JI53: =1/(1+(120/300*WACC!$E$34+180/300*WACC!$E$35))^267 | JJ53: =1/(1+(120/300*WACC!$E$34+180/300*WACC!$E$35))^268 | JK53: =1/(1+(120/300*WACC!$E$34+180/300*WACC!$E$35))^269 | JL53: =1/(1+(120/300*WACC!$E$34+180/300*WACC!$E$35))^270 | JM53: =1/(1+(120/300*WACC!$E$34+180/300*WACC!$E$35))^271 | JN53: =1/(1+(120/300*WACC!$E$34+180/300*WACC!$E$35))^272 | JO53: =1/(1+(120/300*WACC!$E$34+180/300*WACC!$E$35))^273 | JP53: =1/(1+(120/300*WACC!$E$34+180/300*WACC!$E$35))^274 | JQ53: =1/(1+(120/300*WACC!$E$34+180/300*WACC!$E$35))^275 | JR53: =1/(1+(120/300*WACC!$E$34+180/300*WACC!$E$35))^276 | JS53: =1/(1+(120/300*WACC!$E$34+180/300*WACC!$E$35))^277 | JT53: =1/(1+(120/300*WACC!$E$34+180/300*WACC!$E$35))^278 | JU53: =1/(1+(120/300*WACC!$E$34+180/300*WACC!$E$35))^279 | JV53: =1/(1+(120/300*WACC!$E$34+180/300*WACC!$E$35))^280 | JW53: =1/(1+(120/300*WACC!$E$34+180/300*WACC!$E$35))^281 | JX53: =1/(1+(120/300*WACC!$E$34+180/300*WACC!$E$35))^282 | JY53: =1/(1+(120/300*WACC!$E$34+180/300*WACC!$E$35))^283 | JZ53: =1/(1+(120/300*WACC!$E$34+180/300*WACC!$E$35))^284 | KA53: =1/(1+(120/300*WACC!$E$34+180/300*WACC!$E$35))^285 | KB53: =1/(1+(120/300*WACC!$E$34+180/300*WACC!$E$35))^286 | KC53: =1/(1+(120/300*WACC!$E$34+180/300*WACC!$E$35))^287 | KD53: =1/(1+(120/300*WACC!$E$34+180/300*WACC!$E$35))^288 | KE53: =1/(1+(120/300*WACC!$E$34+180/300*WACC!$E$35))^289 | KF53: =1/(1+(120/300*WACC!$E$34+180/300*WACC!$E$35))^290 | KG53: =1/(1+(120/300*WACC!$E$34+180/300*WACC!$E$35))^291 | KH53: =1/(1+(120/300*WACC!$E$34+180/300*WACC!$E$35))^292 | KI53: =1/(1+(120/300*WACC!$E$34+180/300*WACC!$E$35))^293 | KJ53: =1/(1+(120/300*WACC!$E$34+180/300*WACC!$E$35))^294 | KK53: =1/(1+(120/300*WACC!$E$34+180/300*WACC!$E$35))^295 | KL53: =1/(1+(120/300*WACC!$E$34+180/300*WACC!$E$35))^296 | KM53: =1/(1+(120/300*WACC!$E$34+180/300*WACC!$E$35))^297 | KN53: =1/(1+(120/300*WACC!$E$34+180/300*WACC!$E$35))^298 | KO53: =1/(1+(120/300*WACC!$E$34+180/300*WACC!$E$35))^299 | KP53: =1/(1+(120/300*WACC!$E$34+180/300*WACC!$E$35))^300

Sheet Debt Sizing
A1: Debt Sizing — Sculpting Algorithm | DSCR_min PPA=1.20x | DSCR_min Merchant=1.35x | r_d PPA=4.00% | r_d Merchant=5.50%
A2: NOTE: Debt sized on positive CFADS only. Negative CFADS months indicate periods where debt service is not supportable.
A4: CFADS DIAGNOSTIC
A5: Scenario | B5: Min CFADS Merchant (EURk) | C5: Neg CFADS Months (Merchant) | D5: First Neg Month | E5: First Neg Year | F5: Implied Merchant Debt Capacity (EURk)
A6: P50 | B6: 125.86 | C6: 0 | D6: None | E6: None | F6: 9286
A7: P90 | B7: -7.88 | C7: 29 | D7: 267 | E7: 22.2 | F7: 909
A8: P99 | B8: -155.8 | C8: 180 | D8: 121 | E8: 10.1 | F8: 0
A10: DEBT SIZING SUMMARY
A11: Scenario | B11: Debt Quantum (EURk) | C11: Gearing (D/CAPEX) | D11: LLCR | E11: Min DSCR PPA | F11: Min DSCR Merchant | G11: Neg CFADS Months (Merchant) | H11: Outstanding at M120 (EURk) | I11: Last Debt Service Month
A12: P50 | B12: 19541 | C12: 0.8496 | D12: 1.27 | E12: 1.2 | F12: 1.35 | G12: 0 | H12: 13745 | I12: 300
A13: P90 | B13: 11164 | C13: 0.4854 | D13: 1.21 | E13: 1.2 | F13: 1.35 | G13: 29 | H13: 1346 | I13: 288
A14: P99 | B14: 10255 | C14: 0.4459 | D14: 1.2 | E14: 1.2 | F14: N/A | G14: 180 | H14: 0 | I14: 120
A16: Debt Capacity Contraction P50 → P90 | B16: -0.4287
A17: Debt Capacity Contraction P50 → P99 | B17: -0.4752
A19: MONTHLY DEBT SERVICE SCHEDULE — P90 (Primary Sizing Case)
A20: Month | B20: Year | C20: CFADS (EURk) | D20: Interest (EURk) | E20: Principal (EURk) | F20: Debt Service (EURk) | G20: Outstanding (EURk) | H20: DSCR
A21: 1 | B21: 0.0833 | C21: 129.7746 | D21: 36.5488 | E21: 71.5968 | F21: 108.1455 | G21: 11092.632 | H21: 1.2
A22: 2 | B22: 0.1667 | C22: 129.7746 | D22: 36.3144 | E22: 71.8311 | F22: 108.1455 | G22: 11020.801 | H22: 1.2
A23: 3 | B23: 0.25 | C23: 129.7746 | D23: 36.0792 | E23: 72.0663 | F23: 108.1455 | G23: 10948.735 | H23: 1.2
A24: 4 | B24: 0.3333 | C24: 129.7746 | D24: 35.8433 | E24: 72.3022 | F24: 108.1455 | G24: 10876.433 | H24: 1.2
A25: 5 | B25: 0.4167 | C25: 129.7746 | D25: 35.6066 | E25: 72.5389 | F25: 108.1455 | G25: 10803.894 | H25: 1.2
A26: 6 | B26: 0.5 | C26: 129.7746 | D26: 35.3691 | E26: 72.7764 | F26: 108.1455 | G26: 10731.117 | H26: 1.2
A27: 7 | B27: 0.5833 | C27: 129.7746 | D27: 35.1309 | E27: 73.0147 | F27: 108.1455 | G27: 10658.103 | H27: 1.2
A28: 8 | B28: 0.6667 | C28: 129.7746 | D28: 34.8919 | E28: 73.2537 | F28: 108.1455 | G28: 10584.849 | H28: 1.2
A29: 9 | B29: 0.75 | C29: 129.7746 | D29: 34.652 | E29: 73.4935 | F29: 108.1455 | G29: 10511.355 | H29: 1.2
A30: 10 | B30: 0.8333 | C30: 129.7746 | D30: 34.4114 | E30: 73.7341 | F30: 108.1455 | G30: 10437.621 | H30: 1.2
A31: 11 | B31: 0.9167 | C31: 129.7746 | D31: 34.1701 | E31: 73.9755 | F31: 108.1455 | G31: 10363.646 | H31: 1.2
A32: 12 | B32: 1 | C32: 129.7746 | D32: 33.9279 | E32: 74.2177 | F32: 108.1455 | G32: 10289.428 | H32: 1.2
... A286: 266 | B286: 22.1667 | C286: 2.6108 | D286: 0.024 | E286: 1.9099 | F286: 1.9339 | G286: 3.4679 | H286: 1.35
A287: 267 | B287: 22.25 | C287: -1.0702 | D287: 0.0155 | E287: 0 | F287: 0.0155 | G287: 3.4679 | H287: N/A
A288: 268 | B288: 22.3333 | C288: 0.9348 | D288: 0.0155 | E288: 0.677 | F288: 0.6925 | G288: 2.7909 | H288: 1.35
A289: 269 | B289: 22.4167 | C289: 0.349 | D289: 0.0125 | E289: 0.246 | F289: 0.2585 | G289: 2.5449 | H289: 1.35
A290: 270 | B290: 22.5 | C290: 2.194 | D290: 0.0114 | E290: 1.6138 | F290: 1.6252 | G290: 0.9311 | H290: 1.35
A291: 271 | B291: 22.5833 | C291: -1.8197 | D291: 0.0042 | E291: 0 | F291: 0.0042 | G291: 0.9311 | H291: N/A
A292: 272 | B292: 22.6667 | C292: 0.1046 | D292: 0.0042 | E292: 0.0733 | F292: 0.0775 | G292: 0.8578 | H292: 1.35
A293: 273 | B293: 22.75 | C293: -1.7268 | D293: 0.0038 | E293: 0 | F293: 0.0038 | G293: 0.8578 | H293: N/A
A294: 274 | B294: 22.8333 | C294: -3.2183 | D294: 0.0038 | E294: 0 | F294: 0.0038 | G294: 0.8578 | H294: N/A
A295: 275 | B295: 22.9167 | C295: -3.0298 | D295: 0.0038 | E295: 0 | F295: 0.0038 | G295: 0.8578 | H295: N/A
A296: 276 | B296: 23 | C296: -3.9146 | D296: 0.0038 | E296: 0 | F296: 0.0038 | G296: 0.8578 | H296: N/A
A297: 277 | B297: 23.0833 | C297: -2.8564 | D297: 0.0038 | E297: 0 | F297: 0.0038 | G297: 0.8578 | H297: N/A
A298: 278 | B298: 23.1667 | C298: -7.0115 | D298: 0.0038 | E298: 0 | F298: 0.0038 | G298: 0.8578 | H298: N/A
A299: 279 | B299: 23.25 | C299: -4.6318 | D299: 0.0038 | E299: 0 | F299: 0.0038 | G299: 0.8578 | H299: N/A
A300: 280 | B300: 23.3333 | C300: -3.6713 | D300: 0.0038 | E300: 0 | F300: 0.0038 | G300: 0.8578 | H300: N/A
A301: 281 | B301: 23.4167 | C301: -2.8634 | D301: 0.0038 | E301: 0 | F301: 0.0038 | G301: 0.8578 | H301: N/A
A302: 282 | B302: 23.5 | C302: -5.1934 | D302: 0.0038 | E302: 0 | F302: 0.0038 | G302: 0.8578 | H302: N/A
A303: 283 | B303: 23.5833 | C303: -4.0917 | D303: 0.0038 | E303: 0 | F303: 0.0038 | G303: 0.8578 | H303: N/A
A304: 284 | B304: 23.6667 | C304: -4.5116 | D304: 0.0038 | E304: 0 | F304: 0.0038 | G304: 0.8578 | H304: N/A
... A307: 287 | B307: 23.9167 | C307: -4.4583 | D307: 0.0038 | E307: 0 | F307: 0.0038 | G307: 0.8578 | H307: N/A
A308: 288 | B308: 24 | C308: 1.2728 | D308: 0.0038 | E308: 0.8578 | F308: 0.8616 | G308: 0 | H308: 1.4772
A309: 289 | B309: 24.0833 | C309: -2.7402 | D309: 0 | E309: 0 | F309: 0 | G309: 0 | H309: N/A
A310: 290 | B310: 24.1667 | C310: -1.8404 | D310: 0 | E310: 0 | F310: 0 | G310: 0 | H310: N/A
A311: 291 | B311: 24.25 | C311: -3.8634 | D311: 0 | E311: 0 | F311: 0 | G311: 0 | H311: N/A
A312: 292 | B312: 24.3333 | C312: -1.996 | D312: 0 | E312: 0 | F312: 0 | G312: 0 | H312: N/A
A313: 293 | B313: 24.4167 | C313: -3.174 | D313: 0 | E313: 0 | F313: 0 | G313: 0 | H313: N/A
A314: 294 | B314: 24.5 | C314: -4.9107 | D314: 0 | E314: 0 | F314: 0 | G314: 0 | H314: N/A
A315: 295 | B315: 24.5833 | C315: -3.4865 | D315: 0 | E315: 0 | F315: 0 | G315: 0 | H315: N/A
A316: 296 | B316: 24.6667 | C316: -4.0471 | D316: 0 | E316: 0 | F316: 0 | G316: 0 | H316: N/A
A317: 297 | B317: 24.75 | C317: -4.5317 | D317: 0 | E317: 0 | F317: 0 | G317: 0 | H317: N/A
A318: 298 | B318: 24.8333 | C318: -7.8842 | D318: 0 | E318: 0 | F318: 0 | G318: 0 | H318: N/A
A319: 299 | B319: 24.9167 | C319: -5.4537 | D319: 0 | E319: 0 | F319: 0 | G319: 0 | H319: N/A
A320: 300 | B320: 25 | C320: -5.8304 | D320: 0 | E320: 0 | F320: 0 | G320: 0 | H320: N/A

Sheet Stress Test
A1: Stress Test — Tornado Analysis & Scenario Analysis
A2: DK1 Primary | Base case NPV P50 = 3,732 EURk
A3: TORNADO ANALYSIS — ONE-WAY SENSITIVITY (+-20%)
A4: Input | B4: Base Value | C4: NPV Low (-20%) | D4: NPV High (+20%) | E4: Range (EURk) | F4: Change Low vs Base | G4: Change High vs Base
A5: NCF (%) | B5: 0.1223 | C5: -2930 | D5: 10392 | E5: 13321 | F5: -6662 | G5: 6659
A6: CAPEX (EURk) | B6: 23000 | C6: 8332 | D6: -868 | E6: 9200 | F6: 4600 | G6: -4600
A7: OU mu (EUR/MWh) | B7: 68.2947 | C7: 98 | D7: 7320 | E7: 7222 | F7: -3634 | G7: 3587
A8: PPA Price (EUR/MWh) | B8: 45 | C8: 605 | D8: 6859 | E8: 6254 | F8: -3127 | G8: 3127
A9: Alpha end (%) | B9: 0.2 | C9: 5086 | D9: 2370 | E9: 2716 | F9: 1353 | G9: -1363
A10: WACC_PPA,m | B10: 0.0028 | C10: 5104 | D10: 2440 | E10: 2664 | F10: 1372 | G10: -1292
A11: WACC_merchant,m | B11: 0.0036 | C11: 4551 | D11: 2981 | E11: 1570 | F11: 819 | G11: -751
A12: OU sigma (EUR/MWh) | B12: 17.5069 | C12: 3790 | D12: 3644 | E12: 146 | F12: 57 | G12: -89
A15: SCENARIO ANALYSIS
A16: Scenario | B16: NPV P50 (EURk) | C16: vs Base Case (EURk) | D16: vs Base Case (%)
A17: Optimistic | B17: 16496 | C17: 12764 | D17: 3.4197
A18: Base Case | B18: 3732 | C18: 0 | D18: 0
A19: Pessimistic | B19: -7461 | C19: -11193 | D19: -2.999

Sheet Output
A1: Output Summary — Valuation of Renewable Energy Assets under Power Price Uncertainty | DK1 Primary Specification
A2: 50MW Danish Solar PV | 25-Year Project Life | PPA 10 years @ 45.0 EUR/MWh | CAPEX 23,000 EURk | NCF 12.2%
A4: 1. OU CALIBRATION PARAMETERS — DK1 PRIMARY
A5: Parameter | B5: DK1 ex-2022 (Primary) | C5: DK1 Post-crisis | D5: DK2 ex-2022 | E5: DK2 Post-crisis | F5: Unit
A6: Long-run mean (mu) | B6: 68.2947 | C6: 77.6851 | D6: 67.3754 | E6: 77.2663 | F6: EUR/MWh
A7: Mean reversion (kappa) | B7: 0.1401 | C7: 0.5931 | D7: 0.1928 | E7: 0.7383 | F7: /month
A8: Volatility (sigma) | B8: 17.5069 | C8: 16.815 | D8: 19.3572 | E8: 18.0415 | F8: EUR/MWh
A9: Half-life | B9: 4.9486 | C9: 1.1687 | D9: 3.5948 | E9: 0.9388 | F9: months
A11: 2. MONTE CARLO SIMULATION — DK1 PRIMARY (10,000 paths)
A12: Horizon | B12: P50 (EUR/MWh) | C12: P90 (EUR/MWh) | D12: P99 (EUR/MWh) | E12: mu_capture (EUR/MWh)
A13: Year 5 | B13: 62.42 | C13: 19.97 | D13: -14.85 | E13: 62.86
A14: Year 10 | B14: 60.67 | C14: 18.27 | D14: -17.66 | E14: 60.8 | F14: <- PPA expiry
A15: Year 15 | B15: 58.52 | C15: 16.52 | D15: -15.45 | E15: 58.75
A16: Year 20 | B16: 57.43 | C16: 14.71 | D16: -19.55 | E16: 56.69
A17: Year 25 | B17: 54.79 | C17: 12.55 | D17: -22.5 | E17: 54.64
A19: 3. NPV RESULTS — SEGMENTED vs SINGLE WACC
A20: Scenario | B20: NPV Segmented WACC (EURk) | C20: NPV Single WACC (EURk) | D20: Difference (EURk) | E20: Difference (%) | F20: Interpretation
A21: P50 | B21: 3732 | C21: 2890 | D21: -842 | E21: -0.2256 | F21: Base case — project marginally viable
A22: P90 | B22: 9 | C22: -698 | D22: -707 | E22: -78.5556 | F22: Conservative downside — project loss-making
A23: P99 | B23: -3044 | C23: -3629 | D23: -585 | E23: -0.1922 | F23: Extreme stress — significant loss
A25: 4. DEBT SIZING — P90 PRIMARY | DSCR_min PPA=1.20x | Merchant=1.35x
A26: Scenario | B26: Debt Quantum (EURk) | C26: Gearing (D/CAPEX) | D26: LLCR | E26: Min DSCR PPA | F26: Min DSCR Merchant
A27: P50 (reference) | B27: 19541 | C27: 0.8496 | D27: 1.27 | E27: 1.2 | F27: 1.35
A28: P90 (primary) | B28: 11164 | C28: 0.4854 | D28: 1.21 | E28: 1.2
A29: P99 (stress) | B29: 10255 | C29: 0.4459 | D29: 1.2 | E29: 1.2
A31: Debt Capacity Contraction (P50 -> P90): | B31: -0.4287
A32: Debt Capacity Contraction (P50 -> P99): | B32: -0.4752
A34: 5. STRESS TEST — TOP 5 SENSITIVITIES & SCENARIO ANALYSIS
A35: Input | B35: NPV Low (-20%) (EURk) | C35: NPV Base (EURk) | D35: NPV High (+20%) (EURk) | E35: Range (EURk) | F35: Rank
A36: NCF (%) | B36: -2930 | C36: 3732 | D36: 10392 | E36: 13321 | F36: 1
A37: CAPEX (EURk) | B37: 8332 | C37: 3732 | D37: -868 | E37: 9200 | F37: 2
A38: OU mu (EUR/MWh) | B38: 98 | C38: 3732 | D38: 7320 | E38: 7222 | F38: 3
A39: PPA Price (EUR/MWh) | B39: 605 | C39: 3732 | D39: 6859 | E39: 6254 | F39: 4
A40: Alpha end (%) | B40: 5086 | C40: 3732 | D40: 2370 | E40: 2716 | F40: 5
A42: Scenario | B42: NPV P50 (EURk) | C42: vs Base (EURk) | D42: vs Base (%)
A43: Optimistic | B43: 16496 | C43: 12764 | D43: 3.4198
A44: Base Case | B44: 3732 | C44: 0 | D44: 0
A45: Pessimistic | B45: -7461 | C45: -11193 | D45: -2.9989
A47: 6. KEY THESIS FINDINGS
A48: Finding 1 | B48: Segmented WACC framework produces higher NPV than single WACC (difference: -842 EURk at P50). Single WACC systematically overestimates the discount rate applied to contracted PPA cash flows, leading to systematic undervaluation.
A49: Finding 2 | B49: Merchant tail risk causes significant debt capacity contraction of 42.9% from P50 to P90. A lender using P50 to size debt would over-leverage the project. P90 is the appropriate conservative basis for debt sizing in non-recourse project finance.
A50: Finding 3 | B50: NCF (capacity factor) is the primary value driver (sensitivity range: 13,321 EURk), followed by long-run mean price mu (9,200 EURk). OU volatility sigma has negligible NPV impact (146 EURk) — volatility affects risk distribution, not expected value.
A51: Finding 4 | B51: P50 NPV = 3,732 EURk under segmented WACC. P99 NPV = -3,044 EURk under extreme merchant stress. The segmented WACC framework reveals a valuation gap that a single blended WACC would obscure, with material implications for both equity valuation and debt capacity assessment.
